Workbook

Sheet Copy of Kertas Kerja
A1: No | B1: Nama Layanan | C1: Tujuan dan Fungsi Layanan | D1: Dasar Hukum Layanan | E1: SOP / Proses Bisnis Layanan | F1: Referensi Layanan | G1: Target Layanan | H1: Data yang dimasukan | I1: Data yang dihasilkan | J1: Sifat Data | K1: Data Pribadi | L1: Interval update data yang dihasilkan | M1: Aplikasi Pendukung | N1: Pengembang | O1: Pemilik | P1: Platform | Q1: Alamat Aplikasi | R1: Kategori Akses | S1: Jenis Aplikasi | T1: Tahun Pembuatan | U1: Status Aplikasi | V1: Telah Terintegrasi | W1: Terintegrasi dengan Aplikasi | X1: Mekanisme Integrasi | Y1: Frekuensi Sinkronisasi | Z1: Bidang / Unit Kerja | AA1: OPD | AB1: Nama | AC1: No. HP | AD1: Email
A2: 1 | B2: 2 | C2: 3 | D2: 4 | E2: 5 | F2: 6 | G2: 7 | H2: 8 | I2: 9 | J2: 10 | K2: 11 | L2: 12 | M2: 13 | N2: 14 | O2: 15 | P2: 16 | Q2: 17 | R2: 18 | S2: 19 | T2: 20 | U2: 21 | V2: 22 | W2: 23 | X2: 24 | Y2: 25 | Z2: 26 | AA2: 27 | AB2: 28 | AC2: 29 | AD2: 30
A3: Panduan | B3: Isikan dengan nama layanan yang selenggarakan | C3: Isikan dengan tujuan dan fungsi diselenggarakan layanan | D3: Isikan dengan dasar hukum penyelenggaraan layanan (Isikan dengan peraturan tingkat daerah, jika tidak ada dapat mengacu ke peraturan tingkat pusat) | E3: isikan dengan link dokumen berbentuk pdf terkait SOP / Proses Bisnis layanan | F3: Isikan referensi layanan sesuai daftar (Isikan dengan referensi layanan yang mendekati, dapat dilihat pada sheet referensi) | G3: Isikan dengan penerima layanan | H3: Isikan dengan input data | I3: Isikan dengan output data | J3: Isikan dengan sifat data | K3: Apakah terdapat Data Pribadi yang digunakan ? | L3: Pemutakhiran data hasil dari proses layanan | M3: Masukan nama aplikasi pendukung layanan, jika tidak ada maka isikan dengan "Belum terdapat aplikasi" | N3: Isikan dengan pengembang aplikasi | O3: Isikan dengan pemilik aplikasi | P3: Isikan dengan platform aplikasi | Q3: Isikan dengan alamat akses aplikasi, jika berbasis mobile isikan dengan link download | R3: Isikan dengan metode akses aplikasi | S3: Isikan dengan jenis aplikasi, informasi untuk satu arah, transaksi untuk dua arah) | T3: Isikan dengan tahun pembuatan | U3: Isikan dengan status aplikasi | V3: Apakah aplikasi telah terintegrasi ? | W3: Terintegrasi dengan aplikasi ? (Isikan dengan nama aplikasi, jika tidak isikan Tidak Terintegrasi | X3: Bagaimana proses integrasi berlangsung ? | Y3: Berapa lama integrasi data/layanan mutakhirkan ? | Z3: Isikan dengan unit kerja pelaksana layanan | AA3: Isikan dengan OPD pelaksana layanan | AB3: Isikan dengan Nama PIC pelaksana layanan | AC3: Isikan dengan nomor kontak pelaksana layanan | AD3: Isikan dengan email pelaksana layanan
A4: Contoh | B4: Layanan Pengaduan Masyarakat | C4: Layanan Pengaduan Masyarakat (LPM) adalah wadah atau sistem yang disediakan oleh instansi pemerintah (atau lembaga publik lainnya) bagi masyarakat untuk menyampaikan keluhan, saran, masukan, aspirasi, hingga laporan atas dugaan penyimpangan atau maladministrasi dalam penyelenggaraan pemerintahan dan pelayanan publik. | D4: Undang-Undang Nomor 25 Tahun 2009 tentang Pelayanan Publik | E4: abcd.pdf | F4: PENINGKATAN KUALITAS PELAYANAN PUBLIK | G4: Masyarakat | H4: Data Pengguna, Data Adun | I4: Data Aduan Masyarakat | J4: Tertutup | K4: Terdapat | L4: Harian | M4: SP4N Lapor | N4: Pusat | O4: Pusat | P4: Website dan Mobile | Q4: https://lapor.go.id/ | R4: Secara Online | S4: Transaksi | T4: 2018 | U4: Aktif | V4: Tidak | W4: Tidak Terintegrasi | X4: Tidak Terintegrasi | Y4: Tidak Terintegrasi | Z4: Bidang Informasi Komunikasi Publik | AA4: Diskominfo | AB4: Rima Diani, S.Si.Kom | AC4: 123 | AD4: rima@bandungkab.go.id
A5: Contoh | B5: Layanan Call center 112 | C5: Layanan Nomor Panggilan Darurat 112 merupakan layanan yang dapat digunakan saat terjadi keadaan darurat dengan menghubungi nomor 112 (Bebas Pulsa) yang akan terhubung dengan Pusat Panggilan Darurat (Call Center 112) yang dibangun oleh pemerintah daerah | D5: Permenkominfo 10/2016 tentang Layanan Nomor Tunggal Panggilan Darurat dan Keputusan Dirjen PPI 112/2019 tentang Pedoman Teknis Penyediaan Layanan Nomor Panggilan Darurat 112. | E5: Belum Tersedia | F5: PENINGKATAN KUALITAS PELAYANAN PUBLIK | G5: Masyarakat | H5: Data Pelapor dan Kejadian | I5: Data Laporan Kedaruratan | J5: Terbuka | K5: Terdapat | L5: Harian | M5: Sakti112 | N5: Pihak Ke 3 | O5: Pihak Ke 3 (Lisensi) | P5: Website | Q5: https://kabbandungv2.sakti112.id/ | R5: Secara Online | S5: Informasi | T5: 2023 | U5: Aktif | V5: Ya | W5: Tersedia untuk di integrasi ke aplikasi lain dan sudah dicoba ke aplikasi APAR milik disdamkar | X5: API | Y5: Lainnya | Z5: Bidang Informasi Komunikasi Publik | AA5: Diskominfo | AB5: Gugun | AC5: 456 | AD5: gugun@bandungkab.go.id
A6: 1 | B6: Layanan Data | C6: Pengelolaan Data Statistik Sektoral untuk pemanfaatan data melalui Portal Satu Data | D6: Perbup Simasda | F6: PENGELOLAAN DATA STATISTIK | G6: Masyarakat | H6: Data Statistik Sektoral yang bersumber dari produsen data/OPD | I6: Daftar Data Hasil Kegiatan Statistik di OPD yang tersaji pada portal satu data | J6: Terbuka | K6: Tidak terdapat | L6: Tahunan | M6: Simasda dan Portal Satu Data | N6: Diskominfo | O6: Kab. Bandung | P6: Website | Q6: https://simasda.bandungkab.go.id/ dan https://satudata.bandungkab.go.id/ | R6: Secara Online | S6: Informasi | T6: 2019 | U6: Aktif | V6: Ya | W6: Open data Provinsi Jawa Barat dan Satu Data Indonesia | X6: API | Y6: Tahunan | Z6: Bidang Statistik | AA6: Diskominfo | AB6: Nyimas Ayu Kikie Zakiyah | AC6: 0813-2184-5099 | AD6: kikiezaki72@gmail.com
A7: 2 | B7: Layanan Pembangunan dan Pengembangan Aplikasi | C7: Bertujuan untuk menjadi fasilitator dalam membangun dan mengembangkan aplikasi dpada Perangkat Daerah | F7: PENATAKELOLAAN APLIKASI INFORMATIKA | G7: Instansi Pemerintah Lainnya | H7: Permohonan Pembangunan dan Pengembangan Aplikasi dari OPD
A8: 3 | B8: Layanan Akses dan Kualitas Informasi Publik Pemerintah Daerah | C8: Bertujuan untuk menghitung indeks Layanan Akses dan Kualitas Informasi Publik Pemerintah Daerah | F8: PENGELOLAAN INFORMASI PUBLIK | G8: Masyarakat
A9: 4 | B9: Layanan Penerbitan Tanda Tangan Elektronik | C9: Sebagai Fasilitator dalam pelayanan penerbitan tanda tangan elektronik | F9: MANAJEMEN KEAMANAN INFORMASI | G9: Pegawai
A10: 5
A11: 6
A12: 7
A13: 8
A14: 9
A15: 10
A16: 11
A17: 12
A18: 13
A19: 14
A20: 15
A21: 16
... A55: 50

Sheet Ref
A1: No | B1: Nama Layanan | C1: Tujuan dan Fungsi Layanan | D1: Dasar Hukum Layanan | E1: SOP / Proses Bisnis Layanan | F1: REFERENSI LAYANAN | G1: Target Layanan | H1: Data yang dimasukan | I1: Data yang dihasilkan | J1: Sifat Data | K1: Data Pribadi | L1: Interval update data yang dihasilkan | M1: Aplikasi Pendukung | N1: Pengembang | O1: Pemilik | P1: Platform | Q1: Alamat Aplikasi | R1: Kategori Akses | S1: Jenis Aplikasi | T1: Tahun Pembuatan | U1: Status Aplikasi | V1: Telah Terintegrasi | W1: Terintegrasi dengan Aplikasi | X1: Mekanisme Integrasi | Y1: Frekuensi Sinkronisasi | Z1: Bidang | AA1: OPD | AB1: Nama | AC1: No. HP | AD1: Email | AF1: JUMLAH LAYANAN | AG1: JUMLAH APLIKASI
E2: Tersedia | F2: STRATEGI PERTAHANAN | G2: Pelaku Bisnis | J2: Terbuka | K2: Terdapat | L2: Harian | N2: Pusat | O2: Pusat | P2: Website | R2: Secara Online | S2: Informasi | U2: Aktif | V2: Ya | X2: API | Y2: Realtime | AA2: Setda
E3: Tidak Tersedia | F3: PERENCANAAN PERTAHANAN | G3: Masyarakat | J3: Tertutup | K3: Tidak terdapat | L3: Mingguan | N3: Provinsi | O3: Provinsi | P3: Mobile | R3: Secara Offline | S3: Transaksi | U3: Non Aktif | V3: Tidak | X3: Web Service | Y3: Harian | AA3: Setwan
F4: POTENSI PERTAHANAN | G4: Pegawai | J4: Terbatas | L4: Bulanan | N4: Diskominfo | O4: Kab. Bandung | P4: Desktop | U4: Maintenance | X4: Database to Database | Y4: Mingguan | AA4: Inspektorat
F5: KEKUATAN PERTAHANAN | G5: Instansi Pemerintah Lainnya | J5: Rahasia | L5: Tahunan | N5: OPD | O5: Pihak Ke 3 (Lisensi) | P5: Website dan Mobile | X5: Manual | Y5: Bulanan | AA5: Disdik
F6: PENYELENGGARAAN HUBUNGAN LUAR NEGERI DAN POLITIK LUAR NEGERI | L6: Lainnya | N6: Pihak Ke 3 | X6: Tidak Terintegrasi | Y6: Tahunan | AA6: Dinkes
F7: HUKUM DAN PERJANJIAN INTERNASIONAL | Y7: Lainnya | AA7: DPUTR
F8: INFORMASI DAN DIPLOMASI PUBLIK | Y8: Tidak Terintegrasi | AA8: Disperkimtan
F9: PROTOKOL DAN KONSULER | AA9: Dinsos
F10: PELINDUNGAN WNI | AA10: Disnaker
F11: FASILITAS DIPLOMATIK | AA11: DP2KBP3A
F12: PENINGKATAN DAYA SAING DAN KEMANDIRIAN INDUSTRI | AA12: DLH
F13: PENGUATAN IMPLEMENTASI MAKING INDONESIA 4 | AA13: Disdukcapil
F14: PENINGKATAN KEMAMPUAN INDUSTRI BARANG DAN JASA SERTA INDUSTRI HALAL DALAM NEGERI | AA14: DPMD
F15: PERLUASAN PENGUASAAN PASAR INDUSTRI | AA15: Dishub
F16: PENGUATAN KEWIRAUSAHAAN DAN INDUSTRI KECIL DAN MENENGAH | AA16: Diskominfo
F17: PEMERATAAN PERSEBARAN INDUSTRI | AA17: DPMPTSP
F18: PENGELOLAAN INDUSTRI KREATIF | AA18: Dispora
F19: PENGUATAN DAN PENGEMBANGAN PERDAGANGAN DALAM NEGERI | AA19: Disperdagin
F20: PENGUATAN PERDAGANGAN LUAR NEGERI | AA20: Distan
... F33: PENGEMBANGAN KELEMBAGAAN PETANI | AA33: BPBD
F34: PENGELOLAAN STANDARDISASI DAN PENILAIAN KESESUAIAN KOMODITAS TANAMAN PANGAN DAN HORTIKULTURA
F35: PENGELOLAAN STANDARDISASI DAN PENILAIAN KESESUAIAN PASCA PANEN TANAMAN PANGAN DAN HORTIKULTURA
F36: PENGELOLAAN STANDARDISASI DAN PENILAIAN KESESUAIAN PRASARANA DAN SARANA TANAMAN PANGAN DAN HORTIKULTURA
F37: PENGELOLAAN REKOMENDASI KEBIJAKAN SOSIAL EKONOMI PEMBANGUNAN TANAMAN PANGAN DAN HORTIKULTURA
F38: PENGELOLAAN LAHAN PERTANIAN
F39: PENGELOLAAN PUPUK DAN PESTISIDA
F40: PENGELOLAAN IRIGASI PERTANIAN, KONSERVASI AIR DAN LINGKUNGAN HIDUP
F41: PENGELOLAAN ALAT DAN MESIN PERTANIAN
F42: PENGELOLAAN PEMBIAYAAN TANAMAN PANGAN DAN HORTIKULTURA
F43: PENGELOLAAN LAYANAN PERIZINAN BERUSAHA BIDANG PERTANIAN DAN PERLINDUNGAN VARIETAS TANAMAN
F44: KETERSEDIAN PANGAN
F45: STABILITAS PASOKAN DAN HARGA PANGAN
... F307: PENGELOLAAN PELAYANAN KESEHATAN

Sheet Kertas Kerja - All
A1: No | B1: Nama Layanan | C1: Pemilik Layanan | D1: Tujuan dan Fungsi Layanan | E1: Dasar Hukum Layanan | F1: SOP / Proses Bisnis Layanan | G1: Referensi Layanan | H1: Target Layanan | I1: Data yang dimasukan | J1: Data yang dihasilkan | K1: Sifat Data | L1: Data Pribadi | M1: Interval update data yang dihasilkan | N1: Aplikasi Pendukung | O1: Pengembang | P1: Pemilik | Q1: Platform | R1: Alamat Aplikasi | S1: Kategori Akses | T1: Jenis Aplikasi | U1: Tahun Pembuatan | V1: Status Aplikasi | W1: Telah Terintegrasi | X1: Terintegrasi dengan Aplikasi | Y1: Mekanisme Integrasi | Z1: Frekuensi Sinkronisasi | AA1: Bidang / Unit Kerja | AB1: OPD | AC1: Nama | AD1: No. HP | AE1: Email | AF1: Keterkaitan 58 Rencana Aksi | AG1: Frekuensi Penggunaan Aplikasi | AH1: TA
A2: 1 | B2: 2 | D2: 3 | E2: 4 | F2: 5 | G2: 6 | H2: 7 | I2: 8 | J2: 9 | K2: 10 | L2: 11 | M2: 12 | N2: 13 | O2: 14 | P2: 15 | Q2: 16 | R2: 17 | S2: 18 | T2: 19 | U2: 20 | V2: 21 | W2: 22 | X2: 23 | Y2: 24 | Z2: 25 | AA2: 26 | AB2: 27 | AC2: 28 | AD2: 29 | AE2: 30 | AF2: 31 | AG2: 32 | AH2: 33
A3: Panduan | B3: Isikan dengan nama layanan yang selenggarakan | D3: Layanan Pengaduan Masyarakat (LPM) adalah wadah atau sistem yang disediakan oleh instansi pemerintah (atau lembaga publik lainnya) bagi masyarakat untuk menyampaikan keluhan, saran, masukan, aspirasi, hingga laporan atas dugaan penyimpangan atau maladministrasi dalam penyelenggaraan pemerintahan dan pelayanan publik. | E3: Isikan dengan dasar hukum penyelenggaraan layanan (Isikan dengan peraturan tingkat daerah, jika tidak ada dapat mengacu ke peraturan tingkat pusat) | F3: isikan dengan link dokumen berbentuk pdf terkait SOP / Proses Bisnis layanan | G3: Isikan referensi layanan sesuai daftar (Isikan dengan referensi layanan yang mendekati, dapat dilihat pada sheet referensi) | H3: Isikan dengan penerima layanan | I3: Isikan dengan input data | J3: Isikan dengan output data | K3: Isikan dengan sifat data | L3: Apakah terdapat Data Pribadi yang digunakan ? | M3: Pemutakhiran data hasil dari proses layanan | N3: Masukan nama aplikasi pendukung layanan, jika tidak ada maka isikan dengan "Belum terdapat aplikasi" | O3: Isikan dengan pengembang aplikasi | P3: Isikan dengan pemilik aplikasi | Q3: Isikan dengan platform aplikasi | R3: Isikan dengan alamat akses aplikasi, jika berbasis mobile isikan dengan link download | S3: Isikan dengan metode akses aplikasi | T3: Isikan dengan jenis aplikasi, informasi untuk satu arah, transaksi untuk dua arah) | U3: Isikan dengan tahun pembuatan | V3: Isikan dengan status aplikasi | W3: Apakah aplikasi telah terintegrasi ? | X3: Terintegrasi dengan aplikasi ? (Isikan dengan nama aplikasi, jika tidak isikan Tidak Terintegrasi | Y3: Bagaimana proses integrasi berlangsung ? | Z3: Berapa lama integrasi data/layanan mutakhirkan ? | AA3: Isikan dengan unit kerja pelaksana layanan | AB3: Isikan dengan OPD pelaksana layanan | AC3: Isikan dengan Nama PIC pelaksana layanan | AD3: Isikan dengan nomor kontak pelaksana layanan | AE3: Isikan dengan email pelaksana layanan | AF3: Isikan keterkaitan layanan/probis/data dengan 58 Rencana Aksi. Sebutkan nomor rencana aksi tersebut. | AG3: Isikan sesuai dengan frekuensi penggunaan aplikasi. Harian / Mingguan / Bulanan / Tahunan / Insidentil
A4: Contoh | B4: Layanan Pengaduan Masyarakat | E4: Undang-Undang Nomor 25 Tahun 2009 tentang Pelayanan Publik | F4: abcd.pdf | G4: PENINGKATAN KUALITAS PELAYANAN PUBLIK | H4: Masyarakat | I4: Data Pengguna, Data Adun | J4: Data Aduan Masyarakat | K4: Tertutup | L4: Terdapat | M4: Harian | N4: SP4N Lapor | O4: Pusat | P4: Pusat | Q4: Website dan Mobile | R4: https://lapor.go.id/ | S4: Secara Online | T4: Transaksi | U4: 2018 | V4: Aktif | W4: Tidak | X4: Tidak Terintegrasi | Y4: Tidak Terintegrasi | Z4: Tidak Terintegrasi | AA4: Bidang Informasi Komunikasi Publik | AB4: Diskominfo | AC4: Rima Diani, S.Si.Kom | AD4: 123 | AE4: rima@bandungkab.go.id | AF4: 28 | AG4: Harian
A5: Diskominfo
A6: 1 | B6: Layanan Penerbitan Sertifikasi Elektronik | C6: Diskominfo | D6: layanan bagi para pejabat, Kepala Sekolah, dan Kepala Desa untuk memproleh Tanda tangan digital yang tersertifikasi BSSN | G6: MANAJEMEN KEAMANAN INFORMASI | H6: Instansi Pemerintah Lainnya | I6: Data Tanda Tangan Elektronik | J6: Data Tanda Tangan Elektronik | K6: Terbatas | M6: Tahunan | AA6: Persandian | AB6: Diskominfo
A7: 2 | B7: Layanan Radio Kandaga | C7: Diskominfo | D7: layanan bagi para pembicara yang telah menyampaiakan informasi melalui Podcast Radio Kandaga | G7: PENYIARAN RADIO PUBLIK | I7: Data Siaran atau Podcast | J7: Data Siaran atau Podcast | K7: Terbuka | M7: Tahunan | N7: KANDAGA | Q7: Mobile | R7: https://play.google.com/store/apps/details?id=com.diskominfo.radiokandagabedas&pcampaignid=web_share | AA7: Penyelenggaraan Informasi dan Komunikasi Publik | AB7: Diskominfo
A8: 3 | B8: Layanan Data Statisktik Sektoral | C8: Diskominfo | D8: memudahkan pengambilan keputusan yang akurat dari instansi pemerintah terkait, dapat dilakukan dengan pengujian terhadap system dan data sebelumnya dengan pembuatan aplikasi atau system informasi versi beta untuk menghasilkan analisa yang tepat serta sasaran yang akurat dari produk yang akan dihasilkan melalui produk kompilasi, produk survey, produk komparasi dan produk lainnya baik dari data sektoral suatu daerah yang akan digunakan nantinya untun meminimalisir masalah yang ada | G8: PENGELOLAAN DATA STATISTIK | H8: Instansi Pemerintah Lainnya | I8: Data Statistik Sektoral | J8: Data Statistik Sektoral | K8: Terbuka | M8: Tahunan | N8: SIMASDA | Q8: Website | R8: https://simasda.bandungkab.go.id/ | AA8: Statistik | AB8: Diskominfo
A9: 4 | B9: Layanan Domain dan Sub Domain | C9: Diskominfo | D9: membangun branding Pemerintah Kabupaten Bandung yaitu bandungkab.go.id | G9: PENATAKELOLAAN APLIKASI INFORMATIKA | H9: Masyarakat | I9: Data Domain dan Sub Domain | J9: Data Domain dan Sub Domain | K9: Terbatas | M9: Tahunan | AA9: TIK | AB9: Diskominfo
A10: 5 | B10: Layanan Cpanel | C10: Diskominfo | D10: menyelenggarakan website Desa dan Website SMP | G10: PENATAKELOLAAN APLIKASI INFORMATIKA | H10: Masyarakat | I10: Data Cpanel | J10: Data Cpanel | K10: Terbatas | M10: Tahunan | AA10: TIK | AB10: Diskominfo
A11: 6 | B11: Layanan SSL | C11: Diskominfo | D11: mengamankan lalu lintas data dari domain bandungkab.go.id beserta subdomainnya | G11: MANAJEMEN KEAMANAN INFORMASI | H11: Masyarakat | I11: Data SSL | J11: Data SSL | K11: Terbatas | M11: Tahunan | AA11: TIK | AB11: Diskominfo
A12: 7 | B12: Layanan Pengembangan Aplikasi | C12: Diskominfo | D12: Layanan Pengembangan Aplikasi: Menyediakan pembuatan aplikasi sesuai kebutuhan pemerintah daerah. | G12: PENATAKELOLAAN APLIKASI INFORMATIKA | H12: Instansi Pemerintah Lainnya | I12: Data Aplikasi | J12: Data Aplikasi | K12: Terbatas | M12: Tahunan | AA12: TIK | AB12: Diskominfo
A13: 8 | B13: Layanan Pembinaan dan Fasilitasi KIM | C13: Diskominfo | D13: Layanan Pembinaan dan Fasilitasi KIM: Mendorong pengembangan kawasan industri melalui pembinaan dan fasilitasi. | G13: PEMBERDAYAAN DAN PERAN MASYARAKAT | H13: Instansi Pemerintah Lainnya | I13: Data Peserta KIM | J13: Data Peserta KIM | K13: Terbatas | M13: Tahunan | N13: KIM | Q13: Website | R13: https://kimonline.bandungkab.go.id/ kim/ | AB13: Diskominfo
A14: 9 | B14: Layanan Informasi Publik Pejabat Pelaksana Informasi dan Dokumentasi (PPID) | C14: Diskominfo | D14: Layanan Informasi Publik PPID: Memberikan akses informasi publik dan dokumen pemerintah melalui pejabat pelaksana. | G14: PENGELOLAAN INFORMASI PUBLIK | H14: Instansi Pemerintah Lainnya | I14: Data PPID | J14: Data PPID | K14: Terbuka | M14: Bulanan | N14: PPID | Q14: Website | R14: http://ppid.bandungkab.go.id/ | AB14: Diskominfo
A15: 10 | B15: Layanan Helpdesk TIK | C15: Diskominfo | D15: Layanan Helpdesk TIK: Menyediakan bantuan dan dukungan teknis dalam penggunaan teknologi informasi dan komunikasi. | G15: PENATAKELOLAAN APLIKASI INFORMATIKA | H15: Instansi Pemerintah Lainnya | I15: Data Helpdesk TIK | J15: Data Helpdesk TIK | K15: Terbatas | M15: Tahunan | AB15: Diskominfo
A16: 11 | B16: Layanan Pengelolaan Jaringan dan Keamanan TIK | C16: Diskominfo | D16: Layanan Pengelolaan Jaringan dan Keamanan TIK: Menyediakan pengelolaan jaringan dan keamanan sistem teknologi informasi. | G16: PENATAKELOLAAN APLIKASI INFORMATIKA | H16: Instansi Pemerintah Lainnya | I16: Data Jaringan dan Keamanan TIK | J16: Data Jaringan dan Keamanan TIK | K16: Terbatas | M16: Tahunan | AB16: Diskominfo
A17: 12 | B17: Layanan Portal Aplikasi | C17: Diskominfo | D17: Layanan Portal Aplikasi: Memberikan akses terpadu ke berbagai aplikasi pemerintah daerah. | G17: PENATAKELOLAAN APLIKASI INFORMATIKA | H17: Instansi Pemerintah Lainnya | I17: Data Portal Layanan | J17: Data Portal Layanan | K17: Terbuka | M17: Tahunan | N17: PORTAL KAB BANDUNG | Q17: Website | R17: https://bandungkab.go.id/ | AB17: Diskominfo
A18: 13 | B18: Layanan Publikasi Infromasi dan Berita | C18: Diskominfo | D18: Layanan Publikasi Informasi dan Berita: Menyajikan informasi dan berita terkini terkait pemerintahan daerah. | G18: MANAJEMEN KEAMANAN INFORMASI | H18: Masyarakat | I18: Data Publikasi Informasi dan Berita | J18: Data Publikasi Informasi dan Berita | K18: Terbuka | M18: Tahunan | AB18: Diskominfo
A19: 14 | B19: Layanan Diskusi Publik | C19: Diskominfo | D19: Layanan Diskusi Publik: Memberikan platform untuk diskusi dan partisipasi masyarakat dalam pengambilan keputusan. | G19: PENGELOLAAN KOMUNIKASI PUBLIK | H19: Masyarakat | I19: Data Diskusi Publik | J19: Data Diskusi Publik | K19: Terbatas | M19: Tahunan | AB19: Diskominfo
A20: 15 | B20: Layanan Pengaduan Masyarakat | C20: Diskominfo | D20: Layanan Pengaduan Masyarakat: Memfasilitasi masyarakat untuk menyampaikan keluhan dan pengaduan terkait pelayanan publik. | G20: PENINGKATAN KUALITAS PELAYANAN PUBLIK | H20: Masyarakat | I20: Data Aduan Masyarakat | J20: Data Aduan Masyarakat | K20: Terbuka | M20: Bulanan | N20: SP4N Lapor | AB20: Diskominfo
A21: 16 | B21: Layanan Smart CIty | C21: Diskominfo | D21: Layanan Smart City: Mengintegrasikan teknologi untuk meningkatkan efisiensi dan kualitas hidup warga dalam konteks perkotaan. | G21: PENINGKATAN KUALITAS PELAYANAN PUBLIK | H21: Masyarakat | I21: Data Smart City | J21: Data Smart City | K21: Terbuka | M21: Tahunan | N21: SMART CITY | Q21: Website | R21: https://smartcity.bandungkab.go.id/ | AB21: Diskominfo
A22: BAGIAN PERENCKEU
A23: 1 | B23: Layanan Sistem Informasi Tindak Lanjut Hasil Layanan Terpadu | C23: BAGIAN PERENCKEU | D23: Layanan Sistem Informasi Tindak Lanjut Hasil Layanan Terpadu mengacu pada sistem informasi berbasis web untuk mengelola dan memantau proses tindak lanjut (TL) hasil rekomendasi pemeriksaan oleh lembaga seperti Badan Pemeriksa Keuangan (BPK), agar prosesnya menjadi lebih efisien, transparan, dan akuntabel melalui digitalisasi data dan komunikasi online secara real-time antara BPK dan entitas yang diperiksa. | E23: Undang-Undang Nomor 25 Tahun 2009 tentang Pelayanan Publik, Peraturan Pemerintah Nomor 96 Tahun 2012 | G23: PENINGKATAN KUALITAS PELAYANAN PUBLIK | H23: Instansi Pemerintah Lainnya | I23: Data Evidence Tindak Lanjut yang Direkomendasikan | J23: Data Hasil Tindak Lanjut | K23: Terbatas | L23: Tidak terdapat | M23: Tahunan | N23: SIMASLAHAT | O23: Pihak Ke 3 | P23: Kab. Bandung | Q23: Website | R23: https://simaslahat.bandungkab.go.id | S23: Secara Online | T23: Transaksi | U23: 2022 | V23: Aktif | W23: Tidak | X23: Tidak Terintegrasi | Y23: Tidak Terintegrasi | Z23: Tidak Terintegrasi | AA23: Bagian Perencanaan dan Keuangan | AB23: Setda | AC23: VERRYNOVYANDI SADIKIN, SE., MM | AD23: 895327038135 | AE23: setdakab.bdg@gmail.com | AF23: - | AG23: Tahunan
A24: 2 | B24: Layanan Pengaduan Masyarakat | C24: BAGIAN PERENCKEU | D24: Layanan Pengaduan Masyarakat (LPM) adalah wadah atau sistem yang disediakan oleh instansi pemerintah (atau lembaga publik lainnya) bagi masyarakat untuk menyampaikan keluhan, saran, masukan, aspirasi, hingga laporan atas dugaan penyimpangan atau maladministrasi dalam penyelenggaraan pemerintahan dan pelayanan publik. | E24: Undang-Undang Nomor 25 Tahun 2009 tentang Pelayanan Publik | G24: PENINGKATAN KUALITAS PELAYANAN PUBLIK | H24: Masyarakat | I24: Data Pengguna, Data Adun | J24: Data Aduan Masyarakat | K24: Terbatas | L24: Terdapat | M24: Harian | N24: SP4N Lapor | O24: Pusat | P24: Pusat | Q24: Website | R24: https://lapor.go.id/ | S24: Secara Online | T24: Informasi | U24: 2018 | V24: Aktif | W24: Tidak | X24: Tidak Terintegrasi | Y24: Tidak Terintegrasi | Z24: Tidak Terintegrasi | AA24: Bidang Informasi Komunikasi Publik | AB24: Diskominfo | AC24: ALIPHIO DYAKSHA PUTRA, A.Md.Ak. | AD24: 8988005270 | AE24: setdakab.bdg@gmail.com | AF24: - | AG24: Insidentil
A25: 3 | B25: Layanan Data Sektoral | C25: BAGIAN PERENCKEU | D25: Layanan data sektoral adalah statistik yang dihasilkan oleh instansi pemerintah pusat atau daerah sesuai dengan tugas dan fungsi masing-masing, yang bertujuan untuk memenuhi kebutuhan internal instansi tersebut dalam penyelenggaraan pemerintahan dan pembangunan. | E25: PERATURAN BADAN PUSAT STATISTIK NOMOR 3 TAHUN 2022 TENTANG EVALUASI PENYELENGGARAAN STATISTIK SEKTORAL | G25: PENGELOLAAN DATA STATISTIK | H25: Instansi Pemerintah Lainnya | I25: Data Sektoral | J25: Data Sektoral | K25: Terbatas | L25: Tidak terdapat | M25: Tahunan | N25: SIMASDA | O25: Pihak Ke 3 | P25: Kab. Bandung | Q25: Website | R25: https://simasda.bandungkab.go.id/ | S25: Secara Online | T25: Informasi | U25: 2022 | V25: Aktif | W25: Ya | X25: Terintegrasi dengan Bedas, E-Walidata dan Satu Data Kab Bandung | Y25: Database to Database | Z25: Realtime | AA25: Bidang Statistik | AB25: Diskominfo | AC25: DHANTI AURILIA PRATIWI, M.Stat | AD25: 81904085710 | AE25: setdakab.bdg@gmail.com
A26: 4 | B26: Layanan Rekonsiliasi Pajak Pusat | C26: BAGIAN PERENCKEU | D26: Rekonsiliasi pajak pusat atas belanja daerah adalah proses penyesuaian atau pencocokan antara jumlah pajak yang harus dibayarkan oleh pemerintah daerah kepada pemerintah pusat dengan total belanja yang telah dilakukan oleh pemerintah daerah dalam kerangka Anggaran Pendapatan dan Belanja Daerah (APBD) | E26: PERBUP Nomor 165 Tahun 2021 dan PERBUP Nomor 289 Tahun 2022 | G26: AKUNTANSI DAN PELAPORAN KEUANGAN | H26: Instansi Pemerintah Lainnya | I26: Data Pajak Pusat (ID Billing & NTPN) | J26: Rekap Data Pajak Pusat | K26: Terbatas | L26: Tidak terdapat | M26: Bulanan | N26: SIREKON | O26: Diskominfo | P26: Kab. Bandung | Q26: Website | R26: https://sirekonpajak.bandungkab.go.id/ | S26: Secara Online | T26: Informasi | U26: 2020 | V26: Aktif | W26: Tidak | X26: Tidak Terintegrasi | Y26: Tidak Terintegrasi | Z26: Tidak Terintegrasi | AA26: Bagian Perencanaan dan Keuangan | AB26: Setda | AC26: VERRYNOVYANDI SADIKIN, SE., MM | AD26: 895327038135 | AE26: setdakab.bdg@gmail.com | AF26: - | AG26: Bulanan
A27: 5 | B27: Layanan Pajak | C27: BAGIAN PERENCKEU | D27: Fungsi layanan pajak meliputi pengumpulan pajak daerah, pengelolaan data wajib pajak, pengawasan kepatuhan, serta penyediaan kemudahan pembayaran menggunakan aplikasi digital yang mendukung optimalisasi penerimaan pajak dan peningkatan kualitas pelayanan kepada masyarakat. | E27: UU No. 1 Tahun 2022 | G27: AKUNTANSI DAN PELAPORAN KEUANGAN | H27: Instansi Pemerintah Lainnya | I27: Data Pajak | J27: ID Billing | K27: Terbatas | L27: Terdapat | M27: Harian | N27: Coretax | O27: Pusat | P27: Pusat | Q27: Website | R27: coretaxdjp.pajak.go.id | S27: Secara Online | T27: Informasi | U27: 2025 | V27: Aktif | W27: Tidak | X27: Tidak Terintegrasi | Y27: Tidak Terintegrasi | Z27: Tidak Terintegrasi | AA27: Bagian Perencanaan dan Keuangan | AB27: Setda | AC27: VERRYNOVYANDI SADIKIN, SE., MM | AD27: 895327038135 | AE27: setdakab.bdg@gmail.com | AF27: - | AG27: Harian
A28: 6 | B28: Layanan Pajak Daerah | C28: BAGIAN PERENCKEU | D28: Pajak daerah yang ada digunakan untuk membiayai semua kepentingan umum. Termasuk untuk membuka lapangan kerja baru, sehingga terjadi pemerataan pendapatan agar kesenjangan ekonomi antara yang kaya dan miskin tidak terlalu menonjol. Pajak daerah diharapkan dapat meningkatkan pemerataan di setiap daerah. | E28: Undang-Undang Nomor 28 Tahun 2009 tentang Pajak Daerah dan Retribusi Daerah (UU PDRD) | G28: AKUNTANSI DAN PELAPORAN KEUANGAN | H28: Instansi Pemerintah Lainnya | I28: Data Pajak Daerah | J28: Data Rekap Pajak Daerah | K28: Terbatas | L28: Tidak terdapat | M28: Harian | N28: E-SPTPD | O28: Diskominfo | P28: Kab. Bandung | Q28: Website | R28: https://e-sptpd.bandungkab.go.id/ | S28: Secara Online | T28: Informasi | U28: 2019 | V28: Aktif | W28: Tidak | X28: Tidak Terintegrasi | Y28: Tidak Terintegrasi | Z28: Tidak Terintegrasi | AA28: Bagian Perencanaan dan Keuangan | AB28: Setda, Bapenda | AC28: VERRYNOVYANDI SADIKIN, SE., MM | AD28: 895327038135 | AE28: setdakab.bdg@gmail.com | AF28: - | AG28: Harian
A29: 7 | B29: Layanan Transaksi | C29: BAGIAN PERENCKEU | D29: Fungsi utama layanan transaksi di Kabupaten Bandung adalah untuk memudahkan masyarakat dalam memenuhi kewajiban pembayaran pajak daerah dan mendukung efisiensi pengelolaan pajak oleh pemerintah daerah. Layanan ini meliputi berbagai fasilitas dan sistem, seperti pengesahan STNK, pembayaran PKB, dan pemanfaatan teknologi untuk pelaporan data transaksi usaha secara online. | E29: Peraturan Bupati (Perbup) Kabupaten Bandung Nomor 22 Tahun 2018 tentang Implementasi Transaksi Non Tunai, yang telah beberapa kali diubah dengan Perbup Nomor 6 Tahun 2020 dan Perbup Nomor 15 Tahun 2020. | G29: AKUNTANSI DAN PELAPORAN KEUANGAN | H29: Instansi Pemerintah Lainnya | I29: Data Transaksi | J29: Data Rekening Koran | K29: Terbatas | L29: Tidak terdapat | M29: Lainnya | N29: IBC (Internet Banking Corporate) | O29: Pihak Ke 3 | P29: Pihak Ke 3 (Lisensi) | Q29: Desktop | R29: Aplikasi dari BJB | S29: Secara Online | T29: Transaksi | U29: 2019 | V29: Aktif | W29: Tidak | X29: Tidak Terintegrasi | Y29: Tidak Terintegrasi | Z29: Tidak Terintegrasi | AA29: Bagian Perencanaan dan Keuangan | AB29: Setda | AC29: VERRYNOVYANDI SADIKIN, SE., MM | AD29: 895327038135 | AE29: setdakab.bdg@gmail.com | AF29: - | AG29: Harian
A30: 8 | B30: Layanan Penatausahaan Keuangan | C30: BAGIAN PERENCKEU | D30: Fungsi layanan penatausahaan keuangan di Kabupaten Bandung adalah mencatat dan menyimpan semua transaksi penerimaan dan pengeluaran kas daerah secara akurat dan tertib untuk penyusunan laporan keuangan, pengendalian APBD, serta penyediaan data dan informasi keuangan yang dapat dipertanggungjawabkan. Penatausahaan ini mendukung efektivitas pengelolaan keuangan daerah dan memastikan transparansi serta akuntabilitas dalam penggunaan dana publik. | E30: Peraturan Bupati (Perbup) Kabupaten Bandung Nomor 48 Tahun 2025 tentang Perubahan Atas Peraturan Bupati Nomor 83 Tahun 2024 | G30: AKUNTANSI DAN PELAPORAN KEUANGAN | H30: Instansi Pemerintah Lainnya | I30: Data APBD | J30: Data APBD | K30: Tertutup | L30: Terdapat | M30: Lainnya | N30: SIPD | O30: Pusat | P30: Pusat | Q30: Website | R30: SIPD.kemendagri.go.id | S30: Secara Online | T30: Transaksi | U30: 2021 | V30: Aktif | W30: Tidak | X30: Tidak Terintegrasi | Y30: Tidak Terintegrasi | Z30: Tidak Terintegrasi | AA30: Bagian Perencanaan dan Keuangan | AB30: Setda | AC30: VERRYNOVYANDI SADIKIN, SE., MM | AD30: 895327038135 | AE30: setdakab.bdg@gmail.com | AF30: - | AG30: Harian
A31: 10 | B31: Layanan Tata Naskah Dinas | C31: BAGIAN PERENCKEU | D31: Fungsi utama layanan Tata Naskah Dinas (TND) di Kabupaten Bandung adalah untuk menciptakan kelancaran komunikasi tertulis yang efektif dan efisien, memastikan keotentikan, keterpercayaan, kepastian, dan akuntabilitas informasi, serta mendukung terwujudnya tata kelola pemerintahan yang baik (good governance) melalui penerapan penggunaan naskah dinas secara elektronik. TND juga berfungsi sebagai sarana untuk mengatur jenis dan penyusunan naskah dinas, penggunaan lambang negara dan cap dinas, serta penggunaan bahasa Indonesia yang sesuai dalam komunikasi resmi. | E31: Peraturan Bupati (PERBUP) Nomor 82 Tahun 2024 tentang Pedoman Tata Naskah Dinas di Lingkungan Pemerintah Kabupaten Bandung. | G31: PENATAAN SISTEM TATA LAKSANA | H31: Instansi Pemerintah Lainnya | I31: Naskah Surat | J31: Surat yang dilegalisasi | K31: Terbatas | L31: Tidak terdapat | M31: Harian | N31: SULTAN (e-office) | O31: Diskominfo | P31: Kab. Bandung | Q31: Website dan Mobile | R31: https://sultan.bandungkab.go.id/ | S31: Secara Online | T31: Informasi | U31: 2025 | V31: Aktif | W31: Ya | X31: Terintegrasi dengan SIPPHADE, dll | Y31: Web Service | Z31: Realtime | AA31: Semua Bagian | AB31: Setda | AC31: ALIPHIO DYAKSHA PUTRA, A.Md.Ak. | AD31: 8988005270 | AE31: setdakab.bdg@gmail.com | AF31: - | AG31: Harian
A32: 11 | B32: Layanan Perencanaan BMD | C32: BAGIAN PERENCKEU | D32: Untuk mengidentifikasi kebutuhan aset, merencanakan pengadaan, pemanfaatan, pemeliharaan, dan pengelolaan aset agar sesuai dengan tugas dan fungsi SKPD, mendukung pelayanan publik, dan memastikan pengelolaan yang akuntabel dan transparan sesuai regulasi. Layanan ini bertujuan untuk menciptakan pengelolaan aset yang efisien dan efektif, mencegah pemborosan, serta mengoptimalkan penggunaan aset daerah untuk pembangunan. | E32: Undang-Undang Nomor 1 Tahun 2004 tentang Perbendaharaan Negara, Peraturan Pemerintah Nomor 27 Tahun 2014 tentang Pengelolaan BMD. | G32: PERENCANAAN PEMBANGUNAN | H32: Instansi Pemerintah Lainnya | I32: Data Kebutuhan Aset | J32: Pengadaan Aset | K32: Terbatas | L32: Tidak terdapat | M32: Tahunan | N32: E-Planning BMD | O32: OPD | P32: Kab. Bandung | Q32: Website | R32: sshsbu.e-planningbmd.id | S32: Secara Online | T32: Informasi | V32: Aktif | W32: Tidak | X32: Tidak Terintegrasi | Y32: Tidak Terintegrasi | Z32: Tidak Terintegrasi | AA32: Bagian Perencanaan dan Keuangan | AB32: BKAD | AC32: YATI KURNIATI, SE., M.K.P. | AD32: 81321814674 | AE32: bagianprogramsetdakab.bandung@gmail.com | AF32: - | AG32: Tahunan
A33: 12 | B33: Layanan Statistik | C33: BAGIAN PERENCKEU | D33: Indonesia Data Hub merupakan one stop collaboration platform yang bertujuan untuk meningkatkan literasi data dan value of statistics serta mendukung interoperabilitas data dan kolaborasi eksplorasi terhadap data. | E33: Undang-Undang Nomor 16 Tahun 1997 tentang Statistik sebagai dasar umum, serta Peraturan Presiden Nomor 86 Tahun 2007 dan Peraturan Kepala Badan Pusat Statistik (BPS) Nomor 78 Tahun 2020 yang mengatur pelayanan statistik terpadu di tingkat pusat. | G33: PENGELOLAAN DATA STATISTIK | H33: Instansi Pemerintah Lainnya | I33: Metadata dan Standar Data Statistik | J33: Metadata dan Standar Data Statistik | K33: Terbuka | L33: Tidak terdapat | M33: Lainnya | N33: INDAH | O33: Pusat | P33: Pusat | Q33: Website | R33: https://indah.bps.go.id/ | S33: Secara Online | T33: Informasi | U33: 2019 | V33: Aktif | W33: Ya | X33: Terintegrasi dengan Aplikasi Romantik | Y33: Web Service | Z33: Realtime | AA33: Bagian Perencanaan dan Keuangan | AB33: Setda | AC33: DHANTI AURILIA PRATIWI, M.Stat | AD33: 81904085710 | AE33: setdakab.bdg@gmail.com | AF33: - | AG33: Tahunan
A34: 13 | B34: Layanan Informasi Pengawasan SAKIP, SPIP, MR | C34: BAGIAN PERENCKEU | D34: Fungsinya adalah menyediakan data dan laporan pengawasan yang terintegrasi untuk mendukung perbaikan tata kelola, meningkatkan transparansi, mengurangi potensi penyimpangan, dan memperkuat pengambilan keputusan berbasis bukti dalam rangka mewujudkan pemerintahan yang efektif, efisien, dan akuntabel. | E34: Nomor 60 Tahun 2008 tentang Sistem Pengendalian Intern Pemerintah (SPIP), Peraturan Presiden (Perpres) Nomor 29 Tahun 2014 tentang Sistem Akuntabilitas Kinerja Instansi Pemerintah (SAKIP). | G34: PENINGKATAN KUALITAS PELAYANAN PUBLIK | H34: Instansi Pemerintah Lainnya | I34: Data Evidence SAKIP, SPIP, MR | J34: Nilai SAKIP dan MR | K34: Terbatas | L34: Tidak terdapat | M34: Tahunan | N34: SIMWAS | O34: Pihak Ke 3 | P34: Kab. Bandung | Q34: Website | R34: simwas.bandungkab.go.id | S34: Secara Online | T34: Transaksi | U34: 2022 | V34: Aktif | W34: Tidak | X34: Tidak Terintegrasi | Y34: Tidak Terintegrasi | Z34: Tidak Terintegrasi | AA34: Bagian Perencanaan dan Keuangan | AB34: Setda, Inspektorat | AC34: DEBI RIANA S.STP., M.Si. | AD34: 8127392553 | AE34: setdakab.bdg@gmail.com | AF34: mungkin berkaitan dengan 27 | AG34: Tahunan
A35: 14 | B35: Layanan Informasi Data, Pengendalian, Evaluasi, dan Pelaporan | C35: BAGIAN PERENCKEU | D35: Mencakup penyediaan dan pengelolaan data dan informasi pembangunan, pemantauan dan pengendalian pelaksanaan program/kegiatan, serta penyusunan laporan hasil evaluasi untuk mendukung perumusan kebijakan dan pengambilan keputusan. Layanan ini bertugas menganalisis data, mengoordinasikan evaluasi, dan menyusun pelaporan program pembangunan daerah. | E35: Undang-Undang Nomor 14 Tahun 2008 tentang Keterbukaan Informasi Publik, Undang-Undang Nomor 25 Tahun 2009 tentang Pelayanan Publik. | G35: PENINGKATAN KUALITAS REFORMASI BIROKRASI, PENGAWASAN, DAN AKUNTABILITAS KINERJA | H35: Instansi Pemerintah Lainnya | I35: Data Kinerja dan Realisasi Anggaran | J35: Data Capaian Kinerja dan Realisasi Anggaran | K35: Terbatas | L35: Tidak terdapat | M35: Lainnya | N35: SIDALMONEP | O35: OPD | P35: Kab. Bandung | Q35: Website | R35: sidalmonep.bandungkab.go.id/ | S35: Secara Online | T35: Informasi | U35: 2021 | V35: Aktif | W35: Tidak | X35: SIPD | Y35: API | Z35: Realtime | AA35: Bagian Perencanaan dan Keuangan | AB35: Setda, Bapperida | AC35: YATI KURNIATI, SE., M.K.P. | AD35: 81321814674 | AE35: bagianprogramsetdakab.bandung@gmail.com | AF35: - | AG35: Tahunan
A36: BAGIAN UMUM
A37: 15 | B37: Layanan Pengelolaan Administrasi Kepegawaian | C37: BAGIAN UMUM | D37: mengelola administrasi, pengembangan, dan pelayanan pegawai secara efektif untuk mendukung kinerja Sekretariat Daerah. Fungsinya meliputi penyiapan bahan kebijakan, manajemen mutasi, kenaikan pangkat, pensiun, disiplin, hingga pengembangan kompetensi pegawai | E37: Undang-Undang Nomor 20 Tahun 2023 tentang Aparatur Sipil Negara | G37: PENATAAN SUMBER DAYA MANUSIA APARATUR | H37: Pegawai | I37: Data Kepegawaian | J37: Data Kepegawaian | K37: Terbatas | L37: Terdapat | M37: Harian | N37: SIMPEL BKPSDM | O37: Diskominfo | P37: Kab. Bandung | Q37: Website | R37: https://simpelbkpsdm.bandungkab.go.id/ | S37: Secara Online | T37: Informasi | V37: Aktif | W37: Ya | X37: Terintegrasi | Y37: Database to Database | Z37: Realtime | AA37: Bagian Umum | AB37: Setda | AC37: Iman Herman Sudrajat, S.IP. | AE37: bag_umum@bandungkab.go.id | AF37: 28 | AG37: Harian
A38: 16 | B38: Layanan Surat Masuk dan Penomoran Surat Keluar | C38: BAGIAN UMUM | D38: mengelola tata usaha, surat-menyurat, dan arsip secara tertib, aman, dan efisien. Fungsinya meliputi pengendalian naskah dinas masuk/keluar, penataan kearsipan, serta memfasilitasi administrasi pimpinan, staf ahli, dan perangkat daerah guna mendukung kelancaran kebijakan | E38: Peraturan Bupati (PERBUP) Nomor 82 Tahun 2024 tentang Pedoman Tata Naskah Dinas di Lingkungan Pemerintah Kabupaten Bandung. | G38: PENINGKATAN KUALITAS PELAYANAN PUBLIK | H38: Instansi Pemerintah Lainnya | I38: Surat Masuk. Naskah Dinas | J38: Nomor Surat | K38: Terbatas | L38: Tidak terdapat | M38: Harian | N38: SULTAN (E-Office) | O38: Diskominfo | P38: Kab. Bandung | Q38: Website | R38: https://sultan.bandungkab.go.id/ | S38: Secara Online | T38: Informasi | V38: Aktif | W38: Ya | X38: Terintegrasi | Y38: Database to Database | Z38: Realtime | AA38: Bagian Umum | AB38: Setda | AC38: Iman Herman Sudrajat, S.IP. | AE38: bag_umum@bandungkab.go.id | AF38: 28 | AG38: Harian
A39: 16 | B39: Layanan Piagam Penghargaan Bupati Bandung | C39: BAGIAN UMUM | D39: Layanan Fasilitasi Piagam Penghargaan Bupati berupa administrasi penerbitan, penyiapan naskah, dan pendokumentasian piagam penghargaan Bupati Bandung | E39: Peraturan Bupati (PERBUP) Nomor 82 Tahun 2024 tentang Pedoman Tata Naskah Dinas di Lingkungan Pemerintah Kabupaten Bandung. | G39: PENINGKATAN KUALITAS PELAYANAN PUBLIK | H39: Instansi Pemerintah Lainnya | I39: Permohonan Piagam | J39: Naskah dan Dokumen Piagam | K39: Terbatas | L39: Tidak terdapat | M39: Lainnya | N39: Microsoft Excel | O39: OPD | P39: Kab. Bandung | Q39: Desktop | R39: - | S39: Secara Offline | T39: Informasi | V39: Aktif | W39: Tidak | X39: Tidak Terintegrasi | Y39: Tidak Terintegrasi | Z39: Tidak Terintegrasi | AA39: Bagian Umum | AB39: Setda | AC39: Iman Herman Sudrajat, S.IP. | AE39: bag_umum@bandungkab.go.id | AF39: 28 | AG39: Harian
A40: BAGIAN ORGANISASI
A41: 17 | B41: Layanan Informasi Akuntabilitas Kinerja | C41: BAGIAN ORGANISASI | D41: Layanan Sistem Informasi Akuntabilitas Kinerja adalah sebuah sistem elektronik yang digunakan oleh instansi pemerintah untuk mengelola, mengukur, dan melaporkan kinerja secara terukur dan transparan. Sistem ini bertujuan untuk mewujudkan pemerintahan yang akuntabel, efektif, dan efisien, serta memberikan pertanggungjawaban atas penggunaan anggaran dan pencapaian tujuan organisasi kepada masyarakat. | E41: Peraturan Presiden Nomor 29 Tahun 2014 tentang Sistem Akuntabilitas Kinerja Instansi Pemerintah, serta peraturan pelaksanaannya seperti Peraturan Menteri Pendayagunaan Aparatur Negara dan Reformasi Birokrasi Nomor 88 Tahun 2021 tentang Evaluasi Akuntabilitas Kinerja Instansi Pemerintah | G41: PENINGKATAN KUALITAS REFORMASI BIROKRASI, PENGAWASAN, DAN AKUNTABILITAS KINERJA | H41: Instansi Pemerintah Lainnya | I41: Data Akuntabilitas Kinerja | J41: Data Akuntabilitas Kinerja | K41: Terbatas | L41: Tidak terdapat | M41: Tahunan | N41: SIAKANG | O41: OPD | P41: Kab. Bandung | Q41: Website dan Mobile | R41: siakang.bandungkab.go.id | S41: Secara Online | T41: Informasi | U41: 2023 | V41: Aktif | W41: Tidak | X41: Tidak Terintegrasi | Y41: Tidak Terintegrasi | Z41: Tidak Terintegrasi | AA41: Bagian Organisasi | AB41: Setda | AC41: IRMA PURNAMA, S.STP, M.Tr.A.P | AD41: 85218888714 | AE41: setdakab.bdg@gmail.com
A42: 18 | B42: Layanan Reformasi Birokrasi | C42: BAGIAN ORGANISASI | D42: Fungsi utama layanan Reformasi Birokrasi (RB) di Kabupaten Bandung adalah meningkatkan birokrasi yang bersih dan akuntabel, pelayanan publik yang prima, serta efektivitas kelembagaan agar menjadi organisasi yang adaptif, inovatif, dan berintegritas tinggi dalam melayani masyarakat. Tujuannya adalah menciptakan aparatur negara yang profesional, profesional, dan sejahtera, yang bekerja dengan integritas tinggi untuk memberikan pelayanan terbaik kepada masyarakat. | E42: Perpres No. 81 Tahun 2010 tentang Grand Design RB, Perbup No. 286 Tahun 2022 tentang Roadmap Reformasi Birokrasi Kabupaten Bandung. | G42: PROTOKOL DAN KONSULER | H42: Instansi Pemerintah Lainnya | I42: Data Capaian dan Evidence setiap Indikator RB | J42: Indeks Reformasi Birokrasi (IRB) | K42: Terbatas | L42: Tidak terdapat | M42: Tahunan | N42: SURABI | O42: Provinsi | P42: Provinsi | Q42: Website dan Mobile | R42: https://surabi.jabarprov.go.id/ | S42: Secara Online | T42: Informasi | U42: 2023 | V42: Aktif | W42: Tidak | X42: Tidak Terintegrasi | Y42: Tidak Terintegrasi | Z42: Tidak Terintegrasi | AA42: Bagian Organisasi | AB42: Setda | AC42: IRMA PURNAMA, S.STP, M.Tr.A.P | AD42: 85218888714 | AE42: setdakab.bdg@gmail.com
A43: 19 | B43: Layanan Survey Kepuasan Masyarakat | C43: BAGIAN ORGANISASI | D43: Fungsi utama layanan Survey Kepuasan Masyarakat (SKM) di Kabupaten Bandung adalah mengukur tingkat kepuasan masyarakat terhadap kualitas layanan publik yang diberikan oleh instansi pemerintah daerah, guna mengidentifikasi kelemahan dan kekurangan untuk selanjutnya menetapkan kebijakan dan tindakan perbaikan yang bertujuan meningkatkan kualitas pelayanan di masa mendatang. | E43: Undang-Undang Nomor 25 Tahun 2009 tentang Pelayanan Publik dan Peraturan Menteri Pendayagunaan Aparatur Negara dan Reformasi Birokrasi (PermenPAN-RB) Nomor 14 Tahun 2017 tentang Pedoman Penyusunan Survei Kepuasan Masyarakat Unit Penyelenggara Pelayanan Publik. | G43: PENINGKATAN KUALITAS PELAYANAN PUBLIK | H43: Masyarakat | I43: Hasil Survei Kepuasan Masyarakat | J43: Nilai Survei Kepuasan Masyarakat | K43: Terbatas | L43: Terdapat | M43: Lainnya | N43: E-SKM | O43: Diskominfo | P43: Kab. Bandung | Q43: Website dan Mobile | R43: https://skm.bandungkab.go.id/ | S43: Secara Online | T43: Informasi | U43: 2021 | V43: Aktif | W43: Tidak | X43: Tidak Terintegrasi | Y43: Tidak Terintegrasi | Z43: Tidak Terintegrasi | AA43: Bagian Organisasi | AB43: Setda | AC43: RAFSANJANI M. AMIN, S.STP | AD43: 82190093518 | AE43: setdakab.bdg@gmail.com
A44: 20 | B44: Layanan Tambahan Penghasilan ASN | C44: BAGIAN ORGANISASI | D44: Tujuannya untuk menyusun Kepbup besaran TPP-ASN dan Memberi kemudahan dalam penyusunan TPP-ASN dan mengontrol realisasi TPP setiap Perangkat Daerah | E44: Pasal 58-PP 12/2019 Tentang PENGELOLAAN KEUANGAN DAERAH, Permendagri 14/2025 Tentang PEDOMAN PENYUSUNAN ANGGARAN PENDAPATAN DAN BELANJA DAERAH TAHUN ANGGARAN 2026 Kepmendagri 900.1.3.2-1287 Tahun 2024 Tentang Tata Cara Persetujuan Menteri Dalam Negeri Terhadap Pemberian Tambahan Penghasilan Pegawai Aparatur Sipil Negara di Pemerintah Daerah | G44: PENINGKATAN KUALITAS REFORMASI BIROKRASI, PENGAWASAN, DAN AKUNTABILITAS KINERJA | H44: Pegawai | I44: Data Jabatan, Jumlah Pegawai dan Pagu Anggaran | J44: Keputusan Bupati Tentang Besaran TPP-ASN | K44: Terbatas | L44: Terdapat | M44: Bulanan | N44: SITAMPAN | O44: Pihak Ke 3 | P44: Kab. Bandung | Q44: Website dan Mobile | R44: https://sitampan-insaba.web.app/ | S44: Secara Online | T44: Transaksi | U44: 2025 | V44: Aktif | W44: Tidak | X44: Belum Terintegrasi | Y44: Tidak Terintegrasi | Z44: Realtime | AA44: Bagian Organisasi | AB44: Setda | AC44: IRMA PURNAMA, S.STP, M.Tr.A.P | AD44: 85218888714 | AE44: setdakab.bdg@gmail.com
A45: BAGIAN PROKOPIM
A46: 20 | B46: Layanan Informasi Agenda Pimpinan | C46: BAGIAN PROKOPIM | D46: Fungsi Utama layanan agenda pimpinan adalah agar PD dan ASN di pemerintah kabupaten bandung dapat dengan mudah melihat detail jadwal Bapak Bupati dan mengajukan permohonan untuk mengundang Bapak Bupati | G46: PENINGKATAN KUALITAS PELAYANAN PUBLIK | H46: Pegawai | I46: Data Pengajuan Agenda | J46: Data Agenda Pimpinan | K46: Terbatas | L46: Tidak terdapat | M46: Harian | N46: SIAGAN BEDAS | O46: Diskominfo | P46: Kab. Bandung | Q46: Website dan Mobile | R46: https://play.google.com/store/apps/details?id=com.diskominfo.siagan_bedas&hl=id | S46: Secara Online | T46: Informasi | U46: 2023 | V46: Aktif | W46: Tidak | X46: Tidak Terintegrasi | Y46: Tidak Terintegrasi | Z46: Tidak Terintegrasi | AA46: Bagian Prokopim | AB46: Setda | AC46: Ira | AD46: 85294019899 | AE46: - | AF46: - | AG46: Harian
A47: 21 | B47: Analisi Media Monitoring | C47: BAGIAN PROKOPIM | G47: INFORMASI DAN DIPLOMASI PUBLIK | H47: Pelaku Bisnis | I47: Data berita dan sosial media | J47: Statistik Data berita & sosial medi | K47: Rahasia | L47: Tidak terdapat | M47: Harian | N47: SIMANIS | O47: Diskominfo | P47: Kab. Bandung | Q47: Website | R47: {{need url}} | S47: Secara Online | T47: Informasi | U47: 2024 | V47: Non Aktif | W47: Ya | X47: Web Prokopim | Y47: API | Z47: Realtime | AA47: Bagian Prokopim | AB47: Setda | AC47: Vita | AD47: 62 813-1222-9386 | AF47: Semua | AG47: Harian
A48: BAGIAN TAPEM
A49: 21 | B49: Layanan Informasi Nama Rupabumi | C49: BAGIAN TAPEM | D49: Fungsi utama layanan aplikasi adalah melaksanakan Penyelenggaraan Nama Rupabumi pada tahapan pendataan Nama Rupabumi dan penelaaahan Nama Rupabumi dengan output berupa Nama Rupabumi baku beserta atributnya sebagai dasar penyusunan Gazeter RI | E49: PP Nomor 2 Tahun 2021 tentang Penyelenggaraan Nama Rupabumi | G49: PEMBINAAN ADMINISTRASI KEWILAYAHAN | H49: Instansi Pemerintah Lainnya | I49: Objek Rupabumi buatan dan alami | J49: Nama Rupabumi Baku | K49: Terbuka | L49: Tidak terdapat | M49: Harian | N49: SINAR | O49: Pusat | P49: Pusat | Q49: Website dan Mobile | R49: Sinar.big.go.id | S49: Secara Online | T49: Informasi | U49: 2021 | V49: Aktif | W49: Tidak | X49: Tidak Terintegrasi | Y49: Tidak Terintegrasi | Z49: Tidak Terintegrasi | AA49: Tim Pembakuan Nama Rupabumi Kab. Bandung (Sekretariat: Bagian Tata Pemerintahan) | AB49: Setda | AC49: Gugum Gumilar, S.STP., M.Si | AD49: 0819-1001-1980 | AE49: admkewilayah@gmail.com
A50: 22 | B50: Layanan Laporan Penyelenggaraan Pemerintahan Daerah | C50: BAGIAN TAPEM | D50: Sebagai sistem aplikasi terpusat yang mempermudah Pemerintah Daerah (Provinsi, Kabupaten, Kota) untuk menyampaikan Laporan Penyelenggaraan Pemerintahan Daerah (LPPD) dan melakukan evaluasi secara online dan real-time, sehingga menghasilkan satu data yang akurat, mengurangi redundansi data, dan mempercepat penyebaran informasi pelaporan | E50: Peraturan Menteri Dalam Negeri Nomor 19 Tahun 2024 tentang Peraturan Pelaksana Peraturan Pemerintah Nomor 13 Tahun 2019 tentang Laporan dan Evaluasi Penyelenggaraan Pemerintahan Daerah; | G50: OTONOMI DAERAH | H50: Instansi Pemerintah Lainnya | J50: Laporan Penyelenggaraan Pemerintahan Daerah (LPPD) | K50: Terbuka | L50: Tidak terdapat | M50: Tahunan | N50: SILPPD | O50: Pusat | P50: Pusat | Q50: Website dan Mobile | R50: https://elppd.kemendagri.go.id/ | S50: Secara Online | T50: Informasi | U50: 2021 | V50: Aktif | W50: Tidak | X50: Tidak Terintegrasi | Y50: Tidak Terintegrasi | Z50: Tidak Terintegrasi | AA50: Bagian Tata Pemerintahan | AB50: Setda, Disdik, Dinkes, DPUTR, Disperkimtan, Dinsos, Disdamkar, Satpol PP, BPBD, Inspektorat, Disnaker, DP2KBP3A, DLH, Disdukcapil, DPMD, Dishub, Diskominfo, DPMPTSP, Dispora, Disperdagin, Distan, Dispakan, Disbud, DISKOP-UKM, Dispusip, Disparekraf, BKAD, BKPSDM | AC50: Gugum Gumilar, S.STP., M.Si | AD50: 0819-1001-1980 | AE50: admkewilayah@gmail.com
A51: 23 | B51: Layanan Pelaporan Standar Pelayanan Minimal (SPM) Ditjen Bina Pembangunan Daerah Kementerian Dalam Negeri | C51: BAGIAN TAPEM | D51: Sebagai dasar untuk melakukan monitoring dan evaluasi terpadu, mengelola data dan menganalisis capaian penerapan SPM di daerah, serta menjadi alat untuk mengkoordinasikan implementasi SPM antara pemerintah pusat dan daerah agar pelayanan dasar yang diberikan kepada masyarakat sesuai dengan ketentuan yang berlaku | E51: Peraturan Menteri Dalam Negeri Nomor 59 Tahun 2021 Tentang Penerapan Standar Pelayanan Minimal | G51: OTONOMI DAERAH | H51: Instansi Pemerintah Lainnya | J51: Laporan Penerapan Standar Pelayanan Minimal (SPM) | K51: Terbuka | L51: Tidak terdapat | M51: Lainnya | N51: e-SPM | O51: Pusat | P51: Pusat | Q51: Website dan Mobile | R51: https://spm.bangda.kemendagri.go.id/ | S51: Secara Online | T51: Informasi | U51: 2021 | V51: Aktif | W51: Tidak | X51: Tidak Terintegrasi | Y51: Tidak Terintegrasi | Z51: Tidak Terintegrasi | AA51: Bagian Tata Pemerintahan | AB51: Setda, Disdik, Dinkes, DPUTR, Disperkimtan, BPBD, Disdamkar, Satpol PP | AC51: Gugum Gumilar, S.STP., M.Si | AD51: 0819-1001-1980 | AE51: admkewilayah@gmail.com
A52: BAGIAN KESRA
A53: 31 | B53: Layanan informasi publik | C53: BAGIAN KESRA | D53: Keterbukaan informasi publik merupakan sarana dalam mengoptimalkan pengawasan publik terhadap penyelenggaraan negara dan Badan Publik lainnya dan segala sesuatu yang berakibat pada kepentingan publik sebagaimana yang diamanatkan dalam Undang-Undang Nomor 14 Tahun 2008 | E53: Undang-Undang Nomor 14 Tahun 2008 | G53: PENGELOLAAN INFORMASI PUBLIK | H53: Pelaku Bisnis | I53: Data Informasi Publik | J53: Data Informasi Publik | K53: Terbatas | L53: Tidak terdapat | M53: Lainnya | N53: PPID | O53: Diskominfo | P53: Kab. Bandung | Q53: Website dan Mobile | R53: https://ppid.bandungkab.go.id/ | S53: Secara Online | T53: Informasi | V53: Aktif | W53: Ya | X53: Tidak Terintegrasi | Y53: Tidak Terintegrasi | Z53: Tidak Terintegrasi | AA53: Bagian Kesra | AB53: Setda
A54: BAGIAN HUKUM
A55: 32 | B55: Layanan Pengajuan Produk Hukum | C55: BAGIAN HUKUM | D55: Sipphade, yang juga disebut BEDAS Sipphade (akronim dari “Sistem Informasi Penyusunan Produk Hukum Daerah”), adalah sebuah aplikasi digital yang diluncurkan oleh Pemerintah Kabupaten Bandung. Aplikasi ini dirancang untuk:Mempermudah proses pengajuan produk hukum daerah oleh perangkat daerah. | E55: Undang-Undang Nomor 12 Tahun 2011 tentang Pembentukan Peraturan Perundang-Undangan sebagaimana telah diubah dengan Undang-Undang Nomor 13 Tahun 2022 tentang Perubahan Kedua atas Undang-Undang Nomor 12 Tahun 2011 tentang Pembentukan Peraturan Perundang-Undangan | F55: - | G55: PENYELENGGARAAN PERATURAN PERUNDANG-UNDANGAN | H55: Instansi Pemerintah Lainnya | I55: Identitas Perangkat Daerah Pengusul | J55: surat keputusan | K55: Terbatas | L55: Tidak terdapat | M55: Bulanan | N55: SIPPHADE | O55: Diskominfo | P55: Kab. Bandung | Q55: Website | R55: https://sipphade.bandungkab.go.id/ | S55: Secara Online | T55: Informasi | U55: 2024 | V55: Aktif | W55: Ya | X55: TERINTERGRASI DENGAN E OFFICE DAN BSRE | Y55: Database to Database | Z55: Realtime | AA55: Bagian Hukum Sekretariat Daerah Kabupaten Bandung | AB55: Setda | AC55: DADAN SUNANDAR, SH | AD55: 85721347799 | AE55: baghukum17@gmail.com
A56: 33 | B56: Layanan Penanganan litigasi Hukum bedas | C56: BAGIAN HUKUM | D56: Sistem Penanganan litigasi Hukum bedas | E56: - | F56: - | G56: ADMINISTRASI HUKUM UMUM | H56: Masyarakat | I56: para pihak yang berperkara | J56: panggilan sidang | K56: Terbuka | L56: Terdapat | M56: Bulanan | N56: SIPATUHBEDAS | O56: Diskominfo | P56: Kab. Bandung | Q56: Website | R56: https://sipatuhbedas.bandungkab.go.id/ | S56: Secara Online | T56: Informasi | U56: 2023 | V56: Aktif | W56: Ya | X56: - | Y56: Database to Database | Z56: Bulanan | AA56: bagian Hukum Sekretariat Daerah Kabupaten Bandung | AB56: Setda | AC56: ZAENAL MUTTAQIN,SH | AD56: 8127585399 | AE56: zaenal1972.zm@gmail.com
A57: BAGIAN KERJA SAMA
A58: 34 | B58: Layanan Fasilitasi Kerja Sama Daerah | C58: BAGIAN KERJA SAMA | D58: Mempercepat transformasi digital dalam tata kelola pemerintahan dan penyusunan peraturan perundang-undangan. | E58: PP No 28 Tahun 2018 tentang Kerja Sama Daerah. Permendagri No 22 Tahun 2020 tentang Tata Cara Kerja Sama Daerah dengan Daerah Lain dan Kerja Sama Daerah dengan Pihak Ketiga, Permendagri No 25 Tahun 2020 tentang Tata Cara Kerja Sama Daerah dengan Pemerintah Daerah di Luar Negeri dan Kerja Sama Daerah dengan Lembaga di Luar Negeri | F58: Ada sesuai Keputusan Sekretaris Dearah No.415.4/KEP.25-KSM/2023 tentang Penetapan Standar Operasional Prosedur Kerja Sama Daerah di Lingkungan Pemerintah Kabupaten Bandung | G58: PENINGKATAN KUALITAS PELAYANAN PUBLIK | H58: Pelaku Bisnis, Masyarakat, Pegawai, Instansi Pemerintah Lainnya | I58: Data Pengguna, data persyaratan permohonan kerja sama, laporan dan perencanaan | J58: Data kerja sama, data permohonan, data perencanaan dan data laporan | K58: Terbatas | L58: Terdapat | M58: Lainnya | N58: SiBERKAH | O58: Diskominfo | P58: Kab. Bandung | Q58: Website dan Mobile | R58: kerjasama.bandungkab.go.id | S58: Secara Online | T58: Informasi | U58: 2022 | V58: Aktif | W58: Ya | X58: BDS | Y58: Web Service | Z58: Realtime | AA58: Bagian Kerja Sama SETDA | AB58: Setda | AC58: Ir. Elis Kusmawati,MM | AD58: 85322543009 | AE58: kerjasamabandungkab@gmail.com | AG58: harian | AH58: data kerjasama daerah dengan daerah atau daerah dengan pihak ketiga perangkat daerah sudah punya admin sendiri pengguna mitra kerja dan perangkat daerah, kabupaten lain Mitra kerja itu perangkat daerah lain dan oerguruan tinggi
A59: BAGIAN PEREKONOMIAN
A60: 35 | B60: Layanan informasi data terkait penyerapan KUR untuk UMKM Kabupaten Bandung | C60: BAGIAN PEREKONOMIAN | D60: Meningkatkan kapasitas SDM (sumber daya manusia) yang merancang produk hukum. | E60: keputusan bupati bandung nomor 500/KEP..671-Perek/2017 tentang pembentukan tim inflasi darah kabupaten bandung | G60: USAHA KECIL DAN MENENGAH | H60: Instansi Pemerintah Lainnya | I60: dataUMKM yang membutuhkan KUR | J60: data UMKM yang telah menerima KUR | K60: Terbuka | L60: Terdapat | M60: Harian | N60: SIKP | O60: Pusat | P60: Pusat | Q60: Website | R60: https://sikp.kemenkeu.go.id/login | S60: Secara Online | T60: Informasi | U60: 2017 | V60: Aktif | W60: Tidak | X60: Tidak Terintegrasi | Z60: Mingguan | AA60: bagian perekonomian | AC60: herrier mustari | AE60: usmankaryana1961@gmail.com
A61: 36 | B61: Layanan informasi dan penginputan realisasi terkait program percepatan keuangan daerah | C61: BAGIAN PEREKONOMIAN | E61: keputusan bupati bandung nomor 539/Kep.481-Perek/2021 tentang pembentukan tim percepatan akses keuangan daerah kabupaten bandung | G61: PEMBINAAN KEUANGAN DAERAH | H61: Instansi Pemerintah Lainnya | I61: target dan realisasi program percepatan akses keuangan daerah | J61: realisasi program percepatan akses keuangan daerah | K61: Terbuka | L61: Tidak terdapat | M61: Bulanan | N61: SITPAKD | O61: Pusat | P61: Pusat | Q61: Website | R61: https://sitpakd.ojk.go.id/Account/Login | S61: Secara Online | T61: Informasi | U61: 2021 | V61: Aktif | W61: Tidak | X61: Tidak Terintegrasi | Z61: Mingguan | AA61: bagian perekonomian | AB61: Setda | AC61: herrier mustari | AE61: usmankaryana1961@gmail.com
A62: 37 | B62: Layanan penginputan rencana kerja anggaran, laporan hasil kegiatan dan realisasi DBHCHT | C62: BAGIAN PEREKONOMIAN | D62: Meningkatkan kualitas produk hukum agar sesuai tujuan seperti kepastian hukum, manfaat, dan keadilan bagi pemangku kepentingan | E62: KEPUTUSAN BUPATI BANDUNG NOMOR : 900.1.14.3/KEP.746-PEREK/2024 Penetapan Pagu Alokasi Dana Bagi Hasil Cukai Hasil Tembakau Bagian Pemerintah Daerah Kabupaten Bandung Tahun Anggaran 2025 dan KEPUTUSAN BUPATI BANDUNG NOMOR : 000.8.1.1/KEP.738-PEREK/202 TIM KOORDINASI PENGELOLAAN DANA BAGI HASIL CUKAI HASIL TEMBAKAU DAERAH KABUPATEN BANDUNG TAHUN 2025 | G62: PENINGKATAN KUALITAS REFORMASI BIROKRASI, PENGAWASAN, DAN AKUNTABILITAS KINERJA | H62: Instansi Pemerintah Lainnya | I62: realisasi dan laporan hasil kegiatan DBHCHT | J62: realisasi dan laporan hasil kegiatan DBHCHT | K62: Terbuka | L62: Tidak terdapat | M62: Bulanan | N62: e-DBHCHT | O62: Provinsi | P62: Provinsi | Q62: Website | R62: https://www.appsheet.com/Account/Login?appName=DBHCHT%20App&FullScope=False&provider=google&returnUrl=https%3A%2F%2Fwww.appsheet.com%2Fstart%2F93891b63-df85-4aa1-a7bf-d007dfa96cf8%3Fplatform%3Ddesktop#appName=DBHCHTApp-787771102-23-06-21&vss=H4sIAAAAAAAAA6WPwU4CMRCG32XOhTRlIaFX9WAMHIR4kHqodNY07Lab7aCSTd-dqUI03NDj_DPfNzMDvHv8WJHd7kBvhp_qAQ-gYTCwPnRoQBu4iYH62BgQBpa2_Q5XSOTDWzKQIb-IM0-YQA_X4fp_2wV4h4F87bEvrkKy48Rxu1AcnBnIAto92dcGvw4uzGn4clLAY4zESR37lqtbS5aZtuNISVWN5GykqrVUulJ6KsdzOZ3MZ5PnclO6D3fO0yI6Vta2SZgzb67jdp_QPfHDf3i0SD87G9xv7RGGjFddywEAAA==&view=Settings | S62: Secara Online | T62: Informasi | V62: Aktif | W62: Tidak | X62: Tidak Terintegrasi | Z62: Realtime | AA62: bagian perekonomian | AB62: Setda | AC62: selly rossela
A63: 38 | B63: Layanan penginputan rencana kerja anggaran, laporan hasil kegiatan dan realisasi DBHCHT | C63: BAGIAN PEREKONOMIAN | D63: 1. Meningkatkan Efektivitas dan Efisiensi kerja Pimpinan. 2. Mempermudah koordinasi eksternal. 3. Transparansi dan akuntabilitas. 4. Dokumentasi dan arsip digital. 5. Mendukung pengambilan keputusan. 6. Memudahkan akses dan mobilitas. | E63: KEPUTUSAN BUPATI BANDUNG NOMOR : 900.1.14.3/KEP.746-PEREK/2024 Penetapan Pagu Alokasi Dana Bagi Hasil Cukai Hasil Tembakau Bagian Pemerintah Daerah Kabupaten Bandung Tahun Anggaran 2025 dan KEPUTUSAN BUPATI BANDUNG NOMOR : 000.8.1.1/KEP.738-PEREK/202 TIM KOORDINASI PENGELOLAAN DANA BAGI HASIL CUKAI HASIL TEMBAKAU DAERAH KABUPATEN BANDUNG TAHUN 2025 | G63: PENINGKATAN KUALITAS REFORMASI BIROKRASI, PENGAWASAN, DAN AKUNTABILITAS KINERJA | H63: Instansi Pemerintah Lainnya | I63: realisasi dan laporan hasil kegiatan DBHCHT | J63: realisasi dan laporan hasil kegiatan DBHCHT | K63: Terbuka | L63: Tidak terdapat | M63: Bulanan | N63: SIKD | O63: Pusat | P63: Pusat | Q63: Website | R63: https://sikd.djpk.kemenkeu.go.id/lapordbh/ | S63: Secara Online | T63: Informasi | V63: Aktif | W63: Tidak | X63: Tidak Terintegrasi | Z63: Realtime | AA63: bagian perekonomian | AB63: Setda | AC63: selly rossela
A64: 39 | B64: Layanan Informasi pemerintah Daerah | C64: BAGIAN PEREKONOMIAN | D64: 1. Meningkatkan Efektivitas dan Efisiensi kerja Pimpinan. 2. Mempermudah koordinasi eksternal. 3. Transparansi dan akuntabilitas. 4. Dokumentasi dan arsip digital. 5. Mendukung pengambilan keputusan. 6. Memudahkan akses dan mobilitas. | E64: Pasal 391 Undang-Undang Nomor 23 Tahun 2014 tentang Pemerintahan Daerah | G64: PENINGKATAN KUALITAS REFORMASI BIROKRASI, PENGAWASAN, DAN AKUNTABILITAS KINERJA | H64: Pegawai | I64: data realisasi keuangan dan anggaran | J64: data realisasi keuangan dan anggaran | K64: Terbatas | L64: Terdapat | M64: Lainnya | N64: SIPD | O64: Pusat | P64: Pusat | Q64: Website | R64: https://SIPD.kemendagri.go.id/auth/login | X64: Tidak Terintegrasi | AA64: bagian perekonomian | AB64: Setda | AC64: HERRIER MUSTARI, MM
A65: 40 | B65: Layanan realisasi pengendalian inflasi per triwulan | C65: BAGIAN PEREKONOMIAN | D65: 1. Meningkatkan Efektivitas dan Efisiensi kerja Pimpinan. 2. Mempermudah koordinasi eksternal. 3. Transparansi dan akuntabilitas. 4. Dokumentasi dan arsip digital. 5. Mendukung pengambilan keputusan. 6. Memudahkan akses dan mobilitas. | E65: keputusan bupati bandung nomor 500/KEP.671-Perek/2017 tentang pembentukan tim inflasi Daerah | G65: PENINGKATAN KUALITAS REFORMASI BIROKRASI, PENGAWASAN, DAN AKUNTABILITAS KINERJA | H65: Instansi Pemerintah Lainnya | I65: laporan pertriwulan pengendalian inflasi daerah | J65: laporan pertriwulan pengendalian inflasi daerah | K65: Terbuka | L65: Tidak terdapat | M65: Bulanan | N65: TPIN | O65: Pusat | P65: Pusat | Q65: Website | R65: https://tpin.id/login | X65: Tidak Terintegrasi | AA65: bagian perekonomian | AB65: Setda | AC65: MUHAMAD IFAN HERMANTO, S.E
A66: 41 | B66: Layanan laporan realisasi proram reformasi birokrasi di tiap bagian | C66: BAGIAN PEREKONOMIAN | D66: 1. Meningkatkan Efektivitas dan Efisiensi kerja Pimpinan. 2. Mempermudah koordinasi eksternal. 3. Transparansi dan akuntabilitas. 4. Dokumentasi dan arsip digital. 5. Mendukung pengambilan keputusan. 6. Memudahkan akses dan mobilitas. | G66: PENINGKATAN KUALITAS REFORMASI BIROKRASI, PENGAWASAN, DAN AKUNTABILITAS KINERJA | H66: Instansi Pemerintah Lainnya | K66: Terbuka | L66: Tidak terdapat | M66: Lainnya | N66: PORTALRB | O66: Pusat | P66: Pusat | Q66: Website | R66: https://www.portalrb.id/ | S66: Secara Online | T66: Informasi | V66: Aktif | X66: Tidak Terintegrasi | Z66: Realtime | AA66: bagian perekonomian | AB66: Setda | AC66: MUHAMAD IFAN HERMANTO, S.E
A67: 43 | B67: Layanan analisis kebutuhan jabatan dan analisis beban kerja | C67: BAGIAN PEREKONOMIAN | D67: 1. Meningkatkan Efektivitas dan Efisiensi kerja Pimpinan. 2. Mempermudah koordinasi eksternal. 3. Transparansi dan akuntabilitas. 4. Dokumentasi dan arsip digital. 5. Mendukung pengambilan keputusan. 6. Memudahkan akses dan mobilitas. | E67: keputusan sekretaris daerah nomor 800/Kep.29-Umum/2022 tentang pembentukan tim penyusunan analisis jabatan (ANJAB)analisis beban kerja (ABK) evaluasi jabatan (EVJAB) dan standar kompetensi jabatan ASN pada sekretariat daerah kabupaten bandung | G67: PENINGKATAN KUALITAS REFORMASI BIROKRASI, PENGAWASAN, DAN AKUNTABILITAS KINERJA | H67: Pegawai | I67: hasil analisis jabatan, beban kinerja dan evaluasi jabatan | J67: hasil analisis jabatan, beban kinerja dan evaluasi jabatan | K67: Terbuka | L67: Tidak terdapat | M67: Lainnya | N67: BISAKERJA | O67: OPD | P67: Kab. Bandung | Q67: Website | R67: https://bisakerja.bandungkab.go.id/login | S67: Secara Online | T67: Informasi | V67: Aktif | X67: Tidak Terintegrasi | Z67: Realtime | AA67: bagian perekonomian | AB67: Setda | AC67: LIES BETTY HIDAYANTI, SE
A68: 44 | B68: Layanan Laporan Keuangan BUMD | C68: BAGIAN PEREKONOMIAN | D68: 1. Meningkatkan Efektivitas dan Efisiensi kerja Pimpinan. 2. Mempermudah koordinasi eksternal. 3. Transparansi dan akuntabilitas. 4. Dokumentasi dan arsip digital. 5. Mendukung pengambilan keputusan. 6. Memudahkan akses dan mobilitas. | E68: Peraturan Pemerintah Nomor 54 Tahun 2017 tentang Badan Usaha Milik Daerah (BUMD) | G68: PENINGKATAN KUALITAS REFORMASI BIROKRASI, PENGAWASAN, DAN AKUNTABILITAS KINERJA | H68: Instansi Pemerintah Lainnya | I68: Laporan Keuangan BUMD | J68: Laporan Keuangan BUMD | K68: Terbatas | L68: Tidak terdapat | M68: Bulanan | N68: e-BUMD | O68: Pusat | P68: Pusat | Q68: Website | R68: http://e-bumd.com//dashboard | S68: Secara Online | T68: Informasi | V68: Aktif | W68: Tidak | X68: Tidak Terintegrasi | Z68: Bulanan | AA68: bagian perekonomian | AB68: Setda | AC68: ROBBY IRAWAN, S.Sos
A69: BAGIAN ADBANG
A70: 45 | B70: Layanan Administrasi Pembangunan | C70: BAGIAN ADBANG | D70: Membantu memfasilitasi perangkat daerah dalam informasi yang berkaitan dengan kegiatan pembangunan fisik/non fisik di lingkup Pemerintah Daerah Kabupaten Bandung yang bertujuan untuk mendorong terciptanya mekanisme informasi pembangunan yang berkualitas dan tertib administrasi | E70: PP No. 26 Tahun 2006 Tentang Tata Cara Pengendalian dan Evaluasi Pelaksanaan Rencana Pembangunan; PP No. 38 Tahun 2019 Tantang Inovasi Daerah; Perpres No. 95 Tahun 2018 Tentang Sistem Pemerintahan Berbasis Elektronik; Peraturan Bupati No 281 Tahun 2023 Tentang Penerapan Inovasi Berupa Pelaksanaan Monitoring Kegiatan Pembangunan Daerah Melalui Sistem Informasi Manajemen Administrasi Pembangunan; Peraturan Bupati No. 281 Tahun 2023 Tentang Penerapan Inovasi Berupa Pelaksanaan Monitoring Kegiatan Pembangunan Daerah Melalui Sistem Informasi Manajemen Administrasi Pembangunan; Keputusan Bupati Bandung No. 500.12/KEP.754-ADBANG/2024 Tentang Penetapan Pengelola Sistem Informasi Manajemen Administrasi Pembangunan Kabupaten Bandung. | F70: SOP Simbangun: https://drive.google.com/drive/folders/1uT9c4NGjI41uZyGgKpyquckLoM2rSaQa?usp=sharing | G70: PENINGKATAN KUALITAS PELAYANAN PUBLIK | H70: Instansi Pemerintah Lainnya | I70: Data Tenaga Ahli, Data Tenaga Terampil, Data Badan Usaha, Data Quarry, Data Lab. Uji Konstruksi, Data Sewa Alat, Data Paket Pekerjaan, Data Progres Paket Pekerjaan, BPJS | J70: Kurva-S, Diagram Rekap Data, Tagging Kordinat Lokasi dan Dokumentasi | K70: Terbatas | L70: Tidak terdapat | M70: Lainnya | N70: SIMBANGUN | O70: Pihak Ke 3 | P70: Kab. Bandung | Q70: Website | R70: https://simbangun.bandungkab.go.id | S70: Secara Online | T70: Informasi | U70: 2022 | V70: Aktif | W70: Tidak | X70: Link ke Amel, sireka | Y70: Tidak Terintegrasi | Z70: Realtime | AA70: Bagian Administrasi Pembangunan | AB70: Setda | AC70: Wawan Purwanto, ST. | AD70: 8122233244 | AE70: wawan.purwanto3@gmail.com | AF70: - | AG70: Harian | AH70: OPD, Kecamatan
A71: 46 | B71: Layanan Evaluasi Pelaporan Program Pembangunan | C71: BAGIAN ADBANG | D71: Untuk mengevaluasi pencapaian hasil dari program pembangunan yang telah dilaksanakan. Ini melibatkan analisis terhadap kinerja program, dampak terhadap masyarakat, efisiensi penggunaan sumber daya, dan ketaatan terhadap peraturan. | E71: Peraturan Pemerintah Nomor 13 Tahun 2019 dan Peraturan Menteri Dalam Negeri No. 18 Tahun 2020 | G71: PENINGKATAN KUALITAS PELAYANAN PUBLIK | H71: Instansi Pemerintah Lainnya | I71: Data Evaluasi Program Pembangunan | J71: LKPJ, Tugas Perbantuan, DAK | K71: Terbatas | L71: Tidak terdapat | M71: Tahunan | N71: e-LKPJ | O71: Pihak Ke 3 | P71: Pihak Ke 3 (Lisensi) | Q71: Website | R71: https://e-lkpj.id/bandungkab/web/index.php?r=dashboard%2Flogin | S71: Secara Online | T71: Informasi | U71: 2020 | V71: Aktif | W71: Tidak | X71: Tidak Terintegrasi | Y71: Tidak Terintegrasi | Z71: Tidak Terintegrasi | AA71: Bagian Administrasi Pembangunan | AB71: Setda | AC71: Wawan Purwanto, ST. | AD71: 8122233244 | AE71: wawan.purwanto3@gmail.com | AF71: - | AG71: Tahunan | AH71: OPD
A72: BAGIAN BARJAS | AG72: Tahunan
A73: 48 | B73: Layanan Pengadaaan Barang dan Jasa | C73: BAGIAN BARJAS | D73: meningkatkan kualitas layanan, kapasitas dan keamanan informasi dalam penyelenggaraan layanan pengadaan Barang/Jasa secara elektronik dan memfasilitasi pelaksanaan Pengadaan Barang/Jasa secara elektronik | E73: Perpres Nomor 46 Tahun 2025 tentang Perubahan Kedua atas Peraturan Presiden Nomor 16 Tahun 2018 tentang Pengadaan Barang/Jasa Pemerintah | F73: https://drive.google.com/file/d/1bfEasna0yACDkjKfdw6Q1Zy2Ku88gtKx/view?usp=sharing | G73: PENINGKATAN KUALITAS PELAYANAN PUBLIK | H73: Pelaku Bisnis | I73: Proses Pengadaan Barang/Jasa Tender dan Non Tender, Akun PA/KPA, PPK dan Penyedia | J73: Data Pengadaan Barang/Jasa yang dilaksakan secara Tender dan Non Tender | K73: Terbuka | L73: Tidak terdapat | M73: Lainnya | N73: SPSE | O73: Pusat | P73: Pusat | Q73: Website | R73: https://spse.inaproc.id/bandungkab | S73: Secara Online | T73: Informasi | U73: 2013 | V73: Aktif | W73: Tidak | X73: Tidak Terintegrasi | Y73: Tidak Terintegrasi | Z73: Tidak Terintegrasi | AA73: Bagian Pengadaan Barang/Jasa | AB73: Setda | AC73: Ana Suryana, ST., MM. | AD73: 85220648981 | AE73: helpdesk.bandung.kab@gmail.com | AG73: Tahunan
A74: BAGIAN SDA
A75: 49 | B75: Layanan Satgas Percepatan Penyelenggaraan MBG Kabupaten Bandung | C75: BAGIAN SDA | D75: 1. Mengatur, mendokumentasikan, dan menyimpan seluruh dokumen administrasi yang berkaitan dengan pelaksanaan program, seperti notulen rapat, surat-menyurat, laporan, dan arsip lainnya; 2. Memfasilitasi komunikasi dan koordinasi antar anggota Satuan Tugas serta dengan pihak-pihak terkait lainnya agar informasi tersampaikan dengan baik dan tepat waktu; 3. Menyusun dan mengatur jadwal rapat, kunjungan lapangan, dan kegiatan Satuan Tugas lainnya, serta memastikan pelaksanaan kegiatan sesuai dengan jadwal yang ditetapkan; 4. Membantu dalam penyusunan laporan pelaksanaan program, yang akan disampaikan kepada pembina atau pengarah; 5. Menyiapkan agenda rapat, mengundang peserta rapat, menyiapkan bahan rapat, dan mencatat hasil rapat sebagai bahan tindak lanjut; 6. Menjaga dan mengelola arsip data program makan siang bergizi gratis untuk memudahkan akses informasi dan dokumentasi yang dibutuhkan Satuan Tugas; dan 7. Membantu dalam pengumpulan dan pendataan kebutuhan, capaian, dan kendala pelaksanaan program makan siang bergizi gratis. | E75: KEPUTUSAN BUPATI BANDUNG NOMOR : 000.8.1.1/KEP.465-HUK/2025 PEMBENTUKAN SATUAN TUGAS PERCEPATAN PENYELENGGARAAN PROGRAM MAKAN SIANG BERGIZI GRATIS KABUPATEN BANDUNG | G75: PENGENDALIAN PROGRAM PRIORITAS NASIONAL | H75: Instansi Pemerintah Lainnya | I75: Data Koordinasi dan Fasilitasi Pelaksanaan Program Pemerintah Daerah | J75: SK Pembentukan Satgas MBG Kabupaten BandungDokumen rencana kerja / rencana aksi percepatan penyelenggaraan MBG, Notulen atau berita acara rapat koordinasi Satgas MBG, Laporan pelaksanaan kegiatan Satgas, Laporan monitoring dan evaluasi pelaksanaan MBG, Rekomendasi kebijakan atau tindak lanjut percepatan MBG dan Data progres pelaksanaan program MBG di Kabupaten Bandung | K75: Terbuka | L75: Tidak terdapat | M75: Mingguan | N75: Dashboard Satgas MBG | O75: Diskominfo | P75: Kab. Bandung | Q75: Website dan Mobile | R75: https://aplikasi.bandungkab.go.id/publik/dashboard-pendataan-profil-sppg-aktif-untuk-satgas-mbg | S75: Secara Online | T75: Informasi | U75: 2025 | V75: Aktif | W75: Tidak | X75: Terintegrasi (Dashboard Pimpinan) | Y75: Database to Database | Z75: Realtime | AA75: bagian SDA | AB75: Setda, Inspektorat, Disdik, Dinkes, DPUTR | AC75: RUSLI BAIJURI,AP.M.KP | AE75: bagsdasetdakabbandung@gmail.com | AF75: Prioritas Nasional | AG75: Harian | AH75: Desa, Kecamatan & Kabupaten
A76: 50 | B76: Layanan penginputan rencana kerja anggaran, laporan hasil kegiatan dan realisasi DBHCHT | C76: BAGIAN SDA | D76: Meningkatkan kualitas produk hukum agar sesuai tujuan seperti kepastian hukum, manfaat, dan keadilan bagi pemangku kepentingan | E76: KEPUTUSAN BUPATI BANDUNG NOMOR : 900.1.14.3/KEP.657-PEREK/2025 PENETAPAN PAGU ALOKASI DANA BAGI HASIL CUKAI HASIL TEMBAKAU BAGIAN PEMERINTAH KABUPATEN BANDUNG TAHUN ANGGARAN 2026 | G76: PENINGKATAN KUALITAS REFORMASI BIROKRASI, PENGAWASAN, DAN AKUNTABILITAS KINERJA | H76: Instansi Pemerintah Lainnya | I76: realisasi dan laporan hasil kegiatan DBHCHT | J76: realisasi dan laporan hasil kegiatan DBHCHT | K76: Terbuka | L76: Tidak terdapat | M76: Bulanan | N76: e-DBHCHT | O76: Provinsi | P76: Provinsi | Q76: Website | R76: https://www.appsheet.com/Account/Login?appName=DBHCHT%20App&FullScope=False&provider=google&returnUrl=https%3A%2F%2Fwww.appsheet.com%2Fstart%2F93891b63-df85-4aa1-a7bf-d007dfa96cf8%3Fplatform%3Ddesktop#appName=DBHCHTApp-787771102-23-06-21&vss=H4sIAAAAAAAAA6WPwU4CMRCG32XOhTRlIaFX9WAMHIR4kHqodNY07Lab7aCSTd-dqUI03NDj_DPfNzMDvHv8WJHd7kBvhp_qAQ-gYTCwPnRoQBu4iYH62BgQBpa2_Q5XSOTDWzKQIb-IM0-YQA_X4fp_2wV4h4F87bEvrkKy48Rxu1AcnBnIAto92dcGvw4uzGn4clLAY4zESR37lqtbS5aZtuNISVWN5GykqrVUulJ6KsdzOZ3MZ5PnclO6D3fO0yI6Vta2SZgzb67jdp_QPfHDf3i0SD87G9xv7RGGjFddywEAAA==&view=Settings | S76: Secara Online | T76: Informasi | U76: - | V76: Aktif | W76: Tidak | X76: Tidak Terintegrasi | Y76: Manual | Z76: Realtime | AA76: bagian SDA | AB76: Setda, Dinkes, Disnaker, Dinsos, Disperdagin, Distan, Satpol PP | AC76: RUSLI BAIJURI,AP.M.KP | AE76: bagsdasetdakabbandung@gmail.com
A77: SETWAN
A78: 1 | B78: Layanan Penyerapan Asiparasi Masyarakat Kepada DPRD | C78: SETWAN | D78: Layanan Penyerapan Aspirasi Masyarakat kepada DPRD memungkinkan warga Kabupaten Bandung untuk mengungkapkan aspirasi, usulan, dan kekhawatiran mereka kepada DPRD. Warga Kabupaten Bandung dapat dengan mudah menulis pesan atau mengirimkan keluhan terkait isu-isu seperti infrastruktur, pendidikan,kesehatan, lingkungan, dan lainnya. | E78: Peraturan Bupati Bandung Nomor 245 Tahun 2023 Tentang Layanan Aspirasi Masyarakat Secara Elektronik Melalui DPRD Bedas Mendengar Rakyat Bandung (D'Benderang) | F78: https://drive.google.com/file/d/1Xev2F7vScZDTlBaqHqPh8lzFUMNB_y8a/view?usp=sharing | G78: PENINGKATAN KUALITAS PELAYANAN PUBLIK | H78: Masyarakat | I78: Data Pengaduan dan Aspirasi Masyarakat | J78: Data Pengaduan dan Aspirasi Masyarakat | K78: Terbuka | L78: Terdapat | M78: Harian | N78: D'benderang | O78: Diskominfo | P78: Kab. Bandung | Q78: Website | S78: Secara Online | T78: Transaksi | U78: 2022 | V78: Maintenance | W78: Tidak | Z78: Lainnya | AA78: Bagian Umum | AB78: Setwan | AC78: Hilmy Farhan | AD78: 816379600 | AG78: Harian
A79: 2 | B79: Layanan Sistem Informasi Hukum DPRD | C79: SETWAN | D79: Layanan Sistem Informasi Hukum DPRD merupakan layanan yang berada di Sekretariat DPRD yang memiliki manfaat agar seluruh masyarakat di kabupaten Bandung maupun Indonesia dapat mengakses seluruh produk hukum Peraturan Daerah (Perda), Peraturan DPRD, Surat Keputusan Pimpinan DPRD dan Surat Keputusan Sekretaris DPRD yang telah ditetapkan. | E79: Peraturan Presiden Nomor 33 Tahun 2012 tentang Jaringan Dokumentasi dan Informasi Hukum Nasional | G79: HUKUM DAN PERJANJIAN INTERNASIONAL | H79: Masyarakat | I79: Data Keputusan dan Peraturan DPRD | J79: Data Keputusan dan Peraturan DPRD | K79: Terbuka | L79: Tidak terdapat | M79: Harian | N79: Bersih DPRD | O79: Diskominfo | P79: Kab. Bandung | Q79: Website | R79: https://jdihdprd.bandungkab.go.id/ | S79: Secara Online | T79: Informasi | U79: 2022 | V79: Aktif | W79: Ya | X79: JDIH | Y79: API | Z79: Harian | AA79: Bagian Persidangan dan Perundang-undangan | AB79: Setwan | AC79: HAIFA NUR GHAIDA, S.I.Kom | AD79: 81313077230 | AG79: Harian
A80: 3 | B80: Layanan Penerimaan Tamu DPRD | C80: SETWAN | D80: Layanan Penerimaan Tamu DPRD merupakan Layanan penerimaan kunjungan Tamu baik DPRD maupun Sekretariat DPRD ke Kantor Sekretariat DPRD Kabupaten Bandung dalam rangka kunjungan kerja dan studi komparasi. | E80: Peraturan Bupati Bandung Nomor 49 Tahun 2016 Tentang Pengelolaan Tamu Dinas di Lingkungan Pemerintah Kabupaten Bandung | G80: INFORMASI DAN DIPLOMASI PUBLIK | H80: Instansi Pemerintah Lainnya | I80: Data Kunjungan Tamu DPRD | J80: Data Kunjungan Tamu DPRD | K80: Terbuka | O80: Diskominfo | P80: Kab. Bandung | R80: https://aplikasi.bandungkab.go.id/publik/dashboard-kunjungan-dprd-kab-bandung | S80: Secara Online | T80: Transaksi | U80: 2025 | V80: Aktif | W80: Ya | X80: Dashboard Kabupaten Bandung | Y80: API | Z80: Harian | AA80: Bagian Umum | AB80: Setwan | AC80: NOOR DINA CAMELIA, S.I.Kom | AD80: 895385108021 | AG80: Harian
A81: 4 | B81: Layanan MCU DPRD | C81: SETWAN | D81: Layanan MCU DPRD merupakan layanan pemeriksaan kesehatan kepada Anggota DPRD yang bertujuan untuk mengetahui status kesehatan di luar cakupan pelayanan kesehatan yang diberikan oleh Badan penyelenggara Jaminan Sosial Kesehatan | E81: Peraturan Pemerintah Republik Indonesia Nomor 18 Tahun 2017 Tentang Hak Keuangan dan Administratif Pimpinan dan Anggota DPRD | G81: INFORMASI DAN DIPLOMASI PUBLIK | H81: Instansi Pemerintah Lainnya | I81: Data MCU DPRD | J81: Data MCU DPRD | K81: Terbatas | L81: Terdapat | M81: Tahunan | S81: Secara Offline | T81: Transaksi | AA81: Bagian Program dan Keuangan | AB81: Setwan | AC81: THIA RAHMAWATI, S.E | AD81: 81322007652 | AG81: Tahunan
A82: INSPEKTORAT
A83: 1 | B83: Pengawasan real-time perkembangan proyek pembangunan fisik | C83: INSPEKTORAT | D83: Pengawasan real-time perkembangan proyek pembangunan fisik, mulai dari perencanaan hingga serah terima. Aplikasi ini juga mendukung Bupati dalam memantau proyek secara langsung serta berfungsi sebagai alat pelaksanaan probity audit oleh APIP. | E83: Peraturan Pemerintah Nomor 12 Tahun 2017 tentang Pembinaan dan Pengawasan Penyelenggaraan Pemerintahan Daerah | F83: https://drive.google.com/file/d/1YdxVCrqCKB2IhPmEjmI3enR0CnpLLtYZ/view?usp=sharing | G83: PENINGKATAN KUALITAS REFORMASI BIROKRASI, PENGAWASAN, DAN AKUNTABILITAS KINERJA | H83: Instansi Pemerintah Lainnya | I83: Database Objek Pemeriksaan, Data Inputan Laporan Hasil Pemeriksaan | J83: Laporan perkembangan proyek strategis secara real-time dan Dasbor monitoring | K83: Terbatas | L83: Tidak terdapat | M83: Bulanan | N83: SIMPRODAS | O83: Diskominfo | P83: Kab. Bandung | Q83: Website dan Mobile | R83: https://simprodas.bandungkab.go.id/ | S83: Secara Online | T83: Transaksi | U83: 2024 | V83: Aktif | W83: Tidak | X83: tidak terintegrasi | Y83: Tidak Terintegrasi | Z83: Tidak Terintegrasi | AA83: Inspektur Pembantu IV | AB83: Inspektorat | AC83: Naufal Rifki Pratama | AD83: 81776601960 | AE83: - | AF83: 37 | AG83: Bulanan
A84: 2 | B84: Pelayanan konsultasi pada APIP | C84: INSPEKTORAT | D84: Untuk membuat dan mengatur janji temu (sebagai layanan konsultasi) | F84: https://drive.google.com/file/d/1hfZl5u33jLRHizH-t5QZsOhlwNoiUSfh/view?usp=sharing | G84: PENINGKATAN KUALITAS PELAYANAN PUBLIK | H84: Instansi Pemerintah Lainnya | I84: Data Konsultasi Permasalahan | J84: Data Solusi Permasalahan | K84: Tertutup | L84: Tidak terdapat | M84: Mingguan | N84: SANTAI | O84: OPD | P84: Pihak Ke 3 (Lisensi) | Q84: Website | R84: https://calendly.com/inspekkabbdg/santai-saranatanyaapipinteraktif | S84: Secara Online | T84: Transaksi | U84: 2025 | V84: Aktif | W84: Tidak | X84: tidak terintegrasi | Y84: Tidak Terintegrasi | Z84: Tidak Terintegrasi | AA84: Sekertariat Inspektorat Daerah | AB84: Inspektorat | AC84: Yuda Maulid | AD84: 82117986701 | AE84: - | AF84: mungkin berkaitan dengan 27 | AG84: Harian
A85: 3 | B85: ZI | C85: INSPEKTORAT | D85: Meningkatkan kualitas substansi dan pemahaman SDM TPI (Tim Penilai Internal) dalam pembangunan Zona Integritas (ZI) agar hasil evaluasi internal lebih baik dan sesuai kriteria WBK/WBBM. Melaksanakan monitoring, evaluasi, serta penyusunan dokumen | E85: PermenPANRB 90/2021 tentang Pembangunan dan Evaluasi ZI Menuju WBK/WBBM. | G85: PENINGKATAN KUALITAS REFORMASI BIROKRASI, PENGAWASAN, DAN AKUNTABILITAS KINERJA | H85: Instansi Pemerintah Lainnya | I85: LHE (Laporan Hasil Evaluasi) | J85: Nilai Zona Integritas 2025 | K85: Tertutup | L85: Terdapat | M85: Lainnya | N85: BERSIH | O85: Pihak Ke 3 | P85: Kab. Bandung | Q85: Website | R85: Belum Launching | S85: Secara Online | T85: Transaksi | U85: Belum Launching | V85: Non Aktif | W85: Tidak | X85: tidak terintegrasi | Y85: Tidak Terintegrasi | Z85: Tidak Terintegrasi | AA85: Inspektur Pembantu III | AB85: Inspektorat | AC85: Wiwin | AD85: 82130540674 | AE85: - | AF85: - | AG85: Tahunan
A86: 4 | B86: Penilaian Managemen Resiko | C86: INSPEKTORAT | D86: Alat bantu digital yang memfasilitasi monitoring, evaluasi, dan pelaporan kinerja secara elektronik. Untuk mendukung pelaksanaan tugas pengawasan secara optimal, cepat, dan akurat. | E86: Permenpan RB Nomor 88 Tahun 2021 tentang Petunjuk Teknis Penyusunan Penilaian SAKIP; | G86: PENINGKATAN KUALITAS REFORMASI BIROKRASI, PENGAWASAN, DAN AKUNTABILITAS KINERJA | H86: Instansi Pemerintah Lainnya | I86: Dokumen pendukung SAKIP | J86: Hasil evaluasi SAKIP | K86: Tertutup | L86: Terdapat | M86: Tahunan | N86: SIMWAS | O86: Pihak Ke 3 | P86: Kab. Bandung | Q86: Website | R86: simwas.bandungkab.go.id | S86: Secara Online | T86: Transaksi | U86: 2025 | V86: Aktif | W86: Tidak | X86: tidak Terintegrasi | Y86: Tidak Terintegrasi | Z86: Tidak Terintegrasi | AA86: Inspektur Pembantu IV | AB86: Inspektorat | AC86: Ratna | AD86: 8132016216 | AE86: - | AF86: mungkin berkaitan dengan 27 | AG86: Tahunan
A87: 5 | B87: Pengawasan Tindak Lanjut Pemeriksaan APIP | C87: INSPEKTORAT | D87: Sistem Layanan untuk proses monitoring dan evaluasi tindak lanjut atas Laporan Hasil Pemeriksaan untuk Objek Pemeriksaan seperti, Perangkat Daerah, Kecamatan, Sekolah, Puskesmas, dsb. | E87: PERBUP NO 77 TAHUN 2023PEDOMAN PEMANTAUAN PELAKSANAAN TINDAK LANJUT REKOMENDASI HASIL PEMERIKSAAN APARAT PENG AW AS AN INTERN PEMERINTAH DI LINGKUNGAN PEMERINTAH DAERAH KABUPATEN BANDUNG | G87: PENINGKATAN KUALITAS REFORMASI BIROKRASI, PENGAWASAN, DAN AKUNTABILITAS KINERJA | H87: Instansi Pemerintah Lainnya | I87: Database Objek Pemeriksaan, Data Inputan Laporan Hasil Pemeriksaan | J87: Persentase Tindak Lanjut atas Laporan Hasil Pemeriksaan | K87: Rahasia | L87: Terdapat | M87: Lainnya | N87: SIMASLAHAT | O87: Pihak Ke 3 | P87: Kab. Bandung | Q87: Website | R87: https://simaslahat.bandungkab.go.id/ | S87: Secara Online | T87: Transaksi | U87: 2022 | V87: Aktif | W87: Tidak | X87: Tidak Terintegrasi | Y87: Tidak Terintegrasi | Z87: Tidak Terintegrasi | AA87: Sub Bagian Analisis dan Evaluasi | AB87: Inspektorat | AC87: Rani | AD87: 813-2247-5890 | AE87: - | AG87: Bulanan
A88: 6 | B88: Peilaian Sistem Akuntabilitas Kinerja Instansi Pemerintah (SAKIP) | C88: INSPEKTORAT | D88: Meningkatkan efisiensi pengawasan, pengelolaan data pengawasan yang terintegrasi, transparan, akuntabel, serta mendukung perencanaan, pelaksanaan, pelaporan, dan evaluasi kinerja APIP | E88: PermenPANRB 53/2014 tentang Perjanjian Kinerja dan Pelaporan Kinerja. PermenPANRB 88/2021 tentang Evaluasi AKIP. | G88: PENINGKATAN KUALITAS REFORMASI BIROKRASI, PENGAWASAN, DAN AKUNTABILITAS KINERJA | H88: Instansi Pemerintah Lainnya | I88: Data kinerja perangkat daerah. | J88: Laporan evaluasi kinerja | K88: Rahasia | L88: Terdapat | M88: Lainnya | O88: Pihak Ke 3 | P88: Kab. Bandung | Q88: Website | S88: Secara Online | V88: Aktif | W88: Ya | X88: SIMWAS | Z88: Lainnya | AA88: Inspektur Pembantu I | AB88: Inspektorat | AC88: Ilham Nurhidayat | AD88: 8.95358e+16 | AE88: - | AF88: mungkin berkaitan dengan 27 | AG88: Tahunan
A89: 7 | B89: Whistleblower System | C89: INSPEKTORAT | D89: Penanganan pengaduan tindak pidana korupsi di lingkungan Pemerintah Daerah | E89: MenPANRB Nomor 8/M.PAN-RB/06/2012 tentang Sistem Penanganan Pengaduan (Whistleblower System) | G89: PENINGKATAN KUALITAS REFORMASI BIROKRASI, PENGAWASAN, DAN AKUNTABILITAS KINERJA | H89: Masyarakat | I89: Laporan/pengaduan dugaan tindak pidana korupsi | J89: Laporan hasil penanganan | K89: Rahasia | L89: Terdapat | M89: Lainnya | N89: BDS | O89: Diskominfo | P89: Kab. Bandung | Q89: Website | R89: website (BEDAS Digital Services) | S89: Secara Online | T89: Informasi | U89: 2024 | V89: Aktif | W89: Tidak | X89: Tidak Terintegrasi | Y89: Tidak Terintegrasi | Z89: Lainnya | AA89: Inspektur Pembantu Khusus | AB89: Inspektorat | AC89: Aan | AD89: 87881227210 | AE89: - | AF89: - | AG89: Insidentil
A90: DISDIK
A91: 9 | B91: Standar Pelayanan Penerbitan Suket Pengganti Ijazah/STTB | C91: DISDIK | D91: Layanan masyarakat untuk mendapatkan surat keterangan pengganti ijazah/STTB apabila dokumen tersebut hilang, terdapat kesalahan penulisan, atau rusak. | E91: Undang-Undang Nomor 25 Tahun 2009 tentang Pelayanan Publik | F91: LAMPIRAN KEPUTUSAN KEPALA DINAS PENDIDIKAN : 9. Standar Pelayanan Penerbitan Suket Pengganti Ijazah/STTB | G91: PENINGKATAN KUALITAS PELAYANAN PUBLIK | H91: Masyarakat | I91: Dokumen yang diperlukan | J91: Surat Keterangan Pengganti | K91: Tertutup | L91: Terdapat | M91: Lainnya | N91: Sukizah | O91: Diskominfo | P91: Kab. Bandung | Q91: Website dan Mobile | R91: simpeldisdik.bandungkab.go.id/Sukizah | S91: Secara Online | T91: Transaksi | U91: 2024 | V91: Aktif | W91: Ya | X91: Simpel BKPSDM | Y91: Database to Database | Z91: Lainnya | AA91: Sekretariat | AB91: Disdik | AC91: Faturochman Nuroni | AD91: 85117111582 | AE91: - | AG91: Insidentil
A92: 13 | B92: Standar Pelayanan Fasilitasi Data Pokok Pendidikan (Dapodik) | C92: DISDIK | D92: Layanan masyarakat terkait status verifikasi di Dapodik seperti Penugasan Pendidik dan Tenaga Kependidikan, Peserta Didik, Kondisi Bangunan, Mutasi PTK, Manajemen Dapodik Sekolah, Validasi Akun Dapodik Sekolah, Sinkronisasi Data Dapodik, dll. | E92: Undang-Undang Nomor 25 Tahun 2009 tentang Pelayanan Publik | F92: LAMPIRAN KEPUTUSAN KEPALA DINAS PENDIDIKAN : 13. Standar Pelayanan Fasilitasi Data Pokok Pendidikan (Dapodik) | G92: PENINGKATAN KUALITAS PELAYANAN PUBLIK | H92: Masyarakat | I92: Surat pengantar/tugas | J92: Sinkronisasi atau verifikasi data | K92: Tertutup | L92: Tidak terdapat | M92: Bulanan | N92: Dapodik | O92: Pusat | P92: Pusat | Q92: Website | R92: https://dapo.kemendikdasmen.go.id/ | S92: Secara Online | T92: Informasi | U92: [Belum tahu] | V92: Aktif | X92: - | Z92: Bulanan | AA92: SD, SMP | AB92: Disdik | AC92: SD : Erik Sugiarto SMP : Lina Sarlina | AD92: 85117111582 | AE92: - | AG92: Insidentil
A93: 14 | B93: Penyediaan Website Untuk Sekolah-sekolah di kabupaten Bandung | C93: DISDIK | D93: Layanan bagi lembaga/yayasan PAUD, SD, SMP dan PNF yang ingin melakukan pembuatan website sebagai media Informasi dan Branding | E93: Undang-Undang Nomor 25 Tahun 2009 tentang Pelayanan Publik | G93: PENINGKATAN KUALITAS PELAYANAN PUBLIK | H93: Instansi Pemerintah Lainnya | I93: Data Sekolah | J93: Informasi Tampilan Data Sekolah | K93: Tertutup | L93: Tidak terdapat | M93: Lainnya | N93: Multisite Edu | O93: Diskominfo | P93: Kab. Bandung | Q93: Desktop | R93: simpeldisdik.bandungkab.go.id/MultisiteEdu | S93: Secara Online | T93: Informasi | U93: 2024 | V93: Aktif | W93: Tidak | X93: - | Y93: Tidak Terintegrasi | Z93: Tidak Terintegrasi | AA93: Sekretariat | AB93: Disdik | AC93: Raza Candra Anwar S.T | AD93: 85768637781 | AE93: razacandraanwar@gmail.com | AG93: Insidentil
A94: 16 | B94: Layanan SPMBE | C94: DISDIK | D94: Sistem Penerimaan Murid Baru. Layanan terhadap masyarakat dalam rangka penerima siswa baru untuk jenjang pendidikan dasar dan menengah. | E94: Peraturan Menteri Pendidikan Dasar dan Menengah Nomor 3 Tahun 2025 tentang Sistem Penerimaan Murid Baru (Permendikdasmen No. 3 Tahun 2025) | G94: PENDIDIKAN FORMAL PADA PENDIDIKAN ANAK USIA DINI, PENDIDIKAN DASAR, DAN PENDIDIKAN MENENGAH | H94: Masyarakat | I94: Data calon siswa | J94: Data Siswa baru | K94: Tertutup | L94: Terdapat | M94: Lainnya | N94: SPMBE | O94: Diskominfo | P94: Kab. Bandung | Q94: Website | R94: https://spmb.bandungkab.go.id/ | S94: Secara Online | T94: Informasi | U94: 2025 | V94: Aktif | W94: Tidak | X94: - | AA94: SD, SMP | AB94: Disdik | AC94: SD : SMP : | AD94: 87869520475 | AE94: - | AG94: Insidentil
A95: DINKES
A96: 1 | B96: Layanan Perizinan Perorangan | C96: DINKES | D96: Untuk mengeluarkan rekomendasi surat izin praktik bagi tenaga kesehatan | G96: PENGEMBANGAN DAN PEMBERDAYAAN SUMBER DAYA MANUSIA KESEHATAN | H96: Masyarakat | I96: verif pemohon registrasi fasyankes | J96: Data Rekomendasi Perizinan Perorangan Nakes | K96: Terbuka | L96: Terdapat | M96: Harian | N96: SAMIRINDU | O96: OPD | P96: Kab. Bandung | Q96: Website | R96: dpmptsp.bandungkab.go.id | S96: Secara Online | T96: Informasi | V96: Aktif | W96: Tidak | Y96: Manual | Z96: Harian | AA96: Bidang Sumber Daya Kesehatan | AB96: Dinkes | AC96: Arnaningsih | AD96: 82120399599 | AE96: perijinandinkes@gmail.com
A97: 2 | B97: Layanan PSC 119 (Public Safety Center) | C97: DINKES | D97: Untuk menangani kegawatdaruratan dan rujukan medis | G97: PENGELOLAAN PELAYANAN KESEHATAN | H97: Masyarakat | I97: Rujukan Kasus Gawat Darurat | J97: Data Kasus Gawat Darurat Pra Hospital | K97: Tertutup | L97: Terdapat | M97: Harian | N97: PSC Kemenkes | O97: Pusat | P97: Pusat | Q97: Website | R97: psc.kemkes.go.id | S97: Secara Online | T97: Informasi | U97: 2026 | V97: Aktif | W97: Tidak | Y97: Manual | Z97: Harian | AA97: Bidang Pelayanan Kesehatan | AB97: Dinkes | AC97: Ekawati Triyani | AD97: 811976661 | AE97: psc119bandungkab@gmail.com
A98: 3 | B98: Layanan Kesehatan Ibu dan Bayi Baru Lahir | C98: DINKES | D98: Untuk membantu menurunkan AKI dan AKB serta melakuakan informasi rujukan pada kasus kegawatdaruratan ibu dan bayi baru lahir | G98: PENGELOLAAN PELAYANAN KESEHATAN | H98: Masyarakat | I98: Rujukan Kasus Maternal Neonatal | J98: Data Panggilan Masuk Rujukan dan RS Rujukan | K98: Tertutup | L98: Terdapat | M98: Harian | N98: PSC Kemenkes | O98: Pusat | P98: Pusat | Q98: Website | R98: psc.kemkes.go.id | S98: Secara Online | T98: Informasi | U98: 2026 | V98: Aktif | W98: Tidak | Y98: Manual | Z98: Harian | AA98: Bidang Pelayanan Kesehatan | AB98: Dinkes | AC98: Ekawati Triyani | AD98: 811976661 | AE98: psc119bandungkab@gmail.com
A99: 4 | B99: Layanan Pendaftaran Pemeriksaan Laboratorium Kesehatan | C99: DINKES | D99: Untuk mengambil sampel dan pemeriksaan laboratorium klinis | J99: Data Riwayat Pasien | N99: SILABKES | O99: Pihak Ke 3 | Q99: Desktop
A100: 5 | B100: Layanan Surveilans Puskesmas dan Dinkes | C100: DINKES | D100: Untuk mendeteksi secara dini kejadian luar biasa dan wabah di suatu wilayah | G100: PENCEGAHAN DAN PENGENDALIAN PENYAKIT | H100: Masyarakat | J100: Data Peringatan Potensi KLB dan Wabah | K100: Tertutup | L100: Terdapat | M100: Mingguan | N100: APLIKASI Sistem Kewaspadaan Dini dan Respon | O100: Pusat | P100: Pusat | Q100: Website | R100: skdr.kemkes.go.id | S100: Secara Online | T100: Informasi | U100: 2015 | V100: Aktif | W100: Ya | Y100: API | Z100: Realtime | AA100: Bidang Pengendalian dan Pencegahan Penyakit | AB100: Dinkes | AC100: Stella Wirasto Dwiputra | AD100: 87822419136 | AE100: survimkabbandung@gmail.com
...

Sheet cleansing Kertas Kerja
A1: No | B1: Nama Layanan | C1: Tujuan dan Fungsi Layanan | D1: Dasar Hukum Layanan | E1: SOP / Proses Bisnis Layanan | F1: Referensi Layanan | G1: Target Layanan | H1: Data yang dimasukan | I1: Data yang dihasilkan | J1: Sifat Data | K1: Data Pribadi | L1: Interval update data yang dihasilkan | M1: Aplikasi Pendukung | N1: Pengembang | O1: Pemilik | P1: Platform | Q1: Alamat Aplikasi | R1: Kategori Akses | S1: Jenis Aplikasi | T1: Tahun Pembuatan | U1: Status Aplikasi | V1: Telah Terintegrasi | W1: Terintegrasi dengan Aplikasi | X1: Mekanisme Integrasi | Y1: Frekuensi Sinkronisasi | Z1: Bidang / Unit Kerja | AA1: OPD | AB1: Nama | AC1: No. HP | AD1: Email | AE1: Keterkaitan 58 Rencana Aksi | AF1: Frekuensi Penggunaan Aplikasi | AG1: TA
A2: 1 | B2: 2 | C2: 3 | D2: 4 | E2: 5 | F2: 6 | G2: 7 | H2: 8 | I2: 9 | J2: 10 | K2: 11 | L2: 12 | M2: 13 | N2: 14 | O2: 15 | P2: 16 | Q2: 17 | R2: 18 | S2: 19 | T2: 20 | U2: 21 | V2: 22 | W2: 23 | X2: 24 | Y2: 25 | Z2: 26 | AA2: 27 | AB2: 28 | AC2: 29 | AD2: 30 | AE2: 31 | AF2: 32 | AG2: 33
A3: 1 | B3: Layanan Radio Kandaga | C3: layanan bagi para pembicara yang telah menyampaiakan informasi melalui Podcast Radio Kandaga | F3: PENYIARAN RADIO PUBLIK | G3: Masyarakat | H3: Data Siaran atau Podcast | I3: Data Siaran atau Podcast | J3: Terbuka | L3: Tahunan | M3: KANDAGA | P3: Mobile | Q3: https://play.google.com/store/apps/details?id=com.diskominfo.radiokandagabedas&pcampaignid=web_share | Z3: Penyelenggaraan Informasi dan Komunikasi Publik | AA3: Diskominfo
A4: 2 | B4: Layanan Pembinaan dan Fasilitasi KIM | C4: Layanan Pembinaan dan Fasilitasi KIM: Mendorong pengembangan kawasan industri melalui pembinaan dan fasilitasi. | F4: PEMBERDAYAAN DAN PERAN MASYARAKAT | G4: Instansi Pemerintah Lainnya | H4: Data Peserta KIM | I4: Data Peserta KIM | J4: Terbatas | L4: Tahunan | M4: KIM | O4: Pusat | P4: Website | Q4: https://kimonline.bandungkab.go.id/ kim/ | AA4: Diskominfo
A5: 3 | B5: Layanan Portal Aplikasi | C5: Layanan Portal Aplikasi: Memberikan akses terpadu ke berbagai aplikasi pemerintah daerah. | F5: PENATAKELOLAAN APLIKASI INFORMATIKA | G5: Instansi Pemerintah Lainnya | H5: Data Portal Layanan | I5: Data Portal Layanan | J5: Terbuka | L5: Tahunan | M5: PORTAL KAB BANDUNG | N5: Diskominfo | O5: Kab. Bandung | P5: Website | Q5: https://bandungkab.go.id/ | AA5: Diskominfo
A6: 4 | B6: Layanan Smart CIty | C6: Layanan Smart City: Mengintegrasikan teknologi untuk meningkatkan efisiensi dan kualitas hidup warga dalam konteks perkotaan. | F6: PENINGKATAN KUALITAS PELAYANAN PUBLIK | G6: Masyarakat | H6: Data Smart City | I6: Data Smart City | J6: Terbuka | L6: Tahunan | M6: SMART CITY | P6: Website | Q6: https://smartcity.bandungkab.go.id/ | AA6: Diskominfo
A7: 5 | B7: Layanan Sistem Informasi Tindak Lanjut Hasil Layanan Terpadu | C7: Layanan Sistem Informasi Tindak Lanjut Hasil Layanan Terpadu mengacu pada sistem informasi berbasis web untuk mengelola dan memantau proses tindak lanjut (TL) hasil rekomendasi pemeriksaan oleh lembaga seperti Badan Pemeriksa Keuangan (BPK), agar prosesnya menjadi lebih efisien, transparan, dan akuntabel melalui digitalisasi data dan komunikasi online secara real-time antara BPK dan entitas yang diperiksa. | D7: Undang-Undang Nomor 25 Tahun 2009 tentang Pelayanan Publik, Peraturan Pemerintah Nomor 96 Tahun 2012 | F7: PENINGKATAN KUALITAS PELAYANAN PUBLIK | G7: Instansi Pemerintah Lainnya | H7: Data Evidence Tindak Lanjut yang Direkomendasikan | I7: Data Hasil Tindak Lanjut | J7: Terbatas | K7: Tidak terdapat | L7: Tahunan | M7: SIMASLAHAT | N7: Pihak Ke 3 | O7: Kab. Bandung | P7: Website | Q7: https://simaslahat.bandungkab.go.id | R7: Secara Online | S7: Transaksi | T7: 2022 | U7: Aktif | V7: Tidak | W7: Tidak Terintegrasi | X7: Tidak Terintegrasi | Y7: Tidak Terintegrasi | Z7: Bagian Perencanaan dan Keuangan | AA7: Setda | AB7: VERRYNOVYANDI SADIKIN, SE., MM | AC7: 895327038135 | AD7: setdakab.bdg@gmail.com | AE7: - | AF7: Tahunan
A8: 6 | B8: Layanan Pengaduan Masyarakat | C8: Layanan Pengaduan Masyarakat (LPM) adalah wadah atau sistem yang disediakan oleh instansi pemerintah (atau lembaga publik lainnya) bagi masyarakat untuk menyampaikan keluhan, saran, masukan, aspirasi, hingga laporan atas dugaan penyimpangan atau maladministrasi dalam penyelenggaraan pemerintahan dan pelayanan publik. | D8: Undang-Undang Nomor 25 Tahun 2009 tentang Pelayanan Publik | F8: PENINGKATAN KUALITAS PELAYANAN PUBLIK | G8: Masyarakat | H8: Data Pengguna, Data Adun | I8: Data Aduan Masyarakat | J8: Terbatas | K8: Terdapat | L8: Harian | M8: SP4N Lapor | N8: Pusat | O8: Pusat | P8: Website | Q8: https://lapor.go.id/ | R8: Secara Online | S8: Informasi | T8: 2018 | U8: Aktif | V8: Tidak | W8: Tidak Terintegrasi | X8: Tidak Terintegrasi | Y8: Tidak Terintegrasi | Z8: Bidang Informasi Komunikasi Publik | AA8: Diskominfo | AB8: ALIPHIO DYAKSHA PUTRA, A.Md.Ak. | AC8: 8988005270 | AD8: setdakab.bdg@gmail.com | AE8: - | AF8: Insidentil
A9: 7 | B9: Layanan Data Sektoral | C9: Layanan data sektoral adalah statistik yang dihasilkan oleh instansi pemerintah pusat atau daerah sesuai dengan tugas dan fungsi masing-masing, yang bertujuan untuk memenuhi kebutuhan internal instansi tersebut dalam penyelenggaraan pemerintahan dan pembangunan. | D9: PERATURAN BADAN PUSAT STATISTIK NOMOR 3 TAHUN 2022 TENTANG EVALUASI PENYELENGGARAAN STATISTIK SEKTORAL | F9: PENGELOLAAN DATA STATISTIK | G9: Instansi Pemerintah Lainnya | H9: Data Sektoral | I9: Data Sektoral | J9: Terbatas | K9: Tidak terdapat | L9: Tahunan | M9: SIMASDA | N9: Diskominfo | O9: Kab. Bandung | P9: Website | Q9: https://simasda.bandungkab.go.id/ | R9: Secara Online | S9: Informasi | T9: 2022 | U9: Aktif | V9: Ya | W9: Terintegrasi dengan Bedas, E-Walidata dan Satu Data Kab Bandung | X9: Database to Database | Y9: Realtime | Z9: Bidang Statistik | AA9: Diskominfo | AB9: DHANTI AURILIA PRATIWI, M.Stat | AC9: 81904085710 | AD9: setdakab.bdg@gmail.com
A10: 8 | B10: Layanan Rekonsiliasi Pajak Pusat | C10: Rekonsiliasi pajak pusat atas belanja daerah adalah proses penyesuaian atau pencocokan antara jumlah pajak yang harus dibayarkan oleh pemerintah daerah kepada pemerintah pusat dengan total belanja yang telah dilakukan oleh pemerintah daerah dalam kerangka Anggaran Pendapatan dan Belanja Daerah (APBD) | D10: PERBUP Nomor 165 Tahun 2021 dan PERBUP Nomor 289 Tahun 2022 | F10: AKUNTANSI DAN PELAPORAN KEUANGAN | G10: Instansi Pemerintah Lainnya | H10: Data Pajak Pusat (ID Billing & NTPN) | I10: Rekap Data Pajak Pusat | J10: Tertutup | K10: Terdapat | L10: Harian | M10: SIREKON | N10: Pihak Ke 3 | O10: Kab. Bandung | P10: Website | Q10: https://sirekonpajak.bandungkab.go.id/ | R10: Secara Online | S10: Informasi | T10: 2020 | U10: Aktif | V10: Tidak | W10: Tidak Terintegrasi | X10: Tidak Terintegrasi | Y10: Tidak Terintegrasi | Z10: Bagian Perencanaan dan Keuangan | AA10: BKAD | AB10: VERRYNOVYANDI SADIKIN, SE., MM | AC10: 895327038135 | AD10: setdakab.bdg@gmail.com | AE10: - | AF10: Bulanan
A11: 9 | B11: Layanan Pajak | C11: Fungsi layanan pajak meliputi pengumpulan pajak daerah, pengelolaan data wajib pajak, pengawasan kepatuhan, serta penyediaan kemudahan pembayaran menggunakan aplikasi digital yang mendukung optimalisasi penerimaan pajak dan peningkatan kualitas pelayanan kepada masyarakat. | D11: UU No. 1 Tahun 2022 | F11: AKUNTANSI DAN PELAPORAN KEUANGAN | G11: Instansi Pemerintah Lainnya | H11: Data Pajak | I11: ID Billing | J11: Terbatas | K11: Terdapat | L11: Harian | M11: Coretax | N11: Pusat | O11: Pusat | P11: Website | Q11: coretaxdjp.pajak.go.id | R11: Secara Online | S11: Informasi | T11: 2025 | U11: Aktif | V11: Tidak | W11: Tidak Terintegrasi | X11: Tidak Terintegrasi | Y11: Tidak Terintegrasi | Z11: Bagian Perencanaan dan Keuangan | AA11: BKAD | AB11: VERRYNOVYANDI SADIKIN, SE., MM | AC11: 895327038135 | AD11: setdakab.bdg@gmail.com | AE11: - | AF11: Harian
A12: 10 | B12: Layanan Pajak Daerah | C12: Pajak daerah yang ada digunakan untuk membiayai semua kepentingan umum. Termasuk untuk membuka lapangan kerja baru, sehingga terjadi pemerataan pendapatan agar kesenjangan ekonomi antara yang kaya dan miskin tidak terlalu menonjol. Pajak daerah diharapkan dapat meningkatkan pemerataan di setiap daerah. | D12: Undang-Undang Nomor 28 Tahun 2009 tentang Pajak Daerah dan Retribusi Daerah (UU PDRD) | F12: AKUNTANSI DAN PELAPORAN KEUANGAN | G12: Instansi Pemerintah Lainnya | H12: Data Pajak Daerah | I12: Data Rekap Pajak Daerah | J12: Terbatas | K12: Tidak terdapat | L12: Harian | M12: E-SPTPD | N12: Pihak Ke 3 | O12: Kab. Bandung | P12: Website dan Mobile | Q12: https://e-sptpd.bandungkab.go.id/ | R12: Secara Online | S12: Informasi | T12: 2019 | U12: Aktif | V12: Tidak | W12: Tidak Terintegrasi | X12: Tidak Terintegrasi | Y12: Tidak Terintegrasi | Z12: Bagian Perencanaan dan Keuangan | AA12: Setda, Bapenda | AB12: VERRYNOVYANDI SADIKIN, SE., MM | AC12: 895327038135 | AD12: setdakab.bdg@gmail.com | AE12: - | AF12: Harian
A13: 11 | B13: Layanan Transaksi | C13: Fungsi utama layanan transaksi di Kabupaten Bandung adalah untuk memudahkan masyarakat dalam memenuhi kewajiban pembayaran pajak daerah dan mendukung efisiensi pengelolaan pajak oleh pemerintah daerah. Layanan ini meliputi berbagai fasilitas dan sistem, seperti pengesahan STNK, pembayaran PKB, dan pemanfaatan teknologi untuk pelaporan data transaksi usaha secara online. | D13: Peraturan Bupati (Perbup) Kabupaten Bandung Nomor 22 Tahun 2018 tentang Implementasi Transaksi Non Tunai, yang telah beberapa kali diubah dengan Perbup Nomor 6 Tahun 2020 dan Perbup Nomor 15 Tahun 2020. | F13: AKUNTANSI DAN PELAPORAN KEUANGAN | G13: Instansi Pemerintah Lainnya | H13: Data Transaksi | I13: Data Rekening Koran | J13: Terbatas | K13: Tidak terdapat | L13: Lainnya | M13: IBC (Internet Banking Corporate) | N13: Pihak Ke 3 | O13: Pihak Ke 3 (Lisensi) | P13: Desktop | Q13: Aplikasi dari BJB | R13: Secara Online | S13: Transaksi | T13: 2019 | U13: Aktif | V13: Tidak | W13: Tidak Terintegrasi | X13: Tidak Terintegrasi | Y13: Tidak Terintegrasi | Z13: Bagian Perencanaan dan Keuangan | AA13: Setda | AB13: VERRYNOVYANDI SADIKIN, SE., MM | AC13: 895327038135 | AD13: setdakab.bdg@gmail.com | AE13: - | AF13: Harian
A14: 12 | B14: Layanan Penatausahaan Keuangan | C14: Fungsi layanan penatausahaan keuangan di Kabupaten Bandung adalah mencatat dan menyimpan semua transaksi penerimaan dan pengeluaran kas daerah secara akurat dan tertib untuk penyusunan laporan keuangan, pengendalian APBD, serta penyediaan data dan informasi keuangan yang dapat dipertanggungjawabkan. Penatausahaan ini mendukung efektivitas pengelolaan keuangan daerah dan memastikan transparansi serta akuntabilitas dalam penggunaan dana publik. | D14: Peraturan Bupati (Perbup) Kabupaten Bandung Nomor 48 Tahun 2025 tentang Perubahan Atas Peraturan Bupati Nomor 83 Tahun 2024 | F14: AKUNTANSI DAN PELAPORAN KEUANGAN | G14: Instansi Pemerintah Lainnya | H14: Data APBD | I14: Data APBD | J14: Tertutup | K14: Terdapat | L14: Lainnya | M14: SIPD | N14: Pusat | O14: Pusat | P14: Website | Q14: sipd.kemendagri.go.id | R14: Secara Online | S14: Transaksi | T14: 2021 | U14: Aktif | V14: Tidak | W14: Tidak Terintegrasi | X14: Tidak Terintegrasi | Y14: Tidak Terintegrasi | Z14: Bagian Perencanaan dan Keuangan | AA14: Setda | AB14: VERRYNOVYANDI SADIKIN, SE., MM | AC14: 895327038135 | AD14: setdakab.bdg@gmail.com | AE14: - | AF14: Harian
A15: 13 | B15: Layanan Tata Naskah Dinas | C15: Fungsi utama layanan Tata Naskah Dinas (TND) di Kabupaten Bandung adalah untuk menciptakan kelancaran komunikasi tertulis yang efektif dan efisien, memastikan keotentikan, keterpercayaan, kepastian, dan akuntabilitas informasi, serta mendukung terwujudnya tata kelola pemerintahan yang baik (good governance) melalui penerapan penggunaan naskah dinas secara elektronik. TND juga berfungsi sebagai sarana untuk mengatur jenis dan penyusunan naskah dinas, penggunaan lambang negara dan cap dinas, serta penggunaan bahasa Indonesia yang sesuai dalam komunikasi resmi. | D15: Peraturan Bupati (PERBUP) Nomor 82 Tahun 2024 tentang Pedoman Tata Naskah Dinas di Lingkungan Pemerintah Kabupaten Bandung. | F15: PENATAAN SISTEM TATA LAKSANA | G15: Instansi Pemerintah Lainnya | H15: Naskah Surat | I15: Surat yang dilegalisasi | J15: Terbatas | K15: Tidak terdapat | L15: Harian | M15: SULTAN (e-office) | N15: Diskominfo | O15: Kab. Bandung | P15: Website dan Mobile | Q15: https://sultan.bandungkab.go.id/ | R15: Secara Online | S15: Informasi | T15: 2025 | U15: Aktif | V15: Ya | W15: Terintegrasi dengan SIPPHADE, dll | X15: Web Service | Y15: Realtime | Z15: Semua Bagian | AA15: Setda | AB15: ALIPHIO DYAKSHA PUTRA, A.Md.Ak. | AC15: 8988005270 | AD15: setdakab.bdg@gmail.com | AE15: - | AF15: Harian
A16: 14 | B16: Layanan Perencanaan BMD | C16: Untuk mengidentifikasi kebutuhan aset, merencanakan pengadaan, pemanfaatan, pemeliharaan, dan pengelolaan aset agar sesuai dengan tugas dan fungsi SKPD, mendukung pelayanan publik, dan memastikan pengelolaan yang akuntabel dan transparan sesuai regulasi. Layanan ini bertujuan untuk menciptakan pengelolaan aset yang efisien dan efektif, mencegah pemborosan, serta mengoptimalkan penggunaan aset daerah untuk pembangunan. | D16: Undang-Undang Nomor 1 Tahun 2004 tentang Perbendaharaan Negara, Peraturan Pemerintah Nomor 27 Tahun 2014 tentang Pengelolaan BMD. | F16: PERENCANAAN PEMBANGUNAN | G16: Instansi Pemerintah Lainnya | H16: Data Kebutuhan Aset | I16: Pengadaan Aset | J16: Terbatas | K16: Tidak terdapat | L16: Tahunan | M16: SSH SBU | N16: OPD | O16: Kab. Bandung | P16: Website | Q16: sshsbu.e-planningbmd.id | R16: Secara Online | S16: Informasi | U16: Aktif | V16: Tidak | W16: Tidak Terintegrasi | X16: Tidak Terintegrasi | Y16: Tidak Terintegrasi | Z16: Bagian Perencanaan dan Keuangan | AA16: BKAD | AB16: YATI KURNIATI, SE., M.K.P. | AC16: 81321814674 | AD16: bagianprogramsetdakab.bandung@gmail.com | AE16: - | AF16: Tahunan
A17: 15 | B17: Layanan Statistik | C17: Indonesia Data Hub merupakan one stop collaboration platform yang bertujuan untuk meningkatkan literasi data dan value of statistics serta mendukung interoperabilitas data dan kolaborasi eksplorasi terhadap data. | D17: Undang-Undang Nomor 16 Tahun 1997 tentang Statistik sebagai dasar umum, serta Peraturan Presiden Nomor 86 Tahun 2007 dan Peraturan Kepala Badan Pusat Statistik (BPS) Nomor 78 Tahun 2020 yang mengatur pelayanan statistik terpadu di tingkat pusat. | F17: PENGELOLAAN DATA STATISTIK | G17: Instansi Pemerintah Lainnya | H17: Metadata dan Standar Data Statistik | I17: Metadata dan Standar Data Statistik | J17: Terbuka | K17: Tidak terdapat | L17: Lainnya | M17: INDAH | N17: Pusat | O17: Pusat | P17: Website | Q17: https://indah.bps.go.id/ | R17: Secara Online | S17: Informasi | T17: 2019 | U17: Aktif | V17: Ya | W17: Terintegrasi dengan Aplikasi Romantik | X17: Web Service | Y17: Realtime | Z17: Bagian Perencanaan dan Keuangan | AA17: Setda | AB17: DHANTI AURILIA PRATIWI, M.Stat | AC17: 81904085710 | AD17: setdakab.bdg@gmail.com | AE17: - | AF17: Tahunan
A18: 16 | B18: Layanan Informasi Pengawasan SAKIP, SPIP, MR | C18: Fungsinya adalah menyediakan data dan laporan pengawasan yang terintegrasi untuk mendukung perbaikan tata kelola, meningkatkan transparansi, mengurangi potensi penyimpangan, dan memperkuat pengambilan keputusan berbasis bukti dalam rangka mewujudkan pemerintahan yang efektif, efisien, dan akuntabel. | D18: Nomor 60 Tahun 2008 tentang Sistem Pengendalian Intern Pemerintah (SPIP), Peraturan Presiden (Perpres) Nomor 29 Tahun 2014 tentang Sistem Akuntabilitas Kinerja Instansi Pemerintah (SAKIP). | F18: PENINGKATAN KUALITAS PELAYANAN PUBLIK | G18: Instansi Pemerintah Lainnya | H18: Data Evidence SAKIP, SPIP, MR | I18: Nilai SAKIP dan MR | J18: Terbatas | K18: Tidak terdapat | L18: Tahunan | M18: SIMWAS | N18: Pihak Ke 3 | O18: Kab. Bandung | P18: Website | Q18: simwas.bandungkab.go.id | R18: Secara Online | S18: Transaksi | T18: 2022 | U18: Aktif | V18: Tidak | W18: Tidak Terintegrasi | X18: Tidak Terintegrasi | Y18: Tidak Terintegrasi | Z18: Bagian Perencanaan dan Keuangan | AA18: Setda, Inspektorat | AB18: DEBI RIANA S.STP., M.Si. | AC18: 8127392553 | AD18: setdakab.bdg@gmail.com | AE18: mungkin berkaitan dengan 27 | AF18: Tahunan
A19: 17 | B19: Layanan Informasi Data, Pengendalian, Evaluasi, dan Pelaporan | C19: Mencakup penyediaan dan pengelolaan data dan informasi pembangunan, pemantauan dan pengendalian pelaksanaan program/kegiatan, serta penyusunan laporan hasil evaluasi untuk mendukung perumusan kebijakan dan pengambilan keputusan. Layanan ini bertugas menganalisis data, mengoordinasikan evaluasi, dan menyusun pelaporan program pembangunan daerah. | D19: Undang-Undang Nomor 14 Tahun 2008 tentang Keterbukaan Informasi Publik, Undang-Undang Nomor 25 Tahun 2009 tentang Pelayanan Publik. | F19: PENINGKATAN KUALITAS REFORMASI BIROKRASI, PENGAWASAN, DAN AKUNTABILITAS KINERJA | G19: Instansi Pemerintah Lainnya | H19: Data Kinerja dan Realisasi Anggaran | I19: Data Capaian Kinerja dan Realisasi Anggaran | J19: Terbatas | K19: Tidak terdapat | L19: Lainnya | M19: SIDALMONEP | N19: OPD | O19: Kab. Bandung | P19: Website | Q19: sidalmonep.bandungkab.go.id/ | R19: Secara Online | S19: Informasi | T19: 2021 | U19: Aktif | V19: Tidak | W19: SIPD | X19: API | Y19: Realtime | Z19: Bagian Perencanaan dan Keuangan | AA19: Setda, Bapperida | AB19: YATI KURNIATI, SE., M.K.P. | AC19: 81321814674 | AD19: bagianprogramsetdakab.bandung@gmail.com | AE19: - | AF19: Tahunan
A20: 18 | B20: Layanan Pengelolaan Administrasi Kepegawaian | C20: mengelola administrasi, pengembangan, dan pelayanan pegawai secara efektif untuk mendukung kinerja Sekretariat Daerah. Fungsinya meliputi penyiapan bahan kebijakan, manajemen mutasi, kenaikan pangkat, pensiun, disiplin, hingga pengembangan kompetensi pegawai | D20: Undang-Undang Nomor 20 Tahun 2023 tentang Aparatur Sipil Negara | F20: PENATAAN SUMBER DAYA MANUSIA APARATUR | G20: Pegawai | H20: Data Kepegawaian | I20: Data Kepegawaian | J20: Terbatas | K20: Terdapat | L20: Harian | M20: SIMPEL BKPSDM | N20: Diskominfo | O20: Kab. Bandung | P20: Website | Q20: https://simpelbkpsdm.bandungkab.go.id/ | R20: Secara Online | S20: Informasi | U20: Aktif | V20: Ya | W20: Terintegrasi | X20: Database to Database | Y20: Realtime | Z20: Bagian Umum | AA20: BKPSDM | AB20: Iman Herman Sudrajat, S.IP. | AD20: bag_umum@bandungkab.go.id | AE20: 28 | AF20: Harian
A21: 19 | B21: Layanan Piagam Penghargaan Bupati Bandung | C21: Layanan Fasilitasi Piagam Penghargaan Bupati berupa administrasi penerbitan, penyiapan naskah, dan pendokumentasian piagam penghargaan Bupati Bandung | D21: Peraturan Bupati (PERBUP) Nomor 82 Tahun 2024 tentang Pedoman Tata Naskah Dinas di Lingkungan Pemerintah Kabupaten Bandung. | F21: PENINGKATAN KUALITAS PELAYANAN PUBLIK | G21: Instansi Pemerintah Lainnya | H21: Permohonan Piagam | I21: Naskah dan Dokumen Piagam | J21: Terbatas | K21: Tidak terdapat | L21: Lainnya | M21: Microsoft Excel | N21: OPD | O21: Kab. Bandung | P21: Desktop | Q21: - | R21: Secara Offline | S21: Informasi | U21: Aktif | V21: Tidak | W21: Tidak Terintegrasi | X21: Tidak Terintegrasi | Y21: Tidak Terintegrasi | Z21: Bagian Umum | AA21: Setda | AB21: Iman Herman Sudrajat, S.IP. | AD21: bag_umum@bandungkab.go.id | AE21: 28 | AF21: Harian
A22: 20 | B22: Layanan Informasi Akuntabilitas Kinerja | C22: Layanan Sistem Informasi Akuntabilitas Kinerja adalah sebuah sistem elektronik yang digunakan oleh instansi pemerintah untuk mengelola, mengukur, dan melaporkan kinerja secara terukur dan transparan. Sistem ini bertujuan untuk mewujudkan pemerintahan yang akuntabel, efektif, dan efisien, serta memberikan pertanggungjawaban atas penggunaan anggaran dan pencapaian tujuan organisasi kepada masyarakat. | D22: Peraturan Presiden Nomor 29 Tahun 2014 tentang Sistem Akuntabilitas Kinerja Instansi Pemerintah, serta peraturan pelaksanaannya seperti Peraturan Menteri Pendayagunaan Aparatur Negara dan Reformasi Birokrasi Nomor 88 Tahun 2021 tentang Evaluasi Akuntabilitas Kinerja Instansi Pemerintah | F22: PENINGKATAN KUALITAS REFORMASI BIROKRASI, PENGAWASAN, DAN AKUNTABILITAS KINERJA | G22: Instansi Pemerintah Lainnya | H22: Data Akuntabilitas Kinerja | I22: Data Akuntabilitas Kinerja | J22: Terbatas | K22: Tidak terdapat | L22: Tahunan | M22: SIAKANG | N22: OPD | O22: Kab. Bandung | P22: Website dan Mobile | Q22: siakang.bandungkab.go.id | R22: Secara Online | S22: Informasi | T22: 2023 | U22: Aktif | V22: Tidak | W22: Tidak Terintegrasi | X22: Tidak Terintegrasi | Y22: Tidak Terintegrasi | Z22: Bagian Organisasi | AA22: Setda | AB22: IRMA PURNAMA, S.STP, M.Tr.A.P | AC22: 85218888714 | AD22: setdakab.bdg@gmail.com
A23: 21 | B23: Layanan Reformasi Birokrasi | C23: Fungsi utama layanan Reformasi Birokrasi (RB) di Kabupaten Bandung adalah meningkatkan birokrasi yang bersih dan akuntabel, pelayanan publik yang prima, serta efektivitas kelembagaan agar menjadi organisasi yang adaptif, inovatif, dan berintegritas tinggi dalam melayani masyarakat. Tujuannya adalah menciptakan aparatur negara yang profesional, profesional, dan sejahtera, yang bekerja dengan integritas tinggi untuk memberikan pelayanan terbaik kepada masyarakat. | D23: Perpres No. 81 Tahun 2010 tentang Grand Design RB, Perbup No. 286 Tahun 2022 tentang Roadmap Reformasi Birokrasi Kabupaten Bandung. | F23: PROTOKOL DAN KONSULER | G23: Instansi Pemerintah Lainnya | H23: Data Capaian dan Evidence setiap Indikator RB | I23: Indeks Reformasi Birokrasi (IRB) | J23: Terbatas | K23: Tidak terdapat | L23: Tahunan | M23: SURABI | N23: Provinsi | O23: Provinsi | P23: Website dan Mobile | Q23: https://surabi.jabarprov.go.id/ | R23: Secara Online | S23: Informasi | T23: 2023 | U23: Aktif | V23: Tidak | W23: Tidak Terintegrasi | X23: Tidak Terintegrasi | Y23: Tidak Terintegrasi | Z23: Bagian Organisasi | AA23: Setda | AB23: IRMA PURNAMA, S.STP, M.Tr.A.P | AC23: 85218888714 | AD23: setdakab.bdg@gmail.com
A24: 22 | B24: Layanan Survey Kepuasan Masyarakat | C24: Fungsi utama layanan Survey Kepuasan Masyarakat (SKM) di Kabupaten Bandung adalah mengukur tingkat kepuasan masyarakat terhadap kualitas layanan publik yang diberikan oleh instansi pemerintah daerah, guna mengidentifikasi kelemahan dan kekurangan untuk selanjutnya menetapkan kebijakan dan tindakan perbaikan yang bertujuan meningkatkan kualitas pelayanan di masa mendatang. | D24: Undang-Undang Nomor 25 Tahun 2009 tentang Pelayanan Publik dan Peraturan Menteri Pendayagunaan Aparatur Negara dan Reformasi Birokrasi (PermenPAN-RB) Nomor 14 Tahun 2017 tentang Pedoman Penyusunan Survei Kepuasan Masyarakat Unit Penyelenggara Pelayanan Publik. | F24: PENINGKATAN KUALITAS PELAYANAN PUBLIK | G24: Masyarakat | H24: Hasil Survei Kepuasan Masyarakat | I24: Nilai Survei Kepuasan Masyarakat | J24: Terbatas | K24: Terdapat | L24: Lainnya | M24: E-SKM | N24: Diskominfo | O24: Kab. Bandung | P24: Website dan Mobile | Q24: https://skm.bandungkab.go.id/ | R24: Secara Online | S24: Informasi | T24: 2021 | U24: Aktif | V24: Tidak | W24: Tidak Terintegrasi | X24: Tidak Terintegrasi | Y24: Tidak Terintegrasi | Z24: Bagian Organisasi | AA24: Setda | AB24: RAFSANJANI M. AMIN, S.STP | AC24: 82190093518 | AD24: setdakab.bdg@gmail.com
A25: 23 | B25: Layanan Tambahan Penghasilan ASN | C25: Tujuannya untuk menyusun Kepbup besaran TPP-ASN dan Memberi kemudahan dalam penyusunan TPP-ASN dan mengontrol realisasi TPP setiap Perangkat Daerah | D25: Pasal 58-PP 12/2019 Tentang PENGELOLAAN KEUANGAN DAERAH, Permendagri 14/2025 Tentang PEDOMAN PENYUSUNAN ANGGARAN PENDAPATAN DAN BELANJA DAERAH TAHUN ANGGARAN 2026 Kepmendagri 900.1.3.2-1287 Tahun 2024 Tentang Tata Cara Persetujuan Menteri Dalam Negeri Terhadap Pemberian Tambahan Penghasilan Pegawai Aparatur Sipil Negara di Pemerintah Daerah | F25: PENINGKATAN KUALITAS REFORMASI BIROKRASI, PENGAWASAN, DAN AKUNTABILITAS KINERJA | G25: Pegawai | H25: Data Jabatan, Jumlah Pegawai dan Pagu Anggaran | I25: Keputusan Bupati Tentang Besaran TPP-ASN | J25: Terbatas | K25: Terdapat | L25: Bulanan | M25: SITAMPAN | N25: Pihak Ke 3 | O25: Kab. Bandung | P25: Website dan Mobile | Q25: https://sitampan-insaba.web.app/ | R25: Secara Online | S25: Transaksi | T25: 2025 | U25: Aktif | V25: Tidak | W25: Belum Terintegrasi | X25: Tidak Terintegrasi | Y25: Realtime | Z25: Bagian Organisasi | AA25: Setda | AB25: IRMA PURNAMA, S.STP, M.Tr.A.P | AC25: 85218888714 | AD25: setdakab.bdg@gmail.com
A26: 24 | B26: Layanan Informasi Agenda Pimpinan | C26: Fungsi Utama layanan agenda pimpinan adalah agar PD dan ASN di pemerintah kabupaten bandung dapat dengan mudah melihat detail jadwal Bapak Bupati dan mengajukan permohonan untuk mengundang Bapak Bupati | F26: PENINGKATAN KUALITAS PELAYANAN PUBLIK | G26: Pegawai | H26: Data Pengajuan Agenda | I26: Data Agenda Pimpinan | J26: Terbatas | K26: Tidak terdapat | L26: Harian | M26: SIAGAN BEDAS | N26: Diskominfo | O26: Kab. Bandung | P26: Website dan Mobile | Q26: https://play.google.com/store/apps/details?id=com.diskominfo.siagan_bedas&hl=id | R26: Secara Online | S26: Informasi | T26: 2023 | U26: Aktif | V26: Tidak | W26: Tidak Terintegrasi | X26: Tidak Terintegrasi | Y26: Tidak Terintegrasi | Z26: Bagian Prokopim | AA26: Setda | AB26: Ira | AC26: 85294019899 | AD26: - | AE26: - | AF26: Harian
A27: 25 | B27: Analisi Media Monitoring | F27: INFORMASI DAN DIPLOMASI PUBLIK | G27: Pelaku Bisnis | H27: Data berita dan sosial media | I27: Statistik Data berita & sosial medi | J27: Rahasia | K27: Tidak terdapat | L27: Harian | M27: SIMANIS | N27: Diskominfo | O27: Kab. Bandung | P27: Website | Q27: {{need url}} | R27: Secara Online | S27: Informasi | T27: 2024 | U27: Non Aktif | V27: Ya | W27: Web Prokopim | X27: API | Y27: Realtime | Z27: Bagian Prokopim | AA27: Setda | AB27: Vita | AC27: 62 813-1222-9386 | AE27: Semua | AF27: Harian
A28: 26 | B28: Layanan Informasi Nama Rupabumi | C28: Fungsi utama layanan aplikasi adalah melaksanakan Penyelenggaraan Nama Rupabumi pada tahapan pendataan Nama Rupabumi dan penelaaahan Nama Rupabumi dengan output berupa Nama Rupabumi baku beserta atributnya sebagai dasar penyusunan Gazeter RI | D28: PP Nomor 2 Tahun 2021 tentang Penyelenggaraan Nama Rupabumi | F28: PEMBINAAN ADMINISTRASI KEWILAYAHAN | G28: Instansi Pemerintah Lainnya | H28: Objek Rupabumi buatan dan alami | I28: Nama Rupabumi Baku | J28: Terbuka | K28: Tidak terdapat | L28: Harian | M28: SINAR | N28: Pusat | O28: Pusat | P28: Website dan Mobile | Q28: Sinar.big.go.id | R28: Secara Online | S28: Informasi | T28: 2021 | U28: Aktif | V28: Tidak | W28: Tidak Terintegrasi | X28: Tidak Terintegrasi | Y28: Tidak Terintegrasi | Z28: Tim Pembakuan Nama Rupabumi Kab. Bandung (Sekretariat: Bagian Tata Pemerintahan) | AA28: Setda | AB28: Gugum Gumilar, S.STP., M.Si | AC28: 0819-1001-1980 | AD28: admkewilayah@gmail.com
A29: 27 | B29: Layanan Laporan Penyelenggaraan Pemerintahan Daerah | C29: Sebagai sistem aplikasi terpusat yang mempermudah Pemerintah Daerah (Provinsi, Kabupaten, Kota) untuk menyampaikan Laporan Penyelenggaraan Pemerintahan Daerah (LPPD) dan melakukan evaluasi secara online dan real-time, sehingga menghasilkan satu data yang akurat, mengurangi redundansi data, dan mempercepat penyebaran informasi pelaporan | D29: Peraturan Menteri Dalam Negeri Nomor 19 Tahun 2024 tentang Peraturan Pelaksana Peraturan Pemerintah Nomor 13 Tahun 2019 tentang Laporan dan Evaluasi Penyelenggaraan Pemerintahan Daerah; | F29: OTONOMI DAERAH | G29: Instansi Pemerintah Lainnya | I29: Laporan Penyelenggaraan Pemerintahan Daerah (LPPD) | J29: Terbuka | K29: Tidak terdapat | L29: Tahunan | M29: SILPPD | N29: Pusat | O29: Pusat | P29: Website dan Mobile | Q29: https://elppd.kemendagri.go.id/ | R29: Secara Online | S29: Informasi | T29: 2021 | U29: Aktif | V29: Tidak | W29: Tidak Terintegrasi | X29: Tidak Terintegrasi | Y29: Tidak Terintegrasi | Z29: Bagian Tata Pemerintahan | AA29: Setda, Disdik, Dinkes, DPUTR, Disperkimtan, Dinsos, Disdamkar, Satpol PP, BPBD, Inspektorat, Disnaker, DP2KBP3A, DLH, Disdukcapil, DPMD, Dishub, Diskominfo, DPMPTSP, Dispora, Disperdagin, Distan, Dispakan, Disbud, DISKOP-UKM, Dispusip, Disparekraf, BKAD, BKPSDM | AB29: Gugum Gumilar, S.STP., M.Si | AC29: 0819-1001-1980 | AD29: admkewilayah@gmail.com
A30: 28 | B30: Layanan Pelaporan Standar Pelayanan Minimal (SPM) Ditjen Bina Pembangunan Daerah Kementerian Dalam Negeri | C30: Sebagai dasar untuk melakukan monitoring dan evaluasi terpadu, mengelola data dan menganalisis capaian penerapan SPM di daerah, serta menjadi alat untuk mengkoordinasikan implementasi SPM antara pemerintah pusat dan daerah agar pelayanan dasar yang diberikan kepada masyarakat sesuai dengan ketentuan yang berlaku | D30: Peraturan Menteri Dalam Negeri Nomor 59 Tahun 2021 Tentang Penerapan Standar Pelayanan Minimal | F30: OTONOMI DAERAH | G30: Instansi Pemerintah Lainnya | I30: Laporan Penerapan Standar Pelayanan Minimal (SPM) | J30: Terbuka | K30: Tidak terdapat | L30: Lainnya | M30: e-SPM | N30: Pusat | O30: Pusat | P30: Website dan Mobile | Q30: https://spm.bangda.kemendagri.go.id/ | R30: Secara Online | S30: Informasi | T30: 2021 | U30: Aktif | V30: Tidak | W30: Tidak Terintegrasi | X30: Tidak Terintegrasi | Y30: Tidak Terintegrasi | Z30: Bagian Tata Pemerintahan | AA30: Setda, Disdik, Dinkes, DPUTR, Disperkimtan, BPBD, Disdamkar, Satpol PP | AB30: Gugum Gumilar, S.STP., M.Si | AC30: 0819-1001-1980 | AD30: admkewilayah@gmail.com
A31: 29 | B31: Layanan informasi publik | C31: Keterbukaan informasi publik merupakan sarana dalam mengoptimalkan pengawasan publik terhadap penyelenggaraan negara dan Badan Publik lainnya dan segala sesuatu yang berakibat pada kepentingan publik sebagaimana yang diamanatkan dalam Undang-Undang Nomor 14 Tahun 2008 | D31: Undang-Undang Nomor 14 Tahun 2008 | F31: PENGELOLAAN INFORMASI PUBLIK | G31: Pelaku Bisnis | H31: Data Informasi Publik | I31: Data Informasi Publik | J31: Terbatas | K31: Tidak terdapat | L31: Lainnya | M31: PPID | N31: Diskominfo | O31: Kab. Bandung | P31: Website dan Mobile | Q31: https://ppid.bandungkab.go.id/ | R31: Secara Online | S31: Informasi | U31: Aktif | V31: Ya | W31: Tidak Terintegrasi | X31: Tidak Terintegrasi | Y31: Tidak Terintegrasi | Z31: Bagian Kesra | AA31: Diskominfo
A32: 30 | B32: Layanan Pengajuan Produk Hukum | C32: Sipphade, yang juga disebut BEDAS Sipphade (akronim dari “Sistem Informasi Penyusunan Produk Hukum Daerah”), adalah sebuah aplikasi digital yang diluncurkan oleh Pemerintah Kabupaten Bandung. Aplikasi ini dirancang untuk:Mempermudah proses pengajuan produk hukum daerah oleh perangkat daerah. | D32: Undang-Undang Nomor 12 Tahun 2011 tentang Pembentukan Peraturan Perundang-Undangan sebagaimana telah diubah dengan Undang-Undang Nomor 13 Tahun 2022 tentang Perubahan Kedua atas Undang-Undang Nomor 12 Tahun 2011 tentang Pembentukan Peraturan Perundang-Undangan | E32: - | F32: PENYELENGGARAAN PERATURAN PERUNDANG-UNDANGAN | G32: Instansi Pemerintah Lainnya | H32: Identitas Perangkat Daerah Pengusul | I32: surat keputusan | J32: Terbatas | K32: Tidak terdapat | L32: Bulanan | M32: SIPPHADE | N32: Diskominfo | O32: Kab. Bandung | P32: Website | Q32: https://sipphade.bandungkab.go.id/ | R32: Secara Online | S32: Informasi | T32: 2024 | U32: Aktif | V32: Ya | W32: TERINTERGRASI DENGAN E OFFICE DAN BSRE | X32: Database to Database | Y32: Realtime | Z32: Bagian Hukum Sekretariat Daerah Kabupaten Bandung | AA32: Setda | AB32: DADAN SUNANDAR, SH | AC32: 85721347799 | AD32: baghukum17@gmail.com
A33: 31 | B33: Layanan Penanganan litigasi Hukum bedas | C33: Sistem Penanganan litigasi Hukum bedas | D33: - | E33: - | F33: ADMINISTRASI HUKUM UMUM | G33: Masyarakat | H33: para pihak yang berperkara | I33: panggilan sidang | J33: Terbuka | K33: Terdapat | L33: Bulanan | M33: SIPATUHBEDAS | N33: Diskominfo | O33: Kab. Bandung | P33: Website | Q33: https://sipatuhbedas.bandungkab.go.id/ | R33: Secara Online | S33: Informasi | T33: 2023 | U33: Aktif | V33: Ya | W33: - | X33: Database to Database | Y33: Bulanan | Z33: bagian Hukum Sekretariat Daerah Kabupaten Bandung | AA33: Setda | AB33: ZAENAL MUTTAQIN,SH | AC33: 8127585399 | AD33: zaenal1972.zm@gmail.com
A34: 32 | B34: Layanan Fasilitasi Kerja Sama Daerah | C34: Mempercepat transformasi digital dalam tata kelola pemerintahan dan penyusunan peraturan perundang-undangan. | D34: PP No 28 Tahun 2018 tentang Kerja Sama Daerah. Permendagri No 22 Tahun 2020 tentang Tata Cara Kerja Sama Daerah dengan Daerah Lain dan Kerja Sama Daerah dengan Pihak Ketiga, Permendagri No 25 Tahun 2020 tentang Tata Cara Kerja Sama Daerah dengan Pemerintah Daerah di Luar Negeri dan Kerja Sama Daerah dengan Lembaga di Luar Negeri | E34: Ada sesuai Keputusan Sekretaris Dearah No.415.4/KEP.25-KSM/2023 tentang Penetapan Standar Operasional Prosedur Kerja Sama Daerah di Lingkungan Pemerintah Kabupaten Bandung | F34: PENINGKATAN KUALITAS PELAYANAN PUBLIK | G34: Pelaku Bisnis, Masyarakat, Pegawai, Instansi Pemerintah Lainnya | H34: Data Pengguna, data persyaratan permohonan kerja sama, laporan dan perencanaan | I34: Data kerja sama, data permohonan, data perencanaan dan data laporan | J34: Terbatas | K34: Terdapat | L34: Lainnya | M34: SiBERKAH | N34: Diskominfo | O34: Kab. Bandung | P34: Website dan Mobile | Q34: kerjasama.bandungkab.go.id | R34: Secara Online | S34: Informasi | T34: 2022 | U34: Aktif | V34: Ya | W34: BDS | X34: Web Service | Y34: Realtime | Z34: Bagian Kerja Sama SETDA | AA34: Setda | AB34: Ir. Elis Kusmawati,MM | AC34: 85322543009 | AD34: kerjasamabandungkab@gmail.com | AF34: harian | AG34: data kerjasama daerah dengan daerah atau daerah dengan pihak ketiga perangkat daerah sudah punya admin sendiri pengguna mitra kerja dan perangkat daerah, kabupaten lain Mitra kerja itu perangkat daerah lain dan oerguruan tinggi
A35: 33 | B35: Layanan informasi data terkait penyerapan KUR untuk UMKM Kabupaten Bandung | C35: Meningkatkan kapasitas SDM (sumber daya manusia) yang merancang produk hukum. | D35: keputusan bupati bandung nomor 500/KEP..671-Perek/2017 tentang pembentukan tim inflasi darah kabupaten bandung | F35: USAHA KECIL DAN MENENGAH | G35: Instansi Pemerintah Lainnya | H35: dataUMKM yang membutuhkan KUR | I35: data UMKM yang telah menerima KUR | J35: Terbuka | K35: Terdapat | L35: Harian | M35: SIKP | N35: Pusat | O35: Pusat | P35: Website | Q35: https://sikp.kemenkeu.go.id/login | R35: Secara Online | S35: Informasi | T35: 2017 | U35: Aktif | V35: Tidak | W35: Tidak Terintegrasi | Y35: Mingguan | Z35: bagian perekonomian | AB35: herrier mustari | AD35: usmankaryana1961@gmail.com
A36: 34 | B36: Layanan informasi dan penginputan realisasi terkait program percepatan keuangan daerah | D36: keputusan bupati bandung nomor 539/Kep.481-Perek/2021 tentang pembentukan tim percepatan akses keuangan daerah kabupaten bandung | F36: PEMBINAAN KEUANGAN DAERAH | G36: Instansi Pemerintah Lainnya | H36: target dan realisasi program percepatan akses keuangan daerah | I36: realisasi program percepatan akses keuangan daerah | J36: Terbuka | K36: Tidak terdapat | L36: Bulanan | M36: SITPAKD | N36: Pusat | O36: Pusat | P36: Website | Q36: https://sitpakd.ojk.go.id/Account/Login | R36: Secara Online | S36: Informasi | T36: 2021 | U36: Aktif | V36: Tidak | W36: Tidak Terintegrasi | Y36: Mingguan | Z36: bagian perekonomian | AA36: Setda | AB36: herrier mustari | AD36: usmankaryana1961@gmail.com
A37: 35 | B37: Layanan penginputan rencana kerja anggaran, laporan hasil kegiatan dan realisasi DBHCHT | C37: 1. Meningkatkan Efektivitas dan Efisiensi kerja Pimpinan. 2. Mempermudah koordinasi eksternal. 3. Transparansi dan akuntabilitas. 4. Dokumentasi dan arsip digital. 5. Mendukung pengambilan keputusan. 6. Memudahkan akses dan mobilitas. | D37: KEPUTUSAN BUPATI BANDUNG NOMOR : 900.1.14.3/KEP.746-PEREK/2024 Penetapan Pagu Alokasi Dana Bagi Hasil Cukai Hasil Tembakau Bagian Pemerintah Daerah Kabupaten Bandung Tahun Anggaran 2025 dan KEPUTUSAN BUPATI BANDUNG NOMOR : 000.8.1.1/KEP.738-PEREK/202 TIM KOORDINASI PENGELOLAAN DANA BAGI HASIL CUKAI HASIL TEMBAKAU DAERAH KABUPATEN BANDUNG TAHUN 2025 | F37: PENINGKATAN KUALITAS REFORMASI BIROKRASI, PENGAWASAN, DAN AKUNTABILITAS KINERJA | G37: Instansi Pemerintah Lainnya | H37: realisasi dan laporan hasil kegiatan DBHCHT | I37: realisasi dan laporan hasil kegiatan DBHCHT | J37: Terbuka | K37: Tidak terdapat | L37: Bulanan | M37: SIKD | N37: Pusat | O37: Pusat | P37: Website | Q37: https://sikd.djpk.kemenkeu.go.id/lapordbh/ | R37: Secara Online | S37: Informasi | U37: Aktif | V37: Tidak | W37: Tidak Terintegrasi | Y37: Realtime | Z37: bagian perekonomian | AA37: Setda | AB37: selly rossela
A38: 36 | B38: Layanan realisasi pengendalian inflasi per triwulan | C38: 1. Meningkatkan Efektivitas dan Efisiensi kerja Pimpinan. 2. Mempermudah koordinasi eksternal. 3. Transparansi dan akuntabilitas. 4. Dokumentasi dan arsip digital. 5. Mendukung pengambilan keputusan. 6. Memudahkan akses dan mobilitas. | D38: keputusan bupati bandung nomor 500/KEP.671-Perek/2017 tentang pembentukan tim inflasi Daerah | F38: PENINGKATAN KUALITAS REFORMASI BIROKRASI, PENGAWASAN, DAN AKUNTABILITAS KINERJA | G38: Instansi Pemerintah Lainnya | H38: laporan pertriwulan pengendalian inflasi daerah | I38: laporan pertriwulan pengendalian inflasi daerah | J38: Terbuka | K38: Tidak terdapat | L38: Bulanan | M38: TPIN | N38: Pusat | O38: Pusat | P38: Website | Q38: https://tpin.id/login | W38: Tidak Terintegrasi | Z38: bagian perekonomian | AA38: Setda | AB38: MUHAMAD IFAN HERMANTO, S.E
A39: 37 | B39: Layanan laporan realisasi proram reformasi birokrasi di tiap bagian | C39: 1. Meningkatkan Efektivitas dan Efisiensi kerja Pimpinan. 2. Mempermudah koordinasi eksternal. 3. Transparansi dan akuntabilitas. 4. Dokumentasi dan arsip digital. 5. Mendukung pengambilan keputusan. 6. Memudahkan akses dan mobilitas. | F39: PENINGKATAN KUALITAS REFORMASI BIROKRASI, PENGAWASAN, DAN AKUNTABILITAS KINERJA | G39: Instansi Pemerintah Lainnya | J39: Terbuka | K39: Tidak terdapat | L39: Lainnya | M39: PORTALRB | N39: Pusat | O39: Pusat | P39: Website | Q39: https://www.portalrb.id/ | R39: Secara Online | S39: Informasi | U39: Aktif | W39: Tidak Terintegrasi | Y39: Realtime | Z39: bagian perekonomian | AA39: Setda | AB39: MUHAMAD IFAN HERMANTO, S.E
A40: 38 | B40: Layanan analisis kebutuhan jabatan dan analisis beban kerja | C40: 1. Meningkatkan Efektivitas dan Efisiensi kerja Pimpinan. 2. Mempermudah koordinasi eksternal. 3. Transparansi dan akuntabilitas. 4. Dokumentasi dan arsip digital. 5. Mendukung pengambilan keputusan. 6. Memudahkan akses dan mobilitas. | D40: keputusan sekretaris daerah nomor 800/Kep.29-Umum/2022 tentang pembentukan tim penyusunan analisis jabatan (ANJAB)analisis beban kerja (ABK) evaluasi jabatan (EVJAB) dan standar kompetensi jabatan ASN pada sekretariat daerah kabupaten bandung | F40: PENINGKATAN KUALITAS REFORMASI BIROKRASI, PENGAWASAN, DAN AKUNTABILITAS KINERJA | G40: Pegawai | H40: hasil analisis jabatan, beban kinerja dan evaluasi jabatan | I40: hasil analisis jabatan, beban kinerja dan evaluasi jabatan | J40: Terbuka | K40: Tidak terdapat | L40: Lainnya | M40: BISAKERJA | N40: OPD | O40: Kab. Bandung | P40: Website | Q40: https://bisakerja.bandungkab.go.id/login | R40: Secara Online | S40: Informasi | U40: Aktif | W40: Tidak Terintegrasi | Y40: Realtime | Z40: bagian perekonomian | AA40: Setda | AB40: LIES BETTY HIDAYANTI, SE
A41: 39 | B41: Layanan Laporan Keuangan BUMD | C41: 1. Meningkatkan Efektivitas dan Efisiensi kerja Pimpinan. 2. Mempermudah koordinasi eksternal. 3. Transparansi dan akuntabilitas. 4. Dokumentasi dan arsip digital. 5. Mendukung pengambilan keputusan. 6. Memudahkan akses dan mobilitas. | D41: Peraturan Pemerintah Nomor 54 Tahun 2017 tentang Badan Usaha Milik Daerah (BUMD) | F41: PENINGKATAN KUALITAS REFORMASI BIROKRASI, PENGAWASAN, DAN AKUNTABILITAS KINERJA | G41: Instansi Pemerintah Lainnya | H41: Laporan Keuangan BUMD | I41: Laporan Keuangan BUMD | J41: Terbatas | K41: Tidak terdapat | L41: Bulanan | M41: e-BUMD | N41: Pusat | O41: Pusat | P41: Website | Q41: http://e-bumd.com//dashboard | R41: Secara Online | S41: Informasi | U41: Aktif | V41: Tidak | W41: Tidak Terintegrasi | Y41: Bulanan | Z41: bagian perekonomian | AA41: Setda | AB41: ROBBY IRAWAN, S.Sos
A42: 40 | B42: Layanan Administrasi Pembangunan | C42: Membantu memfasilitasi perangkat daerah dalam informasi yang berkaitan dengan kegiatan pembangunan fisik/non fisik di lingkup Pemerintah Daerah Kabupaten Bandung yang bertujuan untuk mendorong terciptanya mekanisme informasi pembangunan yang berkualitas dan tertib administrasi | D42: PP No. 26 Tahun 2006 Tentang Tata Cara Pengendalian dan Evaluasi Pelaksanaan Rencana Pembangunan; PP No. 38 Tahun 2019 Tantang Inovasi Daerah; Perpres No. 95 Tahun 2018 Tentang Sistem Pemerintahan Berbasis Elektronik; Peraturan Bupati No 281 Tahun 2023 Tentang Penerapan Inovasi Berupa Pelaksanaan Monitoring Kegiatan Pembangunan Daerah Melalui Sistem Informasi Manajemen Administrasi Pembangunan; Peraturan Bupati No. 281 Tahun 2023 Tentang Penerapan Inovasi Berupa Pelaksanaan Monitoring Kegiatan Pembangunan Daerah Melalui Sistem Informasi Manajemen Administrasi Pembangunan; Keputusan Bupati Bandung No. 500.12/KEP.754-ADBANG/2024 Tentang Penetapan Pengelola Sistem Informasi Manajemen Administrasi Pembangunan Kabupaten Bandung. | E42: SOP Simbangun: https://drive.google.com/drive/folders/1uT9c4NGjI41uZyGgKpyquckLoM2rSaQa?usp=sharing | F42: PENINGKATAN KUALITAS PELAYANAN PUBLIK | G42: Instansi Pemerintah Lainnya | H42: Data Tenaga Ahli, Data Tenaga Terampil, Data Badan Usaha, Data Quarry, Data Lab. Uji Konstruksi, Data Sewa Alat, Data Paket Pekerjaan, Data Progres Paket Pekerjaan, BPJS | I42: Kurva-S, Diagram Rekap Data, Tagging Kordinat Lokasi dan Dokumentasi | J42: Terbatas | K42: Tidak terdapat | L42: Lainnya | M42: SIMBANGUN | N42: Pihak Ke 3 | O42: Kab. Bandung | P42: Website | Q42: https://simbangun.bandungkab.go.id | R42: Secara Online | S42: Informasi | T42: 2022 | U42: Aktif | V42: Tidak | W42: Link ke Amel, sireka | X42: Tidak Terintegrasi | Y42: Realtime | Z42: Bagian Administrasi Pembangunan | AA42: Setda | AB42: Wawan Purwanto, ST. | AC42: 8122233244 | AD42: wawan.purwanto3@gmail.com | AE42: - | AF42: Harian | AG42: OPD, Kecamatan
A43: 41 | B43: Layanan Evaluasi Pelaporan Program Pembangunan | C43: Untuk mengevaluasi pencapaian hasil dari program pembangunan yang telah dilaksanakan. Ini melibatkan analisis terhadap kinerja program, dampak terhadap masyarakat, efisiensi penggunaan sumber daya, dan ketaatan terhadap peraturan. | D43: Peraturan Pemerintah Nomor 13 Tahun 2019 dan Peraturan Menteri Dalam Negeri No. 18 Tahun 2020 | F43: PENINGKATAN KUALITAS PELAYANAN PUBLIK | G43: Instansi Pemerintah Lainnya | H43: Data Evaluasi Program Pembangunan | I43: LKPJ, Tugas Perbantuan, DAK | J43: Terbatas | K43: Tidak terdapat | L43: Tahunan | M43: e-LKPJ | N43: Pihak Ke 3 | O43: Pihak Ke 3 (Lisensi) | P43: Website | Q43: https://e-lkpj.id/login | R43: Secara Online | S43: Informasi | T43: 2020 | U43: Aktif | V43: Tidak | W43: Tidak Terintegrasi | X43: Tidak Terintegrasi | Y43: Tidak Terintegrasi | Z43: Bagian Administrasi Pembangunan | AA43: Setda | AB43: Wawan Purwanto, ST. | AC43: 8122233244 | AD43: wawan.purwanto3@gmail.com | AE43: - | AF43: Tahunan | AG43: OPD
A44: 42 | B44: Layanan Pengadaaan Barang dan Jasa | C44: meningkatkan kualitas layanan, kapasitas dan keamanan informasi dalam penyelenggaraan layanan pengadaan Barang/Jasa secara elektronik dan memfasilitasi pelaksanaan Pengadaan Barang/Jasa secara elektronik | D44: Perpres Nomor 46 Tahun 2025 tentang Perubahan Kedua atas Peraturan Presiden Nomor 16 Tahun 2018 tentang Pengadaan Barang/Jasa Pemerintah | E44: https://drive.google.com/file/d/1bfEasna0yACDkjKfdw6Q1Zy2Ku88gtKx/view?usp=sharing | F44: PENINGKATAN KUALITAS PELAYANAN PUBLIK | G44: Pelaku Bisnis | H44: Proses Pengadaan Barang/Jasa Tender dan Non Tender, Akun PA/KPA, PPK dan Penyedia | I44: Data Pengadaan Barang/Jasa yang dilaksakan secara Tender dan Non Tender | J44: Terbuka | K44: Tidak terdapat | L44: Lainnya | M44: SPSE | N44: Pusat | O44: Pusat | P44: Website | Q44: https://spse.inaproc.id/bandungkab | R44: Secara Online | S44: Informasi | T44: 2013 | U44: Aktif | V44: Tidak | W44: Tidak Terintegrasi | X44: Tidak Terintegrasi | Y44: Tidak Terintegrasi | Z44: Bagian Pengadaan Barang/Jasa | AA44: Setda | AB44: Ana Suryana, ST., MM. | AC44: 85220648981 | AD44: helpdesk.bandung.kab@gmail.com | AF44: Tahunan
A45: 43 | B45: Layanan Satgas Percepatan Penyelenggaraan MBG Kabupaten Bandung | C45: 1. Mengatur, mendokumentasikan, dan menyimpan seluruh dokumen administrasi yang berkaitan dengan pelaksanaan program, seperti notulen rapat, surat-menyurat, laporan, dan arsip lainnya; 2. Memfasilitasi komunikasi dan koordinasi antar anggota Satuan Tugas serta dengan pihak-pihak terkait lainnya agar informasi tersampaikan dengan baik dan tepat waktu; 3. Menyusun dan mengatur jadwal rapat, kunjungan lapangan, dan kegiatan Satuan Tugas lainnya, serta memastikan pelaksanaan kegiatan sesuai dengan jadwal yang ditetapkan; 4. Membantu dalam penyusunan laporan pelaksanaan program, yang akan disampaikan kepada pembina atau pengarah; 5. Menyiapkan agenda rapat, mengundang peserta rapat, menyiapkan bahan rapat, dan mencatat hasil rapat sebagai bahan tindak lanjut; 6. Menjaga dan mengelola arsip data program makan siang bergizi gratis untuk memudahkan akses informasi dan dokumentasi yang dibutuhkan Satuan Tugas; dan 7. Membantu dalam pengumpulan dan pendataan kebutuhan, capaian, dan kendala pelaksanaan program makan siang bergizi gratis. | D45: KEPUTUSAN BUPATI BANDUNG NOMOR : 000.8.1.1/KEP.465-HUK/2025 PEMBENTUKAN SATUAN TUGAS PERCEPATAN PENYELENGGARAAN PROGRAM MAKAN SIANG BERGIZI GRATIS KABUPATEN BANDUNG | F45: PENGENDALIAN PROGRAM PRIORITAS NASIONAL | G45: Instansi Pemerintah Lainnya | H45: Data Koordinasi dan Fasilitasi Pelaksanaan Program Pemerintah Daerah | I45: SK Pembentukan Satgas MBG Kabupaten BandungDokumen rencana kerja / rencana aksi percepatan penyelenggaraan MBG, Notulen atau berita acara rapat koordinasi Satgas MBG, Laporan pelaksanaan kegiatan Satgas, Laporan monitoring dan evaluasi pelaksanaan MBG, Rekomendasi kebijakan atau tindak lanjut percepatan MBG dan Data progres pelaksanaan program MBG di Kabupaten Bandung | J45: Terbuka | K45: Tidak terdapat | L45: Mingguan | M45: Dashboard Satgas MBG | N45: Diskominfo | O45: Kab. Bandung | P45: Website dan Mobile | Q45: https://aplikasi.bandungkab.go.id/publik/dashboard-pendataan-profil-sppg-aktif-untuk-satgas-mbg | R45: Secara Online | S45: Informasi | T45: 2025 | U45: Aktif | V45: Tidak | W45: Terintegrasi (Dashboard Pimpinan) | X45: Database to Database | Y45: Realtime | Z45: bagian SDA | AA45: Setda, Inspektorat, Disdik, Dinkes, DPUTR | AB45: RUSLI BAIJURI,AP.M.KP | AD45: bagsdasetdakabbandung@gmail.com | AE45: Prioritas Nasional | AF45: Harian | AG45: Desa, Kecamatan & Kabupaten
A46: 44 | B46: Layanan penginputan rencana kerja anggaran, laporan hasil kegiatan dan realisasi DBHCHT | C46: Meningkatkan kualitas produk hukum agar sesuai tujuan seperti kepastian hukum, manfaat, dan keadilan bagi pemangku kepentingan | D46: KEPUTUSAN BUPATI BANDUNG NOMOR : 900.1.14.3/KEP.657-PEREK/2025 PENETAPAN PAGU ALOKASI DANA BAGI HASIL CUKAI HASIL TEMBAKAU BAGIAN PEMERINTAH KABUPATEN BANDUNG TAHUN ANGGARAN 2026 | F46: PENINGKATAN KUALITAS REFORMASI BIROKRASI, PENGAWASAN, DAN AKUNTABILITAS KINERJA | G46: Instansi Pemerintah Lainnya | H46: realisasi dan laporan hasil kegiatan DBHCHT | I46: realisasi dan laporan hasil kegiatan DBHCHT | J46: Terbuka | K46: Tidak terdapat | L46: Bulanan | M46: e-DBHCHT | N46: Provinsi | O46: Provinsi | P46: Website | Q46: https://www.appsheet.com/Account/Login?appName=DBHCHT%20App&FullScope=False&provider=google&returnUrl=https%3A%2F%2Fwww.appsheet.com%2Fstart%2F93891b63-df85-4aa1-a7bf-d007dfa96cf8%3Fplatform%3Ddesktop#appName=DBHCHTApp-787771102-23-06-21&vss=H4sIAAAAAAAAA6WPwU4CMRCG32XOhTRlIaFX9WAMHIR4kHqodNY07Lab7aCSTd-dqUI03NDj_DPfNzMDvHv8WJHd7kBvhp_qAQ-gYTCwPnRoQBu4iYH62BgQBpa2_Q5XSOTDWzKQIb-IM0-YQA_X4fp_2wV4h4F87bEvrkKy48Rxu1AcnBnIAto92dcGvw4uzGn4clLAY4zESR37lqtbS5aZtuNISVWN5GykqrVUulJ6KsdzOZ3MZ5PnclO6D3fO0yI6Vta2SZgzb67jdp_QPfHDf3i0SD87G9xv7RGGjFddywEAAA==&view=Settings | R46: Secara Online | S46: Informasi | T46: - | U46: Aktif | V46: Tidak | W46: Tidak Terintegrasi | X46: Manual | Y46: Realtime | Z46: bagian SDA | AA46: Setda, Dinkes, Disnaker, Dinsos, Disperdagin, Distan, Satpol PP | AB46: RUSLI BAIJURI,AP.M.KP | AD46: bagsdasetdakabbandung@gmail.com
A47: 45 | B47: Layanan Penyerapan Asiparasi Masyarakat Kepada DPRD | C47: Layanan Penyerapan Aspirasi Masyarakat kepada DPRD memungkinkan warga Kabupaten Bandung untuk mengungkapkan aspirasi, usulan, dan kekhawatiran mereka kepada DPRD. Warga Kabupaten Bandung dapat dengan mudah menulis pesan atau mengirimkan keluhan terkait isu-isu seperti infrastruktur, pendidikan,kesehatan, lingkungan, dan lainnya. | D47: Peraturan Bupati Bandung Nomor 245 Tahun 2023 Tentang Layanan Aspirasi Masyarakat Secara Elektronik Melalui DPRD Bedas Mendengar Rakyat Bandung (D'Benderang) | E47: https://drive.google.com/file/d/1Xev2F7vScZDTlBaqHqPh8lzFUMNB_y8a/view?usp=sharing | F47: PENINGKATAN KUALITAS PELAYANAN PUBLIK | G47: Masyarakat | H47: Data Pengaduan dan Aspirasi Masyarakat | I47: Data Pengaduan dan Aspirasi Masyarakat | J47: Terbuka | K47: Terdapat | L47: Harian | M47: D'benderang | N47: Diskominfo | O47: Kab. Bandung | P47: Website | R47: Secara Online | S47: Transaksi | T47: 2022 | U47: Maintenance | V47: Tidak | Y47: Lainnya | Z47: Bagian Umum | AA47: Setwan | AB47: Hilmy Farhan | AC47: 816379600 | AF47: Harian
A48: 46 | B48: Layanan Sistem Informasi Hukum DPRD | C48: Layanan Sistem Informasi Hukum DPRD merupakan layanan yang berada di Sekretariat DPRD yang memiliki manfaat agar seluruh masyarakat di kabupaten Bandung maupun Indonesia dapat mengakses seluruh produk hukum Peraturan Daerah (Perda), Peraturan DPRD, Surat Keputusan Pimpinan DPRD dan Surat Keputusan Sekretaris DPRD yang telah ditetapkan. | D48: Peraturan Presiden Nomor 33 Tahun 2012 tentang Jaringan Dokumentasi dan Informasi Hukum Nasional | F48: HUKUM DAN PERJANJIAN INTERNASIONAL | G48: Masyarakat | H48: Data Keputusan dan Peraturan DPRD | I48: Data Keputusan dan Peraturan DPRD | J48: Terbuka | K48: Tidak terdapat | L48: Harian | M48: Bersih DPRD | N48: Diskominfo | O48: Kab. Bandung | P48: Website | Q48: https://jdihdprd.bandungkab.go.id/ | R48: Secara Online | S48: Informasi | T48: 2022 | U48: Aktif | V48: Ya | W48: JDIH | X48: API | Y48: Harian | Z48: Bagian Persidangan dan Perundang-undangan | AA48: Setwan | AB48: HAIFA NUR GHAIDA, S.I.Kom | AC48: 81313077230 | AF48: Harian
A49: 47 | B49: Layanan Penerimaan Tamu DPRD | C49: Layanan Penerimaan Tamu DPRD merupakan Layanan penerimaan kunjungan Tamu baik DPRD maupun Sekretariat DPRD ke Kantor Sekretariat DPRD Kabupaten Bandung dalam rangka kunjungan kerja dan studi komparasi. | D49: Peraturan Bupati Bandung Nomor 49 Tahun 2016 Tentang Pengelolaan Tamu Dinas di Lingkungan Pemerintah Kabupaten Bandung | F49: INFORMASI DAN DIPLOMASI PUBLIK | G49: Instansi Pemerintah Lainnya | H49: Data Kunjungan Tamu DPRD | I49: Data Kunjungan Tamu DPRD | J49: Terbuka | M49: Dashboard kunjungan dprd kab bandung | N49: Diskominfo | O49: Kab. Bandung | P49: Website | Q49: https://aplikasi.bandungkab.go.id/publik/dashboard-kunjungan-dprd-kab-bandung | R49: Secara Online | S49: Transaksi | T49: 2025 | U49: Aktif | V49: Ya | W49: Dashboard Kabupaten Bandung | X49: API | Y49: Harian | Z49: Bagian Umum | AA49: Setwan | AB49: NOOR DINA CAMELIA, S.I.Kom | AC49: 895385108021 | AF49: Harian
A50: 48 | B50: Pengawasan real-time perkembangan proyek pembangunan fisik | C50: Pengawasan real-time perkembangan proyek pembangunan fisik, mulai dari perencanaan hingga serah terima. Aplikasi ini juga mendukung Bupati dalam memantau proyek secara langsung serta berfungsi sebagai alat pelaksanaan probity audit oleh APIP. | D50: Peraturan Pemerintah Nomor 12 Tahun 2017 tentang Pembinaan dan Pengawasan Penyelenggaraan Pemerintahan Daerah | E50: https://drive.google.com/file/d/1YdxVCrqCKB2IhPmEjmI3enR0CnpLLtYZ/view?usp=sharing | F50: PENINGKATAN KUALITAS REFORMASI BIROKRASI, PENGAWASAN, DAN AKUNTABILITAS KINERJA | G50: Instansi Pemerintah Lainnya | H50: Database Objek Pemeriksaan, Data Inputan Laporan Hasil Pemeriksaan | I50: Laporan perkembangan proyek strategis secara real-time dan Dasbor monitoring | J50: Terbatas | K50: Tidak terdapat | L50: Bulanan | M50: SIMPRODAS | N50: Diskominfo | O50: Kab. Bandung | P50: Website dan Mobile | Q50: https://simprodas.bandungkab.go.id/ | R50: Secara Online | S50: Transaksi | T50: 2024 | U50: Aktif | V50: Tidak | W50: tidak terintegrasi | X50: Tidak Terintegrasi | Y50: Tidak Terintegrasi | Z50: Inspektur Pembantu IV | AA50: Inspektorat | AB50: Naufal Rifki Pratama | AC50: 81776601960 | AD50: - | AE50: 37 | AF50: Bulanan
A51: 49 | B51: Pelayanan konsultasi pada APIP | C51: Untuk membuat dan mengatur janji temu (sebagai layanan konsultasi) | E51: https://drive.google.com/file/d/1hfZl5u33jLRHizH-t5QZsOhlwNoiUSfh/view?usp=sharing | F51: PENINGKATAN KUALITAS PELAYANAN PUBLIK | G51: Instansi Pemerintah Lainnya | H51: Data Konsultasi Permasalahan | I51: Data Solusi Permasalahan | J51: Tertutup | K51: Tidak terdapat | L51: Mingguan | M51: SANTAI | N51: OPD | O51: Pihak Ke 3 (Lisensi) | P51: Website | Q51: https://calendly.com/inspekkabbdg/santai-saranatanyaapipinteraktif | R51: Secara Online | S51: Transaksi | T51: 2025 | U51: Aktif | V51: Tidak | W51: tidak terintegrasi | X51: Tidak Terintegrasi | Y51: Tidak Terintegrasi | Z51: Sekertariat Inspektorat Daerah | AA51: Inspektorat | AB51: Yuda Maulid | AC51: 82117986701 | AD51: - | AE51: mungkin berkaitan dengan 27 | AF51: Harian
A52: 50 | B52: ZI | C52: Meningkatkan kualitas substansi dan pemahaman SDM TPI (Tim Penilai Internal) dalam pembangunan Zona Integritas (ZI) agar hasil evaluasi internal lebih baik dan sesuai kriteria WBK/WBBM. Melaksanakan monitoring, evaluasi, serta penyusunan dokumen | D52: PermenPANRB 90/2021 tentang Pembangunan dan Evaluasi ZI Menuju WBK/WBBM. | F52: PENINGKATAN KUALITAS REFORMASI BIROKRASI, PENGAWASAN, DAN AKUNTABILITAS KINERJA | G52: Instansi Pemerintah Lainnya | H52: LHE (Laporan Hasil Evaluasi) | I52: Nilai Zona Integritas 2025 | J52: Tertutup | K52: Terdapat | L52: Lainnya | M52: BERSIH | N52: Pihak Ke 3 | O52: Kab. Bandung | P52: Website | Q52: Belum Launching | R52: Secara Online | S52: Transaksi | T52: Belum Launching | U52: Non Aktif | V52: Tidak | W52: tidak terintegrasi | X52: Tidak Terintegrasi | Y52: Tidak Terintegrasi | Z52: Inspektur Pembantu III | AA52: Inspektorat | AB52: Wiwin | AC52: 82130540674 | AD52: - | AE52: - | AF52: Tahunan
A53: 51 | B53: Standar Pelayanan Penerbitan Suket Pengganti Ijazah/STTB | C53: Layanan masyarakat untuk mendapatkan surat keterangan pengganti ijazah/STTB apabila dokumen tersebut hilang, terdapat kesalahan penulisan, atau rusak. | D53: Undang-Undang Nomor 25 Tahun 2009 tentang Pelayanan Publik | E53: LAMPIRAN KEPUTUSAN KEPALA DINAS PENDIDIKAN : 9. Standar Pelayanan Penerbitan Suket Pengganti Ijazah/STTB | F53: PENINGKATAN KUALITAS PELAYANAN PUBLIK | G53: Masyarakat | H53: Dokumen yang diperlukan | I53: Surat Keterangan Pengganti | J53: Tertutup | K53: Terdapat | L53: Lainnya | M53: Sukizah | N53: Diskominfo | O53: Kab. Bandung | P53: Website dan Mobile | Q53: simpeldisdik.bandungkab.go.id/Sukizah | R53: Secara Online | S53: Transaksi | T53: 2024 | U53: Aktif | V53: Ya | W53: Simpel BKPSDM | X53: Database to Database | Y53: Lainnya | Z53: Sekretariat | AA53: Disdik | AB53: Faturochman Nuroni | AC53: 85117111582 | AD53: - | AF53: Insidentil
A54: 52 | B54: Standar Pelayanan Fasilitasi Data Pokok Pendidikan (Dapodik) | C54: Layanan masyarakat terkait status verifikasi di Dapodik seperti Penugasan Pendidik dan Tenaga Kependidikan, Peserta Didik, Kondisi Bangunan, Mutasi PTK, Manajemen Dapodik Sekolah, Validasi Akun Dapodik Sekolah, Sinkronisasi Data Dapodik, dll. | D54: Undang-Undang Nomor 25 Tahun 2009 tentang Pelayanan Publik | E54: LAMPIRAN KEPUTUSAN KEPALA DINAS PENDIDIKAN : 13. Standar Pelayanan Fasilitasi Data Pokok Pendidikan (Dapodik) | F54: PENINGKATAN KUALITAS PELAYANAN PUBLIK | G54: Masyarakat | H54: Surat pengantar/tugas | I54: Sinkronisasi atau verifikasi data | J54: Tertutup | K54: Tidak terdapat | L54: Bulanan | M54: Dapodik | N54: Pusat | O54: Pusat | P54: Website | Q54: https://dapo.kemendikdasmen.go.id/ | R54: Secara Online | S54: Informasi | T54: [Belum tahu] | U54: Aktif | W54: - | Y54: Bulanan | Z54: SD, SMP | AA54: Disdik | AB54: SD : Erik Sugiarto SMP : Lina Sarlina | AC54: 85117111582 | AD54: - | AF54: Insidentil
A55: 53 | B55: Penyediaan Website Untuk Sekolah-sekolah di kabupaten Bandung | C55: Layanan bagi lembaga/yayasan PAUD, SD, SMP dan PNF yang ingin melakukan pembuatan website sebagai media Informasi dan Branding | D55: Undang-Undang Nomor 25 Tahun 2009 tentang Pelayanan Publik | F55: PENINGKATAN KUALITAS PELAYANAN PUBLIK | G55: Instansi Pemerintah Lainnya | H55: Data Sekolah | I55: Informasi Tampilan Data Sekolah | J55: Tertutup | K55: Tidak terdapat | L55: Lainnya | M55: Multisite Edu | N55: Diskominfo | O55: Kab. Bandung | P55: Desktop | Q55: simpeldisdik.bandungkab.go.id/MultisiteEdu | R55: Secara Online | S55: Informasi | T55: 2024 | U55: Aktif | V55: Tidak | W55: - | X55: Tidak Terintegrasi | Y55: Tidak Terintegrasi | Z55: Sekretariat | AA55: Disdik | AB55: Raza Candra Anwar S.T | AC55: 85768637781 | AD55: razacandraanwar@gmail.com | AF55: Insidentil
A56: 54 | B56: Layanan SPMBE | C56: Sistem Penerimaan Murid Baru. Layanan terhadap masyarakat dalam rangka penerima siswa baru untuk jenjang pendidikan dasar dan menengah. | D56: Peraturan Menteri Pendidikan Dasar dan Menengah Nomor 3 Tahun 2025 tentang Sistem Penerimaan Murid Baru (Permendikdasmen No. 3 Tahun 2025) | F56: PENDIDIKAN FORMAL PADA PENDIDIKAN ANAK USIA DINI, PENDIDIKAN DASAR, DAN PENDIDIKAN MENENGAH | G56: Masyarakat | H56: Data calon siswa | I56: Data Siswa baru | J56: Tertutup | K56: Terdapat | L56: Lainnya | M56: SPMBE | N56: Diskominfo | O56: Kab. Bandung | P56: Website | Q56: https://spmb.bandungkab.go.id/ | R56: Secara Online | S56: Informasi | T56: 2025 | U56: Aktif | V56: Tidak | W56: - | Z56: SD, SMP | AA56: Disdik | AB56: SD : SMP : | AC56: 87869520475 | AD56: - | AF56: Insidentil
A57: 55 | B57: Layanan PSC 119 (Public Safety Center) | C57: Untuk menangani kegawatdaruratan dan rujukan medis | F57: PENGELOLAAN PELAYANAN KESEHATAN | G57: Masyarakat | H57: Rujukan Kasus Gawat Darurat | I57: Data Kasus Gawat Darurat Pra Hospital | J57: Tertutup | K57: Terdapat | L57: Harian | M57: PSC Kemenkes | N57: Pusat | O57: Pusat | P57: Website | Q57: psc.kemkes.go.id | R57: Secara Online | S57: Informasi | T57: 2026 | U57: Aktif | V57: Tidak | X57: Manual | Y57: Harian | Z57: Bidang Pelayanan Kesehatan | AA57: Dinkes | AB57: Ekawati Triyani | AC57: 811976661 | AD57: psc119bandungkab@gmail.com
A58: 56 | B58: Layanan Pendaftaran Pemeriksaan Laboratorium Kesehatan | C58: Untuk mengambil sampel dan pemeriksaan laboratorium klinis | I58: Data Riwayat Pasien | M58: SILABKES | N58: Pihak Ke 3 | P58: Desktop
A59: 57 | B59: Layanan Surveilans Puskesmas dan Dinkes | C59: Untuk mendeteksi secara dini kejadian luar biasa dan wabah di suatu wilayah | F59: PENCEGAHAN DAN PENGENDALIAN PENYAKIT | G59: Masyarakat | I59: Data Peringatan Potensi KLB dan Wabah | J59: Tertutup | K59: Terdapat | L59: Mingguan | M59: APLIKASI Sistem Kewaspadaan Dini dan Respon | N59: Pusat | O59: Pusat | P59: Website | Q59: skdr.kemkes.go.id | R59: Secara Online | S59: Informasi | T59: 2015 | U59: Aktif | V59: Ya | X59: API | Y59: Realtime | Z59: Bidang Pengendalian dan Pencegahan Penyakit | AA59: Dinkes | AB59: Stella Wirasto Dwiputra | AC59: 87822419136 | AD59: survimkabbandung@gmail.com
A60: 58 | B60: Layanan Pelaporan Skrining Faktor Resiko Penyakit Tidak Menular | C60: Untuk melaporkan kegiatan skrining faktor resiko | I60: Data Pelaporan Kegiatan PTM | M60: SIPTM | N60: Pusat | O60: Pusat | P60: Website | Q60: https://surveilans-pptm.kemkes.go.id/ | U60: Non Aktif
A61: 59 | B61: Layanan Program Imunisasi | C61: Untuk memberikan pelayanan imunisasi pada bayi, balita dan wanita usia subur | D61: Surat Edaran Kementerian Kesehatan nomor : HK.02.02/C/5961/2022 tentang Penggunaan Aplikasi Sehat Indonesiaku (ASIK) untuk Imunisasi rutin | F61: PENCEGAHAN DAN PENGENDALIAN PENYAKIT | G61: Masyarakat | I61: Data Imunisasi | J61: Tertutup | K61: Terdapat | L61: Harian | M61: SEHAT INDONESIAKU | N61: Pusat | O61: Pusat | P61: Website | Q61: https://sehatindonesiaku.kemkes.go.id | R61: Secara Online | S61: Informasi | T61: 2023 | U61: Aktif | V61: Ya | X61: API | Y61: Harian | Z61: Bidang Pengendalian dan Pencegahan Penyakit | AA61: Dinkes | AB61: Endang Sunandar | AC61: 81313125931 | AD61: survimkabbandung@gmail.com
A62: 60 | B62: Layanan Pelaporan Penggunaan Sediaan Narkotika dan Psikotropika | C62: Untuk melaporkan penggunaan sediaan narkotika dan psikotropika dari seluruh unit pelayanan (apotek, klinik dan rumah sakit) instalasi farmasi kabupatek/kota, dinas kesehatan kabupaten/ kota dan dinas kesehatan provinsi seluruh indonesia | I62: Data Laporan Penggunaan Sediaan NAPSA Nasional | M62: SIPNAP | N62: Pusat | O62: Pusat | P62: Website | Q62: sipnap.kemkes.go.id | R62: Secara Online | U62: Aktif | AA62: Dinkes
A63: 61 | B63: Layanan Perekaman Data RM Pasien Elektronik | C63: Untuk mencatat data rekam medis pasien yang berkunjung ke puskesmas | I63: Data Rekam Medis | M63: SIMPUS
A64: 62 | B64: Layanan Pendataan Tuberkulosis | C64: Untuk memantau keadaan pasien TBC | F64: PENCEGAHAN DAN PENGENDALIAN PENYAKIT | G64: Masyarakat | I64: Data Pasien TBC | J64: Terbatas | K64: Terdapat | L64: Harian | M64: Sistem Informasi Tuberkulosis (SITB) | N64: Pusat | O64: Pusat | P64: Website | Q64: https://sitb.kemkes.go.id/ | R64: Secara Online | S64: Informasi | U64: Aktif | V64: Ya | X64: Manual | Y64: Realtime | Z64: Bidang Pengendalian dan Pencegahan Penyakit | AA64: Dinkes | AB64: dr.Lucy | AC64: 81322836363 | AD64: seksipmptmkabupatenbandung@gmail.com
A65: 63 | B65: Layanan Penanggulangan Penderita Malaria | C65: Untuk melaporkan penderita malaria | F65: PENCEGAHAN DAN PENGENDALIAN PENYAKIT | G65: Masyarakat | I65: Data Pasien Penderita Malaria | J65: Terbatas | K65: Terdapat | L65: Harian | M65: ESISMAL | N65: Pusat | O65: Pusat | P65: Website | Q65: sismal.kemkes.go.id | R65: Secara Online | S65: Informasi | U65: Aktif | V65: Ya | X65: Manual | Y65: Realtime | Z65: Bidang Pengendalian dan Pencegahan Penyakit | AA65: Dinkes | AB65: Ratna Wulan Sari | AC65: 81223266494 | AD65: seksipmptmkabupatenbandung@gmail.com
A66: 64 | B66: Layanan Penyakit Tular Vektor, Zoonotik dan DBD | C66: Untuk mempersiapkan kewaspadaan dini terhadap penyakit tulat vektor dan zoonotik | F66: PENCEGAHAN DAN PENGENDALIAN PENYAKIT | G66: Masyarakat | I66: Data Penyakit Tular Vektor dan Zoonotik | J66: Terbatas | K66: Terdapat | L66: Harian | M66: SILANTOR | N66: Pusat | O66: Pusat | P66: Website | Q66: silantor.kemkes.go.id | R66: Secara Online | S66: Informasi | U66: Aktif | V66: Ya | X66: Manual | Y66: Realtime | Z66: Bidang Pengendalian dan Pencegahan Penyakit | AA66: Dinkes | AB66: Ratna Wulan Sari | AC66: 81223266494 | AD66: seksipmptmkabupatenbandung@gmail.com
A67: 65 | B67: Layanan Perencanaan Kebutuhan Tenaga Fasyankes Kabupaten Bandung | C67: Untuk merencanakan jumlah kebutuhan tenaga kesehatan di fasyankes pemerintah kabupaten bandung | I67: Data Formasi Nakes Fayankes | M67: RENBUT | AB67: Sari
A68: 66 | B68: Layanan Pencegahan dan Pengendalian HIV AIDS | C68: Untuk melaksanakan upaya-upaya pencegahan dan pengendalian penyakit HIV | F68: PENCEGAHAN DAN PENGENDALIAN PENYAKIT | G68: Masyarakat | I68: Data Penderita Penyakit HIV AIDS | J68: Terbatas | K68: Terdapat | L68: Harian | M68: SIHA | N68: Pusat | O68: Pusat | P68: Website | Q68: https://sihapims2.kemkes.go.id | R68: Secara Online | S68: Informasi | U68: Aktif | V68: Ya | X68: Manual | Y68: Realtime | Z68: Bidang Pengendalian dan Pencegahan Penyakit | AA68: Dinkes | AB68: Ratna Wulan Sari | AC68: 81223266494 | AD68: seksipmptmkabupatenbandung@gmail.com
A69: 67 | B69: Layanan Komdat dan Microsite | C69: Untuk mengetahui data kegiatan Germas dan posyandu aktif | I69: Data Posyandu Aktif & Kegiatan Germas | M69: KOMDAT & MICROSITE
A70: 68 | B70: Pelaporan data realisasi hasil pemantauan pelaksanaan Renja _K/L | C70: untuk Pelaporan data realisasi hasil pemantauan pelaksanaan Renja _K/L | I70: Data TFU ( Tempat Fasilitas Umum ) | M70: E-MONEV TFU
A71: 69 | B71: Pencatatan dan pelaporan status gizi | C71: untuk memperoleh informasi status gizi individu dan kinerja program gizi secara cepat, akurat, teratur dan berkelanjutan untuk penyusunan perencanaan dan perumusan kebijakan gizi | I71: Data Gizi | M71: Sigizi Terpadu
A72: 70 | B72: Sistem Monitoring Inventaris Logistik Kesehatan Secara Elektronik | C72: membantu dalam mencatat dan memantau pemesanan, distribusi, dan logistik vaksin, obat dan alat kesehatan secara real-time | G72: Instansi Pemerintah Lainnya | L72: Harian | M72: SMILE HEALTH | N72: Pusat | O72: Pusat | P72: Website dan Mobile | Q72: https://smile.kemkes.go.id/ | R72: Secara Online | U72: Aktif | V72: Ya | W72: SITB, SIHA | Y72: Realtime | Z72: Farmasi | AA72: Dinkes
A73: 71 | B73: SIJALAK (Sistem Informasi Jalan dan Jembatan Kabupaten Bandung) | C73: Si Jalak merupakan sebuah platform digital inovatif yang bertujuan untuk mempermudah masyarakat dalam melaporkan kondisi kerusakan infrastruktur publik, seperti jalan raya, jembatan, saluran air, dan tembok penahan. | D73: Peraturan Daerah Nomor 23 Tahun 2016 tentang Penyelenggaraan Jalan | E73: Belum Tersedia | F73: PENGELOLAAN PEMBANGUNAN INFRASTRUKTUR BIDANG PUPR | G73: Masyarakat | H73: Data Pelapor dan Aduan Lokasi Kerusakan Jalan, Jembatan, Saluran Tepi Jalan dan Tembok Penahan Tanah | I73: Data Hasil Pelaporan dan Aduan Masyarakat Terkait Kerusakan Jalan, Jembatan, Saluran Tepi Jalan dan Tembok Penahan Tanah | J73: Terbuka | K73: Terdapat | L73: Harian | M73: SI PUTRA (sijalak) | N73: Pihak Ke 3 | O73: Kab. Bandung | P73: Website dan Mobile | Q73: https://sijalak-kab-bandung.com/ | R73: Secara Online | S73: Transaksi | T73: 2024 | U73: Aktif | V73: Tidak | W73: Tidak Terintegrasi | X73: Tidak Terintegrasi | Y73: Tidak Terintegrasi | Z73: Bidang Jalan | AA73: DPUTR | AB73: Luthfi Jauhari, S.T | AC73: 81290730949 | AE73: 39 | AF73: Harian
A74: 72 | B74: SIBEDAS PBG | C74: SIBEDAS PBG merupakan dashboard untuk memonitoring berkas permohonan Persetujuan Bangunan Gedung (PBG). Pada Dashboard juga terdapat fitur yang digunakan untuk mempermudah melihat pemetaan persebaran karena tersajikan dalam bentuk peta. SIBEDAS PBG bertujuan untuk memonitoring setiap berkas PBG berdasarkan satus permohonan seperti belum diverifikasi, perbaikan ulang, verifikasi ulang dan selesai verifikasi. Selain itu SIBEDAS PBG untuk mempermudah melihat pemetaan persebaran karena tersajikan dalam bentuk peta serta untuk mempermudah merekap data. | D74: Permen PUPR Nomor 22 Tahun 2021 tentang Pedoman Teknis Pendataan Bangunan Gedung | E74: https://drive.google.com/drive/folders/187_7CPT7sxhjamsZJOlN2T4qhrxFpoWq?hl=id | F74: PENATAAN BANGUNAN GEDUNG | G74: Masyarakat | H74: Data Pemohon dan Kelengkapan Berkas PBG | I74: Data Tahapan Progres Permohonan PBG | J74: Terbatas | K74: Terdapat | L74: Harian | M74: SI PUTRA (sibedaspbg) | N74: Pihak Ke 3 | O74: Kab. Bandung | P74: Website dan Mobile | Q74: https://sibedaspbg.bandungkab.go.id/ | R74: Secara Online | S74: Informasi | T74: 2022 | U74: Aktif | V74: Ya | W74: Dashboard Pimpinan | X74: Database to Database | Y74: Harian | Z74: Bidang Bangunan Gedung dan Pengembangan Permukiman | AA74: DPUTR | AB74: Dirgantara Putra Mappaono, ST | AC74: 81318911897 | AD74: dirgantaraaapm@gmail.com | AE74: 34,37, dan 42 | AF74: Harian
A75: 73 | B75: LINKTREE PENGADUAN DPUTR KAB. BANDUNG | C75: LINKTREE menjadi wadah yang dapat memonitoring sekaligus memberikan informasi penyelesaian pengaduan untuk kepentingan dinas. LINKTREE Pengaduan DPUTR bertujuan untuk memonitoring setiap pengaduan secara elektronik sehingga memudahkan masyarakat dan untuk mempermudah setiap bidang dalam proses penyelesaian pengaduan serta untuk mempermudah merekap data. | D75: Undang-Undang Nomor 25 Tahun 2009 tentang Pelayanan Publik | E75: https://drive.google.com/drive/folders/1zpVBSJQx0K3N4_wyw8qZeOJVWGrdlDAe?hl=ID | F75: PENINGKATAN KUALITAS PELAYANAN PUBLIK | G75: Masyarakat | H75: Data Pengguna, Data Aduan | I75: Data Aduan Masyarakat | J75: Terbuka | K75: Terdapat | L75: Harian | M75: SI PUTRA (pengaduan) | N75: Pihak Ke 3 | O75: Kab. Bandung | P75: Website dan Mobile | Q75: linktr.ee/PENGADUAN_DPUTR_KABBDG | R75: Secara Online | S75: Transaksi | T75: 2022 | U75: Aktif | V75: Tidak | W75: Tidak Terintegrasi | X75: Tidak Terintegrasi | Y75: Tidak Terintegrasi | Z75: Bidang dan UPTD | AA75: DPUTR | AB75: Operator Bidang dan UPTD | AF75: Harian
A76: 74 | B76: SIPEDAS (Sistem Informasi Pemetaan Drainase) | C76: SIPEDAS merupakan sistem informasi elektronik untuk menyediakan data pemetaan dan memantau pembangunan saluran drainase, sanitasi dan persampahan. | D76: Permen PUPR Nomor 12 Tahun 2014 tentang Penyelenggaraan Sistem Drainase Perkotaan | E76: Belum Tersedia | F76: PENGELOLAAN PEMBANGUNAN INFRASTRUKTUR BIDANG PUPR | G76: Instansi Pemerintah Lainnya | H76: Data Perencanaan Pembangunan dan Pemeliharaan Saluran Drainase | I76: Capaian dan Kondisi Saluran Drainase | J76: Terbatas | K76: Terdapat | L76: Bulanan | M76: SI PUTRA (sipedas) | N76: Pihak Ke 3 | O76: Kab. Bandung | P76: Website dan Mobile | Q76: https://sites.google.com/view/aplikasi-sipedas-drainase/home | R76: Secara Online | S76: Informasi | T76: 2024 | U76: Aktif | V76: Tidak | W76: Tidak Terintegrasi | X76: Tidak Terintegrasi | Y76: Tidak Terintegrasi | Z76: Bidang Drainase dan Penyedia Infrastruktur Persampahan | AA76: DPUTR | AB76: Roni Romansa | AC76: 85860661778 | AD76: roni.romansa78@gmail.com | AE76: 47 | AF76: Bulanan
A77: 75 | B77: SIJAGA (Sistem Informasi Jaringan Irigasi) | C77: Si Jaga merupakan aplikasi yang menyediakan data pengelolaan jaringan irigasi di Kabupaten Bandung. Aplikasi ini memanfaatkan teknologi GIS (Geographic Information System) untuk memberikan tampilan peta jaringan irigasi dan informasi terkait aset-aset irigasi seperti bendungan, saluran, pintu air, dan sebagainya. | D77: Permen PUPR Nomor 12 Tahun 2015 tentang Eksploitasi dan Pemeliharaan Jaringan Irigasi | E77: https://drive.google.com/drive/folders/1foPXyzm-sQ7KaSp-qTysnVqAWt_Dif53?hl=id | F77: PENGELOLAAN IRIGASI PERTANIAN, KONSERVASI AIR DAN LINGKUNGAN HIDUP | G77: Masyarakat | H77: Data Aduan/ Pelaporan Jaringan Irigasi | I77: Data Hasil Aduan/ Pelaporan Masyarakat | J77: Terbuka | K77: Terdapat | L77: Harian | M77: SI PUTRA (sijaga) | N77: Pihak Ke 3 | O77: Kab. Bandung | P77: Website dan Mobile | Q77: https://sijaga.kabbdg.com/ | R77: Secara Online | S77: Transaksi | T77: 2024 | U77: Maintenance | V77: Tidak | W77: Tidak Terintegrasi | X77: Tidak Terintegrasi | Y77: Tidak Terintegrasi | Z77: Bidang Pengelolaan Sumber Daya Air dan Penyediaan Air Minum | AA77: DPUTR | AB77: Dian Noorcahya Permana, S.T. | AC77: 89681575101 | AD77: dian.noorcahya1221@gmail.com | AE77: 47 | AF77: Harian
A78: 76 | B78: SIBEDAS JAKON | C78: SIBEDAS JAKON merupakan aplikasi yang memberikan informasi mengenai paket pekerjaan, penyedia jasa konstruksi, tenaga terampil bersertifikat, dan lain sebagainya. | D78: Permen PUPR Nomor 22 Tahun 2018 tentang Pembangunan Gedung Negara | E78: https://drive.google.com/drive/folders/1sHKD9PH8GG_yqtIurnieYvG1qyHCbekF?hl=id | F78: PENINGKATAN KUALITAS PELAYANAN PUBLIK | G78: Masyarakat | H78: Data Peserta Bimtek Tenaga Terampil Konstruksi | I78: Data Tenaga Terampil Konstruksi yang Bersertifikat | J78: Terbatas | K78: Terdapat | L78: Bulanan | M78: SI PUTRA (sibedas jakon) | N78: Pihak Ke 3 | O78: Kab. Bandung | P78: Website dan Mobile | Q78: https://sibedasjakon.bandungkab.go.id/ | R78: Secara Online | S78: Informasi | T78: 2022 | U78: Aktif | V78: Tidak | W78: Tidak Terintegrasi | X78: Tidak Terintegrasi | Y78: Tidak Terintegrasi | Z78: Bidang Pengembangan Jasa Konstruksi | AA78: DPUTR | AB78: Fuat Ardi Jaya, S.T. | AC78: 89649072891 | AD78: fuatardi222@gmail.com | AE78: 13 | AF78: Bulanan
A79: 77 | B79: Dashboard Persampahan | C79: Dashboard Persampahan bertujuan untuk menyediakan platform efisien dan terpadu dalam mengumpulkan, merekam, dan memantau data pemilahan, penanganan dan volume sampah sebelum masuk ke Tempat Pembuangan Akhir (TPA) | D79: Peraturan Bupati Bandung Nomor 25 Tahun 2010 tentang Pengelolaan Sampah | E79: Belum Tersedia | F79: PENGELOLAAN SAMPAH | G79: Masyarakat | H79: Data Jenis dan Volume Sampah dari Masyarakat | I79: Data Hasil Pemilahan dan Banyaknya Sampah yang Terkumpul dari Masyarakat | J79: Terbuka | K79: Tidak terdapat | L79: Mingguan | M79: SI PUTRA (sibedasok) | N79: Pihak Ke 3 | O79: Kab. Bandung | P79: Website dan Mobile | Q79: https://linktr.ee/SIBEDASOK | R79: Secara Online | S79: Informasi | T79: 2024 | U79: Aktif | V79: Tidak | W79: Tidak Terintegrasi | X79: Tidak Terintegrasi | Y79: Tidak Terintegrasi | Z79: Bidang Drainase dan Penyedia Infrastruktur Persampahan | AA79: DPUTR | AB79: H. Imam Yudha Pratama, S.T., M.T., M.M. | AC79: 81221971903 | AD79: imamprogdbm@gmail.com | AE79: 41 dan 46 | AF79: Bulanan
A80: 78 | B80: Layanan Informasi Perumahan | C80: memberikan layanan informasi perumahan yang sudah dan akan melaksanakan serah terima PSU perumahan Kabupaten Bandung | D80: 1. Undang - Undang Nomor 1 Tahun 2011 tentang Perumahan dan Kawasan Permukiman 2. Peraturan Pemerintah Nomor 12 Tahun 2021 tentang Perumahan Atas Peraturan Pemerintah Nomor 14 Tahun 2016 tentang Penyelenggaraan Perumahan dan Kawasan Permukiman 3. Peraturan Menteri Dalam Negeri Nomor 9 Tahun 2009 Tentang Pedoman Penyerahan Prasarana, Sarana, dan Utilitas Perumahan dan Permukiman di Daerah 4. Peraturan Daerah Kabupaten Bandung Nomor 5 Tahun 2020 dan Peraturan Bupati Nomor 5 TahunTentang Penyediaan, Penyerahan dan Pengelolaan Prasarana, Sarana dan Utilitas Umum Perumahan dan Permukiman 5. Peraturan Bupati Bandung Nomor 4 Tahun 2021 tentang Peratura Pelaksanaan Peraturan Daerah Nomor 5 Tahun 2020 tentang Penyediaan, Penyerahan, dan Pengelolaan Prasarana, Sarana, dan Utilitas Umum Perumahan dan Permukiman | E80: https://drive.google.com/file/d/1kvVSSjFHbdSKP4vPWzb0wDWs5x8kMCbU/view?usp=sharing | F80: PENYELENGGARAAN PERUMAHAN | G80: Masyarakat | H80: Data Pelapor dan Kejadian | I80: Data Perumahan Data Fasos Fasum | J80: Terbatas | K80: Terdapat | L80: Tahunan | M80: SIPIKAT | N80: Diskominfo | O80: Kab. Bandung | P80: Website | Q80: https://aplikasi.bandungkab.com/publik/landing-page-aplikasi-sipikat | R80: Secara Online | S80: Informasi | T80: 2025 | U80: Aktif | Z80: Bidang PSU | AA80: Disperkimtan
A81: 79 | B81: Surat Keterangan Tidak Mampu (SKTM) Online | C81: Surat Keterangan Tidak Mampu (SKTM) adalah surat resmi yang dikeluarkan oleh pemerintah desa/kelurahan Dinas Sosial yang menerangkan bahwa seseorang atau keluarga berada dalam kondisi ekonomi kurang mampu. SKTM biasanya digunakan sebagai syarat untuk mendapatkan keringanan biaya, bantuan sosial, atau akses layanan tertentu dari pemerintah maupun lembaga lain. | D81: - Peraturan Bupati Bandung Nomor 318 Tahun 2022 tentang Pusat Kesejahteraan Sosial Penanganan Kemiskinan - Peraturan Bupati Bandung No 50 Tahun 2018 Tentang Surat Keterangan Tidak Mampu (SKTM) | E81: https://drive.google.com/file/d/1Ramy4vxff2nlZwmQYryTo4j9HIjXgRt2/view?usp=sharing | F81: PENYELENGGARAAN PERLINDUNGAN SOSIAL | G81: Masyarakat | H81: Berkas persyaratan pengajuan rekomendasi SKTM | I81: Berkas rekomendasi SKTM | J81: Tertutup | K81: Terdapat | L81: Bulanan | M81: DIBEDASKEN | N81: OPD | O81: Kab. Bandung | P81: Website dan Mobile | Q81: https://dibedasken.bandungkab.go.id/ | R81: Secara Online | S81: Transaksi | T81: 2021 | U81: Aktif | V81: Tidak | W81: Tidak Terintegrasi | X81: Tidak Terintegrasi | Y81: Tidak Terintegrasi | Z81: Bidang Perlindungan dan Jaminan Sosial | AA81: Dinsos | AB81: M. Fitrian Ramadan, S.Psi., MM | AC81: 8994413332 | AD81: programdinsoskabbdg@gmail.com | AE81: 10 | AF81: Setiap Saat
A82: 80 | B82: Layanan AK1 | C82: Layanan AK1: Meningkatkan akses dan pelayanan terkait Ketenagakerjaan untuk mendukung keberlanjutan karir pekerja. | D82: Permenaker 18 Tahun 2024 tentang Penempatan Tenaga Kerja Dalam Negeri | E82: https://drive.google.com/drive/folders/1Uinu-ZgkI_8xZeYLw7yaEW1HRhG7prDv?usp=drive_link | F82: PENINGKATAN KUALITAS PELAYANAN PUBLIK | G82: Masyarakat | H82: Data Pencari Kerja | I82: Kartu AK 1 | J82: Terbuka | K82: Terdapat | L82: Harian | M82: SIAP KERJA | N82: Pusat | O82: Pusat | P82: Website dan Mobile | Q82: siapkerja.kemnaker.go.id | R82: Secara Online | S82: Transaksi | T82: 2023 | U82: Aktif | V82: Tidak | W82: https://dashnaker.bandungkab.go.id/login | X82: Database to Database | Y82: Harian | Z82: Bidang Penempatan Tenaga Kerja | AA82: Disnaker | AB82: Panji Subakti | AC82: 85759713013 | AD82: bidangpenempatan04@gmail.com | AE82: 28 | AF82: Harian | AG82: masyarakat
A83: 81 | B83: Layanan Informasi Lowongan Pekerjaan | C83: Layanan Informasi Lowongan Pekerjaan: Memberikan informasi terkini mengenai peluang pekerjaan untuk membantu pengangguran atau pencari kerja. | D83: Undang-Undang Nomor 13 Tahun 2003 tentang Ketenagakerjaan Pasal 31 s.d. 34 Pemerintah bertanggung jawab menyediakan informasi pasar kerja serta bursa kerja untuk masyarakat, Undang-Undang Nomor 25 Tahun 2009 tentang Pelayanan Publik, Mengatur kewajiban instansi pemerintah dalam memberikan pelayanan publik yang cepat, tepat, transparan, dan akuntabel, termasuk layanan informasi lowongan kerja | E83: Belum tersedia | F83: PENINGKATAN KUALITAS PELAYANAN PUBLIK | G83: Pelaku Bisnis, Masyarakat | H83: Data Informasi Lowongan Kerja | I83: Data Lowongan Kerja, Data penempatan | J83: Terbuka | K83: Terdapat | L83: Harian | M83: Dashnaker Plus | N83: Diskominfo | O83: Kab. Bandung | P83: Website | Q83: https://dashnaker.bandungkab.go.id/login | R83: Secara Online | S83: Informasi | T83: 2021 | U83: Aktif | V83: Ya | W83: http://siapkerja.kemnaker.go.id/ | X83: Database to Database | Y83: Harian | Z83: Bidang Perencanaan Tenaga Kerja dan Informasi Pasar Kerja | AA83: Disnaker | AB83: Yogie Noor Hidayat, S.I.Kom | AC83: 81809627007 | AD83: bidjamsosdisnaker@gmail.com | AE83: 28 | AF83: Harian | AG83: masyarakat dan perushaan
A84: 82 | B84: Layanan Pengajuan dan Registrasi Transmigrasi | C84: Layanan Pengajuan dan Registrasi Transmigrasi: Memfasilitasi proses pendaftaran dan registrasi bagi individu yang ingin mengikuti program transmigrasi. | D84: Undang-Undang Nomor 29 Tahun 2009 tentang Perubahan atas UU No. 15 Tahun 1997 tentang Ketransmigrasian. Peraturan Pemerintah Nomor 3 Tahun 2014 tentang Pelaksanaan UU No. 15 Tahun 1997 tentang Ketransmigrasian. Peraturan Menteri Tenaga Kerja dan Transmigrasi Nomor 25 Tahun 2009 tentang Tingkat Perkembangan Permukiman Transmigrasi dan Kesejahteraan Transmigran. Peraturan Menteri Tenaga Kerja dan Transmigrasi Nomor 9 Tahun 2012 tentang Pedoman Pengelolaan Data dan Informasi Ketransmigrasian. | E84: Belum tersedia | F84: PENINGKATAN KUALITAS PELAYANAN PUBLIK | G84: Masyarakat | H84: Data Pemohon | I84: Data Animo | J84: Terbuka | K84: Terdapat | L84: Harian | M84: SIBARDUKTRANS | N84: Pusat | O84: Pusat | P84: Website | Q84: sibarduktrans.transmigrasi.go.id | R84: Secara Online | S84: Informasi | T84: 2024 | U84: Aktif | V84: Tidak | W84: Tidak Terintegrasi | X84: Tidak Terintegrasi | Y84: Tidak Terintegrasi | Z84: Bidang Penempatan Tenagga Kerja | AA84: Disnaker | AB84: Jana Silniodi | AC84: 8122423955 | AD84: bidangpenempatan04@gmail.com | AE84: 28 | AF84: Harian
A85: 83 | B85: Layanan Sistem informasi Pelaporan Tindak Kekerasan Perempuan Dan Anak | C85: Memberikan Layanan Data Korban kekerasan Terhadap Perempuan dan Anak | D85: - Undang-Undang Nomor 23 Tahun 2004 Tentang Penghapusan KDRT - Peraturan Daerah Kabupaten Bandung Nomor 20 Tahun 2016 Tentang Perlindungan Hak Anak Di Daerah Kabupaten Bandung | E85: https://drive.google.com/file/d/13kiJLOSVRFOj2CqIpMMxJSxRVwkT4VuN/view?usp=drive_link | F85: PENINGKATAN KUALITAS PELAYANAN PUBLIK | G85: Masyarakat | H85: Data Korban,Progres Pendampingan | I85: Progres Pendampingan | J85: Rahasia | K85: Terdapat | L85: Harian | M85: SIPETIK | N85: Diskominfo | O85: Kab. Bandung | P85: Website | Q85: https://dp2kbp3a.bandungkab.go.id/ppa/ | R85: Secara Online | S85: Transaksi | T85: 2023 | U85: Aktif | V85: Tidak | W85: Tidak Terintegrasi | X85: Tidak Terintegrasi | Y85: Tidak Terintegrasi | Z85: Bidang pemberdayaan Perempuan | AA85: DP2KBP3A | AB85: Deti Rosdiani | AC85: 85722205379 | AE85: 11 | AF85: Harian
A86: 84 | B86: Penyusunan Penganggaran Perencanaan Responsif Gender BErsinergi Dalam Anggaran PengaruStamaan - Gender | C86: Untuk Mempermudah Instansi Lainya Untuk Mengkases Gender Analysis Pathway dan Gender Budget Statement | D86: Peraturan Bupati Nomor 24 tahun 2016 Tentang Pedoman Umum Pelaksanaan Pengarustamaan Gender dalam Pembangunan Daerah di Kabupaten bandung | E86: https://drive.google.com/file/d/1qhJbKAh0RXizTZVD-lHLPJTl4ZBGbOzZ/view?usp=sharing | F86: KESETARAAN GENDER | G86: Instansi Pemerintah Lainnya | H86: Perencanaan Dan Penganggaran Renfonsif Gender | I86: Data Gender Analisis Patway,Data Gender Budget Statmen | J86: Terbatas | K86: Tidak terdapat | L86: Tahunan | M86: PPRG BEDAS-G | N86: Diskominfo | O86: Kab. Bandung | P86: Website | Q86: https://dp2kbp3a.bandungkab.go.id/pprg/ | R86: Secara Online | S86: Transaksi | T86: 2022 | U86: Aktif | V86: Ya | W86: Terintegrasi dengan aplikasi SIPD | X86: Manual | Y86: Tahunan | Z86: Bidang pemberdayaan Perempuan | AA86: DP2KBP3A | AB86: Raihan Ilhamudin, S. Kep | AC86: 82317985659 | AD86: raihanilham6@gmail.com | AE86: 11 | AF86: Tahunan
A87: 85 | B87: Sistem Informasi Keluarga | C87: mengumpulkan, mengelola, dan menyajikan data serta informasi yang akurat dan terkini mengenai kependudukan dan keluarga berencana untuk mendukung perencanaan dan intervensi program-program BKKBN, seperti Program Bangga Kencana dan penurunan stunting. | D87: Undang-Undang Nomor 52 Tahun 2009 tentang Perkembangan Kependudukan dan Pembangunan Keluarga, Badan Kependudukan dan Keluarga Berencana Nasional memiliki tugas untuk melaksanakan Program Pembangunan Keluarga, Kependudukan dan Keluarga Berencana (Bangga Kencana) | F87: PENDATAAN KELUARGA | G87: Masyarakat | H87: Data Keluarga | I87: ,Data Hasil Pelayanan KB,Data Pendataan Keluarga | J87: Tertutup | K87: Terdapat | L87: Bulanan | M87: SIGA | N87: Pusat | O87: Pusat | P87: Website dan Mobile | Q87: https://siga.bkkbn.go.id/ | R87: Secara Online | S87: Transaksi | T87: 2023 | U87: Aktif | V87: Ya | W87: SIPERINDU | X87: API | Y87: Realtime | Z87: Bidang Pengendalian Penduduk | AA87: DP2KBP3A | AB87: Sangki Sopyan, S. Pd. OR | AC87: 85729245486 | AE87: 9 | AF87: Tahunan
A88: 86 | B88: Satgas Perlindungan Perempuan dan Anak | C88: Menciptakan Lingkungan yang Aman Bagi Perempuan dan Anak di Kecamatan dan Desa/Kelurahan dan Memastikan Mendapatkan Hak-Hak untuk Hidup Tumbuh,Berkembang Dan berpartisipasi secara Optimal sesuai harkat dan Martabat Kemanusiaan serta terlindungi dari kekerasan dan diskriminasi | D88: - Peraturan Daerah Nomor 20 Tahun 2016 Tentang Perlindungan dan Hak Anak - Peraturan Daerah Nomor 21 Tahun 2016 Tenang Perlindungan Perempuan | E88: https://drive.google.com/file/d/16ULKF-_fc7--75zz-4n8WtETaChfDzBD/view?usp=sharing | F88: PENINGKATAN KUALITAS PELAYANAN PUBLIK | G88: Masyarakat | H88: Data Perempuan Kepala Keluarga | I88: Data Perempuan Kepala Keluarga | J88: Tertutup | K88: Terdapat | L88: Bulanan | M88: SAPPANA | N88: Diskominfo | O88: Kab. Bandung | P88: Website | Q88: https://dp2kbp3a.bandungkab.go.id/sappana/ | R88: Secara Online | S88: Transaksi | T88: 2024 | U88: Aktif | V88: Ya | W88: Terintegrasi dengan SIPETIK | X88: Tidak Terintegrasi | Y88: Tahunan | Z88: Bidang pemberdayaan Perempuan | AA88: DP2KBP3A | AB88: Riki Kardina, S. Ag | AC88: 882001405143 | AE88: 11 | AF88: Bulanan
A89: 87 | B89: Sistem Informasi Online Perlindungan Perempuan dan Anak | C89: Pencatatan dan pelaporan kekerasan terhadap perempuan dan anak yang terjadi di wilayah Indonesia, baik untuk warga negara indonesia maupun warga negara asing. SIMFONI PPA bekerja sama dengan instansi pemerintahan di setiap provinsi / kabupaten / kota sehingga aplikasi dapat diakses oleh semua unit layanan penanganan korban kekerasan perempuan dan anak dibawah pada tingkat nasional meliputi provinsi / kabupaten / kota secara up to date. | D89: Undang-Undang Nomor 23 Tahun 2004 Tentang Penghapusan KDRT | E89: https://docs.google.com/spreadsheets/d/1f2FpxtXLWyTMlao3H1cM7ZWvZY62FNOP/edit?usp=drivesdk&ouid=101319060553117315214&rtpof=true&sd=true | F89: PENYEDIA LAYANAN BAGI ANAK YANG MEMERLUKAN PERLINDUNGAN KHUSUS DAN PEREMPUAN KORBAN KEKERASAN YANG MEMERLUKAN KOORDINASI LINTAS PROVINSI, TINGKAT NASIONAL, DAN INTERNASIONAL | G89: Pegawai | H89: Data Korban,Progres Pendampingan | I89: Data Korban Kekerasan Perempuan dan Anak, Progres penanganan Kasus | J89: Rahasia | K89: Terdapat | L89: Lainnya | M89: Simfoni PPA | N89: Pusat | O89: Pusat | P89: Website | Q89: https://simfonippa.kemenpppa.go.id/ | R89: Secara Online | S89: Transaksi | T89: 2019 | U89: Aktif | V89: Tidak | W89: Tidak Terintegrasi | X89: Tidak Terintegrasi | Y89: Tidak Terintegrasi | Z89: Unit Pelaksana Teknis Daerah Perindungan Perempuan dan Anak | AA89: DP2KBP3A | AB89: Dinda Nurul | AC89: 81320344426 | AD89: dindanurul150@gmail.com | AE89: 11 | AF89: Insidentil
A90: 88 | B90: Layanan Bersama Lindungi Anak | C90: pengumpulan data tekait KLA untuk mengumpulkan bukti dukung program pemenuhan hak anak di kabupaten bandung | D90: Permen PPA no 4 Tahun 2024 tentang penyelneggaraaan layanan pemenuhan hak anak | F90: PEMENUHAN HAK ANAK | G90: Masyarakat | H90: eviden pelaksanaan kegiatan | I90: pemenuhan penilaian KLA | J90: Terbatas | K90: Terdapat | L90: Tahunan | M90: aplikasi evaluasi KLA | N90: Diskominfo | O90: Kab. Bandung | P90: Website dan Mobile | Q90: https://dp2kbp3a.bandungkab.go.id/apps/perlindungan-anak/ | R90: Secara Online | S90: Informasi | T90: 2020 | U90: Aktif | V90: Tidak | Z90: Bidang Perlinudngan anak | AA90: DP2KBP3A | AB90: Wina Sri Utami | AC90: 8993829204 | AD90: awinwina4@gmail.com
A91: 89 | B91: Layanan Surat Pengelolaan dan Pamantauan Lingkungan Hidup | C91: Untuk menghasilkan Surat Keterangan SPPL, Berita Acara Konsultasi Rencana Teknis dan Notulensi Rapat | D91: Berdasarkan Peraturan Pemerintah Nomor 22 Tahun 2021 tentang Penyelenggaraan Perlindungan dan Pengelolaan Lingkungan Hidup | E91: STANDAR PELAYANAN PADA DINAS LINGKUNGAN HIDUP.pdf | F91: PENATAAN LINGKUNGAN HIDUP SECARA BERKELANJUTAN | G91: Pelaku Bisnis | H91: Data Pemrakarsa, Dokumen Lingkungan | I91: Data Pengelolaan Dan Pamantauan Lingkungan Hidup | J91: Terbatas | K91: Terdapat | L91: Lainnya | M91: Amdalnet | N91: Pusat | O91: Pusat | P91: Website | Q91: amdalnet.kemenlh.go.id | R91: Secara Online | S91: Transaksi | U91: Aktif | V91: Tidak | W91: tidak terintegrasi | X91: Tidak Terintegrasi | Y91: Tidak Terintegrasi | Z91: Bidang Tata Lingkungan | AA91: DLH | AB91: Iqsan Okiyanto / Andri Taufik | AC91: 085225996451 / 081322181254 | AD91: dlh@bandungkab.go.id
A92: 90 | B92: Layanan Pengangkutan Sampah Wilayah Kabupaten Bandung | C92: Menyediakan layanan pengangkutan sampah secara teratur dan efisien di wilayah Kabupaten Bandung guna menjaga kebersihan lingkungan, mencegah pencemaran, dan memastikan pengelolaan sampah yang ramah lingkungan serta sesuai dengan peraturan yang berlaku. | D92: Berdasarkan Peraturan Daerah Kabupaten Bandung Nomor 1 Tahun 2022 Tentang Pengelolaan Sampah | E92: STANDAR PELAYANAN PADA DINAS LINGKUNGAN HIDUP.pdf | F92: PENGELOLAAN SAMPAH | G92: Masyarakat | H92: Data Sampah yang diangkut | I92: Data Pelayanan Pengangkutan Sampah Wilayah Rancaekek Data Pelayanan Pengangkutan Sampah Wilayah Soreang Data Pelayanan Pengangkutan Sampah Wilayah Ciparay Data Pelayanan Pengangkutan Sampah Wilayah Baleendah | J92: Terbuka | K92: Tidak terdapat | L92: Harian | M92: Sampahkita | N92: Provinsi | O92: Provinsi | P92: Website | Q92: https://sampahkita.jabarprov.go.id/ | R92: Secara Online | S92: Informasi | U92: Aktif | V92: Tidak | W92: tidak terintegrasi | X92: Tidak Terintegrasi | Y92: Tidak Terintegrasi | Z92: Bidang Pengelolaan Sampah | AA92: DLH | AB92: Iqsan Okiyanto / Andri Taufik | AC92: 085225996451 / 081322181254 | AD92: dlh@bandungkab.go.id | AE92: 46 | AF92: Harian
A93: 91 | B93: Layanan Pengelolaan dan Pemanfaatan Sampah | C93: Untuk menghasilkan materi penyuluhan atau pelatihan, sarana dan prasarana pelatihan, bibit BSF, pembinaan secara berkala dan surat registrasi pengelola sampah/bank sampah tematik/TPS3R | D93: Berdasarkan Peraturan Daerah Kabupaten Bandung Nomor 1 Tahun 2022 Tentang Pengelolaan Sampah | E93: STANDAR PELAYANAN PADA DINAS LINGKUNGAN HIDUP.pdf | F93: PENGELOLAAN SAMPAH | G93: Masyarakat | H93: Data sampah yang dilakukan pengelolaan | I93: Data Pelayanan Pengelolaan Dan Pemanfaatan Sampah | J93: Terbuka | K93: Tidak terdapat | L93: Tahunan | M93: SIPSN | N93: Pusat | O93: Pusat | P93: Website | Q93: https://sipsn.kemenlh.go.id/sipsn/ | R93: Secara Online | S93: Informasi | U93: Aktif | V93: Tidak | W93: tidak terintegrasi | X93: Tidak Terintegrasi | Y93: Tidak Terintegrasi | Z93: Bidang Pengelolaan Sampah | AA93: DLH | AB93: Iqsan Okiyanto / Andri Taufik | AC93: 085225996451 / 081322181254 | AD93: dlh@bandungkab.go.id | AE93: 46 | AF93: Tahunan
A94: 92 | B94: Layanan Gep4k Sayang | C94: Untuk melayani Gerakan Peduli Penanaman dan Pemeliharaan Pohon Kesayangan (Gep4k Sayang) yang dimana mewajibkan setiap warga Kabupaten Bandung menanam, memiliki, dan memelihara minimal 2 pohon kesayangan seumur hidupnya | D94: Peraturan Menteri Lingkungan Hidup Dan Kehutanan Republik Indonesia Nomor 23 Tahun 2021 Tentang Pelaksanaan Rehabilitasi Hutan Dan Lahan | E94: STANDAR PELAYANAN PADA DINAS LINGKUNGAN HIDUP.pdf | F94: PELESTARIAN LINGKUNGAN HIDUP | G94: Masyarakat | H94: Data penanaman pohon | I94: Data Gerakan Penanaman dan Pemeliharaan Pohon Kesayangan | J94: Terbuka | K94: Tidak terdapat | L94: Bulanan | M94: GeP4K Sayang | N94: Diskominfo | O94: Kab. Bandung | P94: Website | Q94: https://gepak.bandungkab.go.id/ | R94: Secara Online | S94: Informasi | T94: 2025 | U94: Aktif | V94: Tidak | W94: tidak terintegrasi | X94: Tidak Terintegrasi | Y94: Tidak Terintegrasi | Z94: Bidang Konservasi dan Pengendalian Kerusakan Lingkungan | AA94: DLH | AB94: Iqsan Okiyanto / Andri Taufik | AC94: 085225996451 / 081322181254 | AD94: dlh@bandungkab.go.id | AE94: 41 | AF94: Bulanan
A95: 93 | B95: Layanan Taman Kehati | C95: Untuk mengelola Taman Keanekaragaman Hayati (Taman Kehati) dan mengelola kawasan pencadangan sumber daya alam hayati lokal di luar kawasan hutan yang mempunyai fungsi konservasi insitu dan/atau exsitu | D95: Peraturan Menteri Lingkungan Hidup Dan Kehutanan Republik Indonesia Nomor 16 Tahun 2024 Tentang Resor Pada Unit Pelaksana Teknis Direktorat Jenderal Konservasi Sumber Daya Alam Dan Ekosistem | E95: STANDAR PELAYANAN PADA DINAS LINGKUNGAN HIDUP.pdf | F95: PELESTARIAN LINGKUNGAN HIDUP | G95: Masyarakat | H95: Data Taman Kehati | I95: Data Taman Kehati | J95: Terbuka | K95: Tidak terdapat | L95: Bulanan | M95: Taman Kehati | N95: Diskominfo | O95: Kab. Bandung | P95: Website | Q95: Kehati.bandungkab.go.id | R95: Secara Online | S95: Informasi | T95: 2021 | U95: Aktif | V95: Tidak | W95: tidak terintegrasi | X95: Tidak Terintegrasi | Y95: Tidak Terintegrasi | Z95: Bidang Konservasi dan Pengendalian Kerusakan Lingkungan | AA95: DLH | AB95: Iqsan Okiyanto / Andri Taufik | AC95: 085225996451 / 081322181254 | AD95: dlh@bandungkab.go.id | AE95: 41 | AF95: Bulanan
A96: 94 | B96: Pencatatan Biodata | C96: Menjamin ketersediaan data pribadi penduduk yang valid dan terintegrasi dalam database kependudukan nasional. | D96: 1. Undang-Undang Nomor 23 Tahun 2006 tentang Administrasi Kependudukan sebagaimana telah diubah dengan Undang-Undang Nomor 24 Tahun 2013 tentang Perubahan atas Undang-Undang Nomor 23 Tahun 2006 tentang Administrasi Kependudukan; 2. Peraturan Pemerintah Nomor 40 Tahun 2019 tentang Pelaksanaan Undang-Undang Nomor 23 Tahun 2006 tentang Administrasi Kependudukan sebagaimana telah diubah dengan Undang-Undang Nomor 24 Tahun 2013 tentang Perubahan atas Undang-Undang Nomor 23 Tahun 2006 tentang Administrasi Kependudukan; 3. Peraturan Presiden Nomor 96 Tahun 2018 Tentang persyaratan dan Tata Cara Pendaftaran Penduduk dan Pencatatan Sipil; 4. Permendagri Nomor 119 Tahun 2017 Tentang pengangkatan dan pemberhentian serta tugas pokok pejabat pencatatan sipil dan petugas registrasi; 5. Permendagri Nomor 7 Tahun 2019 Tentang Pelayanan Administras! Kependudukan Secara Daring Juncto Permendagri Nomor 2 Tahun 2023 Tentang Perubahan Atas Permendagri Nomor 7 Tahun 2019 Tentang Pelayanan Administrasi Kependudukan secara daring; 6. Permendagri Nomor 108 Tahun 2019 tentang Peraturan Pelaksanaan Peraturan Presiden Nomor 96 Tahun 2018 tentang Persyaratan dan tatacara Pendaftaran Pcnduduk dan Pencatatan Sipil; 7. Permendagri Nomor 109 Tahun 2019 tentang Formulir dan buku yang digunakan dalam Administrasi Kependudukan; 8. Peraturan Daerah Kabu paten Bandung Nomor 1 Tahun 2010 Tentang Penyelenggaraan Administrasi Kependudukan di Kabupaten Bandung sebagaimana telah diubah dengan Peraturan Daerah Kabupaten Bandung Nomor 12 Tahun 2014 tentang perubahan atas Peraturan Daerah Kabupaten Bandung Nomor 1 Tahun 2010 tentang Penyelenggaraan Administrasi Kependudukan di Kabupaten Bandung; 9. Peraturan Bupati Bandung Nomor 75 Tahun 2017 Tentang Pedoman Pengangkatan Dan Pemberhentian Petugas Registrasi Pelayanan Administrasi Kependudukan Desa/Kelurahan di Kabupaten Bandung; 10. Peraturan Bupati Bandung Nomor 2 Tahun 2019 tentang Persyaratan dan Tatacara Pendaftaran Penduduk dan Pencatatan Sipil di Kabupaten Bandung; 11. Peraturan Bupati Bandung Nomor 342 Tahun 2022 Tentang Pedoman Tata Cara Pelayanan Administrasi Kependudukan Secara Daring melalui Anjungan Dukcapil Mandiri (ADM) di Kabupaten Bandung. | E96: SOP Layanan 2025 | F96: PENINGKATAN KUALITAS PELAYANAN PUBLIK | G96: Masyarakat | H96: Data Pelapor | I96: Data Pelapor | J96: Tertutup | K96: Terdapat | L96: Lainnya | M96: BDS | N96: Diskominfo | O96: Kab. Bandung | P96: Website dan Mobile | Q96: https://bds.bandungkab.go.id/ | R96: Secara Online | S96: Transaksi | T96: 2022 | U96: Aktif | V96: Tidak | W96: Tidak Terintegrasi | X96: Tidak Terintegrasi | Y96: Tidak Terintegrasi | Z96: Bidang Pendaftaran Penduduk | AA96: Disdukcapil | AB96: Riana Aji Iskandar S.T., M.Kom. | AC96: 8994450222 | AD96: rianaajiiskandar@gmail.com | AE96: 32. Peningkatan Layanan Kependudukan yang Responsif dan Cepat | AF96: Harian | AG96: 1. SIAK TERPUSAT : Disdukcapil dan 57 OPD yang sudah melakukan Perjanjian Kerjasama Pemanfaatan Data Kependudukan Tahun 2025 dengan 5 Perangkat Daerah baru yaitu Bagian Kesejahteraan Rakyat Sekretariat Daerah, DPMD, Dishub, Baperida dan Kec. Arjasari, disamping Perjanjian Kerjasama yang masih aktif yakni DPMPTSP, Dinsos, Disdik, Diskominfo, Disnaker, Dispora, Dinkes, Distan, Diskop UKM, DP2KBP3A, Dispakan, Disperdagin, Dispusip, Disperkimtan, Disdamkar, Dinas LH, BPBD, BAPENDA, BKPSDM, Kesbangpol, Satpol PP, Sekretariat DPRD, Kec. Baleendah. Kec. Bojongsoang, Kec. Cicalengka, Kec. Dayeuhkolot, Kec. Katapang, Kec. Kutawaringin, Kec. Nagreg, Kec. Cimenyan, Kec. Cimaung, Kec. Rancaekek, Kec. Pasirjambu, Kec. Margaasih, Kec. Ciparay, Kec. Pacet, Kec. Cileunyi, Kec. Pangalengan, Kec. Rancabali, Kec. Cikancung, Kec. Pameungpeuk, Kec. Margahayu, Kec. Majalaya, Kec. Soreang, Kec. Solokan Jeruk, Kec. Ibun, Kec. Cangkuang, Kec. Ciwidey, Kec. Kertasari, Kec. Paseh, Kec. Banjaran, sehingga sampai dengan akhir Tahun 2025 jumlah Perangkat Daerah yang telah melakukan Perjanjian Kerja Sama Pemanfaatan Data Kependudukan sebanyak 57 PD termasuk Disdukcapil sebagai Leading Sector. 2. Aplikasi BDS : Seluruh Masyarakat
A97: 95 | M97: SIAK TERPUSAT | N97: Pusat | O97: Pusat | P97: Website dan Mobile | Q97: Tidak tersedia secara publik. Paket update hanya dapat diunduh via SVN Client internal. | R97: Secara Online | S97: Transaksi | T97: 2022 | U97: Aktif | V97: Tidak | W97: Tidak Terintegrasi | X97: Tidak Terintegrasi | Y97: Tidak Terintegrasi
A98: 96 | B98: LAMPID | C98: Menjamin pencatatan empat peristiwa penting (lahir, mati, pindah, datang) secara cepat dan terintegrasi. | D98: 1. Undang-Undang Nomor 23 Tahun 2006 tentang Administrasi Kependudukan sebagaimana telah diubah dengan Undang-Undang Nomor 24 Tahun 2013 tentang Perubahan atas Undang-Undang Nomor 23 Tahun 2006 tentang Administrasi Kependudukan; 2. Peraturan Pemerintah Nomor 40 Tahun 2019 tentang Pelaksanaan Undang-Undang Nomor 23 Tahun 2006 tentang Administrasi Kependudukan sebagaimana telah diubah dengan Undang-Undang Nomor 24 Tahun 2013 tentang Perubahan atas Undang-Undang Nomor 23 Tahun 2006 tentang Administrasi Kependudukan; 3. Peraturan Presiden Nomor 96 Tahun 2018 Tentang persyaratan dan Tata Cara Pendaftaran Penduduk dan Pencatatan Sipil; 4. Permendagri Nomor 119 Tahun 2017 Tentang pengangkatan dan pemberhentian serta tugas pokok pejabat pencatatan sipil dan petugas registrasi; 5. Permendagri Nomor 7 Tahun 2019 Tentang Pelayanan Administras! Kependudukan Secara Daring Juncto Permendagri Nomor 2 Tahun 2023 Tentang Perubahan Atas Permendagri Nomor 7 Tahun 2019 Tentang Pelayanan Administrasi Kependudukan secara daring; 6. Permendagri Nomor 108 Tahun 2019 tentang Peraturan Pelaksanaan Peraturan Presiden Nomor 96 Tahun 2018 tentang Persyaratan dan tatacara Pendaftaran Pcnduduk dan Pencatatan Sipil; 7. Permendagri Nomor 109 Tahun 2019 tentang Formulir dan buku yang digunakan dalam Administrasi Kependudukan; 8. Peraturan Daerah Kabu paten Bandung Nomor 1 Tahun 2010 Tentang Penyelenggaraan Administrasi Kependudukan di Kabupaten Bandung sebagaimana telah diubah dengan Peraturan Daerah Kabupaten Bandung Nomor 12 Tahun 2014 tentang perubahan atas Peraturan Daerah Kabupaten Bandung Nomor 1 Tahun 2010 tentang Penyelenggaraan Administrasi Kependudukan di Kabupaten Bandung; 9. Peraturan Bupati Bandung Nomor 75 Tahun 2017 Tentang Pedoman Pengangkatan Dan Pemberhentian Petugas Registrasi Pelayanan Administrasi Kependudukan Desa/Kelurahan di Kabupaten Bandung; 10. Peraturan Bupati Bandung Nomor 2 Tahun 2019 tentang Persyaratan dan Tatacara Pendaftaran Penduduk dan Pencatatan Sipil di Kabupaten Bandung; 11. Peraturan Bupati Bandung Nomor 342 Tahun 2022 Tentang Pedoman Tata Cara Pelayanan Administrasi Kependudukan Secara Daring melalui Anjungan Dukcapil Mandiri (ADM) di Kabupaten Bandung. | E98: SOP Layanan 2025 | F98: PENINGKATAN KUALITAS PELAYANAN PUBLIK | G98: Masyarakat | H98: Data Pelapor | I98: Data Pelapor | J98: Tertutup | K98: Terdapat | L98: Lainnya | M98: lampid | N98: OPD | O98: Kab. Bandung | P98: Website | Q98: http://lampid.bandungkab.go.id/ | R98: Secara Online | S98: Transaksi | T98: 2022 | U98: Non Aktif | V98: Tidak | W98: Tidak Terintegrasi | X98: Tidak Terintegrasi | Y98: Tidak Terintegrasi | Z98: Bidang Pencatatan Sipil | AA98: Disdukcapil | AB98: Riana Aji Iskandar S.T., M.Kom. | AC98: 8994450222 | AD98: rianaajiiskandar@gmail.com | AE98: 32. Peningkatan Layanan Kependudukan yang Responsif dan Cepat | AF98: Harian | AG98: Aplikasi LAMPID : Disdukcapil dan Desa/Kecamatan
A99: 97 | B99: Layanan Pengelolaan Keuangan Desa | C99: Meningkatkan transparansi, akuntabilitas, dan efisiensi dalam pengelolaan keuangan di tingkat desa untuk memastikan dana desa digunakan secara efektif dan sesuai peruntukannya. | D99: - Undang-Undang Nomor 6 Tahun 2014 tentang Desa - Permendagri Nomor 20 Tahun 2018 tentang Pengelolaan Keuangan Desa | E99: Tidak ada | F99: PENINGKATAN KUALITAS PELAYANAN PUBLIK | G99: Masyarakat | H99: Data Keuangan Desa | I99: Data Keuangan Desa | J99: Terbatas | K99: Terdapat | L99: Bulanan | M99: SISKEUDES | N99: Pusat | O99: Pusat | P99: Desktop | Q99: http://siskeudes.bandungkab.go.id:8080/guacamole/#/ | R99: Secara Online | S99: Transaksi | T99: 2015 | U99: Aktif | V99: Ya | W99: website konsolidasi Kemendagri | X99: Database to Database | Y99: Lainnya | Z99: Bidang Administrasi Pemerintahan Desa | AA99: DPMD | AB99: Fauzan Pujarahmani | AC99: =+62 852-2443-7788 | AE99: Mewujudkan pembangunan berbasis Desa | AF99: Harian | AG99: Desa
A100: 98 | B100: Layanan Pengelolaan Keuangan Desa | C100: Meningkatkan transparansi, akuntabilitas, dan efisiensi dalam pengelolaan keuangan di tingkat desa untuk memastikan dana desa digunakan secara efektif dan sesuai peruntukannya. | D100: UU Nomor 1 Tahun 2004 tentang Perbendaharaan Negara | E100: Tidak ada | F100: PENINGKATAN KUALITAS PELAYANAN PUBLIK | G100: Masyarakat | H100: Data Keuangan Desa | I100: Data Keuangan Desa | J100: Terbatas | K100: Terdapat | L100: Bulanan | M100: OM-SPAN | N100: Pusat | O100: Pusat | P100: Website | Q100: https://spanint.kemenkeu.go.id/tkd/#/home/login | R100: Secara Online | S100: Transaksi | T100: 2016 | U100: Aktif | V100: Ya | W100: Terintegrasi dengan SISKEUDES | X100: Database to Database | Y100: Lainnya | Z100: Bidang Administrasi Pemerintahan Desa | AA100: DPMD | AB100: Tsalits Nur F | AC100: =+62 877-4168-8587 | AD100: apd.dpmd.bdgkab@gmail.com | AE100: Mewujudkan pembangunan berbasis Desa | AF100: Harian | AG100: Desa
...

Sheet Kertaskerja_Final
A1: No | B1: Nama Layanan | C1: Tujuan dan Fungsi Layanan | D1: Dasar Hukum Layanan | E1: SOP / Proses Bisnis Layanan | F1: Referensi Layanan | G1: Target Layanan | H1: Data yang dimasukan | I1: Data yang dihasilkan | J1: Sifat Data | K1: Data Pribadi | L1: Interval update data yang dihasilkan | M1: Aplikasi Pendukung | N1: Pengembang | O1: Pemilik | P1: Platform | Q1: Alamat Aplikasi | R1: Kategori Akses | S1: Jenis Aplikasi | T1: Tahun Pembuatan | U1: Status Aplikasi | V1: Telah Terintegrasi | W1: Terintegrasi dengan Aplikasi | X1: Mekanisme Integrasi | Y1: Frekuensi Sinkronisasi | Z1: Bidang / Unit Kerja | AA1: OPD | AB1: Nama | AC1: No. HP | AD1: Email | AE1: Keterkaitan 58 Rencana Aksi | AF1: Frekuensi Penggunaan Aplikasi | AG1: TA
A2: 1 | B2: 2 | C2: 3 | D2: 4 | E2: 5 | F2: 6 | G2: 7 | H2: 8 | I2: 9 | J2: 10 | K2: 11 | L2: 12 | M2: 13 | N2: 14 | O2: 15 | P2: 16 | Q2: 17 | R2: 18 | S2: 19 | T2: 20 | U2: 21 | V2: 22 | W2: 23 | X2: 24 | Y2: 25 | Z2: 26 | AA2: 27 | AB2: 28 | AC2: 29 | AD2: 30 | AE2: 31 | AF2: 32 | AG2: 33
A3: 1 | B3: Layanan Radio Kandaga | C3: layanan bagi para pembicara yang telah menyampaiakan informasi melalui Podcast Radio Kandaga | F3: PENYIARAN RADIO PUBLIK | G3: Masyarakat | H3: Data Siaran atau Podcast | I3: Data Siaran atau Podcast | J3: Terbuka | L3: Tahunan | M3: KANDAGA | P3: Mobile | Q3: https://play.google.com/store/apps/details?id=com.diskominfo.radiokandagabedas&pcampaignid=web_share | Z3: Penyelenggaraan Informasi dan Komunikasi Publik | AA3: Diskominfo
A4: 2 | B4: Layanan Pembinaan dan Fasilitasi KIM | C4: Layanan Pembinaan dan Fasilitasi KIM: Mendorong pengembangan kawasan industri melalui pembinaan dan fasilitasi. | F4: PEMBERDAYAAN DAN PERAN MASYARAKAT | G4: Instansi Pemerintah Lainnya | H4: Data Peserta KIM | I4: Data Peserta KIM | J4: Terbatas | L4: Tahunan | M4: KIM | O4: Pusat | P4: Website | Q4: https://kimonline.bandungkab.go.id/ kim/ | AA4: Diskominfo
A5: 3 | B5: Layanan Portal Aplikasi | C5: Layanan Portal Aplikasi: Memberikan akses terpadu ke berbagai aplikasi pemerintah daerah. | F5: PENATAKELOLAAN APLIKASI INFORMATIKA | G5: Instansi Pemerintah Lainnya | H5: Data Portal Layanan | I5: Data Portal Layanan | J5: Terbuka | L5: Tahunan | M5: PORTAL KAB BANDUNG | N5: Diskominfo | O5: Kab. Bandung | P5: Website | Q5: https://bandungkab.go.id/ | AA5: Diskominfo
A6: 4 | B6: Layanan Smart CIty | C6: Layanan Smart City: Mengintegrasikan teknologi untuk meningkatkan efisiensi dan kualitas hidup warga dalam konteks perkotaan. | F6: PENINGKATAN KUALITAS PELAYANAN PUBLIK | G6: Masyarakat | H6: Data Smart City | I6: Data Smart City | J6: Terbuka | L6: Tahunan | M6: SMART CITY | P6: Website | Q6: https://smartcity.bandungkab.go.id/ | AA6: Diskominfo
A7: 5 | B7: Layanan Sistem Informasi Tindak Lanjut Hasil Layanan Terpadu | C7: Layanan Sistem Informasi Tindak Lanjut Hasil Layanan Terpadu mengacu pada sistem informasi berbasis web untuk mengelola dan memantau proses tindak lanjut (TL) hasil rekomendasi pemeriksaan oleh lembaga seperti Badan Pemeriksa Keuangan (BPK), agar prosesnya menjadi lebih efisien, transparan, dan akuntabel melalui digitalisasi data dan komunikasi online secara real-time antara BPK dan entitas yang diperiksa. | D7: Undang-Undang Nomor 25 Tahun 2009 tentang Pelayanan Publik, Peraturan Pemerintah Nomor 96 Tahun 2012 | F7: PENINGKATAN KUALITAS PELAYANAN PUBLIK | G7: Instansi Pemerintah Lainnya | H7: Data Evidence Tindak Lanjut yang Direkomendasikan | I7: Data Hasil Tindak Lanjut | J7: Terbatas | K7: Tidak terdapat | L7: Tahunan | M7: SIMASLAHAT | N7: Pihak Ke 3 | O7: Kab. Bandung | P7: Website | Q7: https://simaslahat.bandungkab.go.id | R7: Secara Online | S7: Transaksi | T7: 2022 | U7: Aktif | V7: Tidak | W7: Tidak Terintegrasi | X7: Tidak Terintegrasi | Y7: Tidak Terintegrasi | Z7: Bagian Perencanaan dan Keuangan | AA7: Setda | AB7: VERRYNOVYANDI SADIKIN, SE., MM | AC7: 895327038135 | AD7: setdakab.bdg@gmail.com | AE7: - | AF7: Tahunan
A8: 6 | B8: Layanan Pengaduan Masyarakat | C8: Layanan Pengaduan Masyarakat (LPM) adalah wadah atau sistem yang disediakan oleh instansi pemerintah (atau lembaga publik lainnya) bagi masyarakat untuk menyampaikan keluhan, saran, masukan, aspirasi, hingga laporan atas dugaan penyimpangan atau maladministrasi dalam penyelenggaraan pemerintahan dan pelayanan publik. | D8: Undang-Undang Nomor 25 Tahun 2009 tentang Pelayanan Publik | F8: PENINGKATAN KUALITAS PELAYANAN PUBLIK | G8: Masyarakat | H8: Data Pengguna, Data Adun | I8: Data Aduan Masyarakat | J8: Terbatas | K8: Terdapat | L8: Harian | M8: SP4N Lapor | N8: Pusat | O8: Pusat | P8: Website | Q8: https://lapor.go.id/ | R8: Secara Online | S8: Informasi | T8: 2018 | U8: Aktif | V8: Tidak | W8: Tidak Terintegrasi | X8: Tidak Terintegrasi | Y8: Tidak Terintegrasi | Z8: Bidang Informasi Komunikasi Publik | AA8: Diskominfo | AB8: ALIPHIO DYAKSHA PUTRA, A.Md.Ak. | AC8: 8988005270 | AD8: setdakab.bdg@gmail.com | AE8: - | AF8: Insidentil
A9: 7 | B9: Layanan Data Sektoral | C9: Layanan data sektoral adalah statistik yang dihasilkan oleh instansi pemerintah pusat atau daerah sesuai dengan tugas dan fungsi masing-masing, yang bertujuan untuk memenuhi kebutuhan internal instansi tersebut dalam penyelenggaraan pemerintahan dan pembangunan. | D9: PERATURAN BADAN PUSAT STATISTIK NOMOR 3 TAHUN 2022 TENTANG EVALUASI PENYELENGGARAAN STATISTIK SEKTORAL | F9: PENGELOLAAN DATA STATISTIK | G9: Instansi Pemerintah Lainnya | H9: Data Sektoral | I9: Data Sektoral | J9: Terbatas | K9: Tidak terdapat | L9: Tahunan | M9: SIMASDA | N9: Diskominfo | O9: Kab. Bandung | P9: Website | Q9: https://simasda.bandungkab.go.id/ | R9: Secara Online | S9: Informasi | T9: 2022 | U9: Aktif | V9: Ya | W9: Terintegrasi dengan Bedas, E-Walidata dan Satu Data Kab Bandung | X9: Database to Database | Y9: Realtime | Z9: Bidang Statistik | AA9: Diskominfo | AB9: DHANTI AURILIA PRATIWI, M.Stat | AC9: 81904085710 | AD9: setdakab.bdg@gmail.com
A10: 8 | B10: Layanan Rekonsiliasi Pajak Pusat | C10: Rekonsiliasi pajak pusat atas belanja daerah adalah proses penyesuaian atau pencocokan antara jumlah pajak yang harus dibayarkan oleh pemerintah daerah kepada pemerintah pusat dengan total belanja yang telah dilakukan oleh pemerintah daerah dalam kerangka Anggaran Pendapatan dan Belanja Daerah (APBD) | D10: PERBUP Nomor 165 Tahun 2021 dan PERBUP Nomor 289 Tahun 2022 | F10: AKUNTANSI DAN PELAPORAN KEUANGAN | G10: Instansi Pemerintah Lainnya | H10: Data Pajak Pusat (ID Billing & NTPN) | I10: Rekap Data Pajak Pusat | J10: Tertutup | K10: Terdapat | L10: Harian | M10: SIREKON | N10: Pihak Ke 3 | O10: Kab. Bandung | P10: Website | Q10: https://sirekonpajak.bandungkab.go.id/ | R10: Secara Online | S10: Informasi | T10: 2020 | U10: Aktif | V10: Tidak | W10: Tidak Terintegrasi | X10: Tidak Terintegrasi | Y10: Tidak Terintegrasi | Z10: Bagian Perencanaan dan Keuangan | AA10: BKAD | AB10: VERRYNOVYANDI SADIKIN, SE., MM | AC10: 895327038135 | AD10: setdakab.bdg@gmail.com | AE10: - | AF10: Bulanan
A11: 9 | B11: Layanan Pajak | C11: Fungsi layanan pajak meliputi pengumpulan pajak daerah, pengelolaan data wajib pajak, pengawasan kepatuhan, serta penyediaan kemudahan pembayaran menggunakan aplikasi digital yang mendukung optimalisasi penerimaan pajak dan peningkatan kualitas pelayanan kepada masyarakat. | D11: UU No. 1 Tahun 2022 | F11: AKUNTANSI DAN PELAPORAN KEUANGAN | G11: Instansi Pemerintah Lainnya | H11: Data Pajak | I11: ID Billing | J11: Terbatas | K11: Terdapat | L11: Harian | M11: Coretax | N11: Pusat | O11: Pusat | P11: Website | Q11: coretaxdjp.pajak.go.id | R11: Secara Online | S11: Informasi | T11: 2025 | U11: Aktif | V11: Tidak | W11: Tidak Terintegrasi | X11: Tidak Terintegrasi | Y11: Tidak Terintegrasi | Z11: Bagian Perencanaan dan Keuangan | AA11: BKAD | AB11: VERRYNOVYANDI SADIKIN, SE., MM | AC11: 895327038135 | AD11: setdakab.bdg@gmail.com | AE11: - | AF11: Harian
A12: 10 | B12: Layanan Pajak Daerah | C12: Pajak daerah yang ada digunakan untuk membiayai semua kepentingan umum. Termasuk untuk membuka lapangan kerja baru, sehingga terjadi pemerataan pendapatan agar kesenjangan ekonomi antara yang kaya dan miskin tidak terlalu menonjol. Pajak daerah diharapkan dapat meningkatkan pemerataan di setiap daerah. | D12: Undang-Undang Nomor 28 Tahun 2009 tentang Pajak Daerah dan Retribusi Daerah (UU PDRD) | F12: AKUNTANSI DAN PELAPORAN KEUANGAN | G12: Instansi Pemerintah Lainnya | H12: Data Pajak Daerah | I12: Data Rekap Pajak Daerah | J12: Terbatas | K12: Tidak terdapat | L12: Harian | M12: E-SPTPD | N12: Pihak Ke 3 | O12: Kab. Bandung | P12: Website dan Mobile | Q12: https://e-sptpd.bandungkab.go.id/ | R12: Secara Online | S12: Informasi | T12: 2019 | U12: Aktif | V12: Tidak | W12: Tidak Terintegrasi | X12: Tidak Terintegrasi | Y12: Tidak Terintegrasi | Z12: Bagian Perencanaan dan Keuangan | AA12: Setda, Bapenda | AB12: VERRYNOVYANDI SADIKIN, SE., MM | AC12: 895327038135 | AD12: setdakab.bdg@gmail.com | AE12: - | AF12: Harian
